Workbook

Sheet Summary
A1: LogiPlan AI｜2026 物流财务演示数据
A2: 虚构求职作品集数据｜Budget 2026 V1｜Actual 截至 2026-08｜Forecast 2026-08 V1｜报告币种 CNY
A4: 年度 Budget 物流总成本 | F4: Latest Outlook 物流总成本 | K4: 全年不利差异 | P4: Cost Saving 9—12 月节省
A5: =SUMIF(Monthly_Summary!$A$5:$A$52,"BUDGET",Monthly_Summary!$I$5:$I$52) -> 16197762 | F5: =SUMIF(Monthly_Summary!$A$5:$A$52,"LATEST_OUTLOOK",Monthly_Summary!$I$5:$I$52) -> 18327463 | K5: =F5-A5 -> 2129701 | P5: =SUMIF(Monthly_Summary!$A$5:$A$52,"FORECAST",Monthly_Summary!$I$5:$I$52)-SUMIF(Monthly_Summary!$A$5:$A$52,"SCENARIO_COST_SAVING",Monthly_Summary!$I$5:$I$52) -> 168354.42
A9: 核心结论：2026 年 8 月英国为最大单月不利异常。促销拉动订单量，同时德国仓至英国的空运和 Carrier C 份额上升；五因素中结构影响最大、量影响其次。Cost Saving 仅在现有线路内调整，准时率约下降 0.19 个百分点并触发软提示，承运能力仍未验证。
A30: 月份 | B30: Budget | C30: Latest Outlook | E30: 因素 | F30: 8 月英国差异 | H30: 月份 | I30: Forecast | J30: Cost Saving | K30: 差异
A31: 1月 | B31: =Monthly_Summary!I5 -> 1194245 | C31: =Monthly_Summary!I41 -> 1193234.5 | E31: 量 | F31: =SUMIFS(Attribution!$G$5:$G$804,Attribution!$A$5:$A$804,"ACTUAL_VS_BUDGET",Attribution!$B$5:$B$804,DATE(2026,8,1),Attribution!$C$5:$C$804,"CHAIN",Attribution!$D$5:$D$804,"VOLUME",Attribution!$E$5:$E$804,"GB") -> 85239.184 | H31: 9月 | I31: =Monthly_Summary!I25 -> 1555201 | J31: =Monthly_Summary!I37 -> 1555201 | K31: =J31-I31 -> 0
A32: 2月 | B32: =Monthly_Summary!I6 -> 1174271.9 | C32: =Monthly_Summary!I42 -> 1187198.7 | E32: 结构 | F32: =SUMIFS(Attribution!$G$5:$G$804,Attribution!$A$5:$A$804,"ACTUAL_VS_BUDGET",Attribution!$B$5:$B$804,DATE(2026,8,1),Attribution!$C$5:$C$804,"CHAIN",Attribution!$D$5:$D$804,"MIX",Attribution!$E$5:$E$804,"GB") -> 324207.82 | H32: 10月 | I32: =Monthly_Summary!I26 -> 1665561.4 | J32: =Monthly_Summary!I38 -> 1631664.1 | K32: =J32-I32 -> -33897.34
A33: 3月 | B33: =Monthly_Summary!I7 -> 1244597 | C33: =Monthly_Summary!I43 -> 1276222.9 | E33: 效率 | F33: =SUMIFS(Attribution!$G$5:$G$804,Attribution!$A$5:$A$804,"ACTUAL_VS_BUDGET",Attribution!$B$5:$B$804,DATE(2026,8,1),Attribution!$C$5:$C$804,"CHAIN",Attribution!$D$5:$D$804,"EFFICIENCY",Attribution!$E$5:$E$804,"GB") -> 64558.279 | H33: 11月 | I33: =Monthly_Summary!I27 -> 1932682.4 | J33: =Monthly_Summary!I39 -> 1861844.7 | K33: =J33-I33 -> -70837.716
A34: 4月 | B34: =Monthly_Summary!I8 -> 1264916.9 | C34: =Monthly_Summary!I44 -> 1301423.8 | E34: 价 | F34: =SUMIFS(Attribution!$G$5:$G$804,Attribution!$A$5:$A$804,"ACTUAL_VS_BUDGET",Attribution!$B$5:$B$804,DATE(2026,8,1),Attribution!$C$5:$C$804,"CHAIN",Attribution!$D$5:$D$804,"PRICE",Attribution!$E$5:$E$804,"GB") -> 79960.157 | H34: 12月 | I34: =Monthly_Summary!I28 -> 2106647.8 | J34: =Monthly_Summary!I40 -> 2043028.5 | K34: =J34-I34 -> -63619.369
A35: 5月 | B35: =Monthly_Summary!I9 -> 1290786.6 | C35: =Monthly_Summary!I45 -> 1350799.6 | E35: 汇率 | F35: =SUMIFS(Attribution!$G$5:$G$804,Attribution!$A$5:$A$804,"ACTUAL_VS_BUDGET",Attribution!$B$5:$B$804,DATE(2026,8,1),Attribution!$C$5:$C$804,"CHAIN",Attribution!$D$5:$D$804,"FX",Attribution!$E$5:$E$804,"GB") -> 20508.78
A36: 6月 | B36: =Monthly_Summary!I10 -> 1311279.9 | C36: =Monthly_Summary!I46 -> 1388064.7
A37: 7月 | B37: =Monthly_Summary!I11 -> 1337669.9 | C37: =Monthly_Summary!I47 -> 1453534.1
A38: 8月 | B38: =Monthly_Summary!I12 -> 1296336.4 | C38: =Monthly_Summary!I48 -> 1916892
A39: 9月 | B39: =Monthly_Summary!I13 -> 1302117.7 | C39: =Monthly_Summary!I49 -> 1555201
A40: 10月 | B40: =Monthly_Summary!I14 -> 1402987.8 | C40: =Monthly_Summary!I50 -> 1665561.4
A41: 11月 | B41: =Monthly_Summary!I15 -> 1597075.6 | C41: =Monthly_Summary!I51 -> 1932682.4
A42: 12月 | B42: =Monthly_Summary!I16 -> 1781477.3 | C42: =Monthly_Summary!I52 -> 2106647.8

Sheet Assumptions
A1: 模型假设与版本边界
A2: 蓝色为冻结规则；黄色为本次虚构数据的演示参数。任何新业务定义应先进入 decisions.md。
A4: 类别 | B4: 项目 | C4: 取值 | D4: 说明
A5: 冻结规则 | B5: 事实粒度 | C5: month x destination_country x fulfillment_center x carrier x transport_mode | D5: 月 × 目的国 × 发货仓 × 承运商 × 运输方式
A6: 冻结规则 | B6: 报告币种 | C6: CNY | D6: 保留原币、币种和汇率字段
A7: 冻结规则 | B7: 最新结账月 | C7: 2026-08 | D7: 1—8 月 Actual；9—12 月 Forecast
A8: 冻结规则 | B8: 归因顺序 | C8: VOLUME → MIX → EFFICIENCY → PRICE → FX | D8: Shapley 32 个组合仅作后台参考
A9: 冻结规则 | B9: 变动成本范围 | C9: 6 类 | D9: 基础运费、燃油附加费、一线作业弹性人工、包装、退货物流、异常配送
A10: 冻结规则 | B10: 固定成本范围 | C10: 4 类 | D10: 仓租、一线作业基础人工、仓库管理人工、系统费用单独展示
A11: 冻结规则 | B11: 人工成本口径 | C11: D-092 | D11: 计件、加班和临时用工为变动成本；一线底薪及管理人工为固定成本
A12: 冻结规则 | B12: 订单—仓库关系 | C12: 单订单单发货仓 | D12: 仓内允许拆包并分配不同线路
A13: 冻结规则 | B13: 情景服务约束 | C13: 软提示 | D13: 允许用户保留极端情景；不作为硬阻断
A14: 冻结规则 | B14: 承运能力 | C14: MVP 未验证 | D14: 数学计算暂按无限容量，不代表供应商确认
A15: 演示参数 | B15: Growth Case | C15: 英国 9—12 月 +10% | D15: 各月相对自身 Forecast 独立调整，不复利
... A19: 技术规则 | B19: 高精度权威数据 | C19: Decimal / numeric(50,24) | D19: 工作簿公式用于审阅；JSON 保留高精度计算结果

Sheet Route_Master
A1: 有效履约线路主数据
A2: 只允许白名单线路；承运能力状态为 MVP 未验证。
A4: Route ID | B4: 目的国 | C4: 发货仓 | D4: 承运商 | E4: 运输方式 | F4: 启用日期 | G4: 停用日期 | H4: 容量状态 | I4: 目的国名称 | J4: 线路说明
A5: R_DE_DE_A_ROAD | B5: DE | C5: DE_FC | D5: CARRIER_A | E5: ROAD | F5: 46023 | H5: NOT_VALIDATED_MVP | I5: 德国 | J5: DE_FC → DE｜CARRIER_A｜ROAD
A6: R_DE_DE_B_ROAD | B6: DE | C6: DE_FC | D6: CARRIER_B | E6: ROAD | F6: 46023 | H6: NOT_VALIDATED_MVP | I6: 德国 | J6: DE_FC → DE｜CARRIER_B｜ROAD
A7: R_DE_FR_B_ROAD | B7: DE | C7: FR_FC | D7: CARRIER_B | E7: ROAD | F7: 46023 | H7: NOT_VALIDATED_MVP | I7: 德国 | J7: FR_FC → DE｜CARRIER_B｜ROAD
A8: R_FR_FR_A_ROAD | B8: FR | C8: FR_FC | D8: CARRIER_A | E8: ROAD | F8: 46023 | H8: NOT_VALIDATED_MVP | I8: 法国 | J8: FR_FC → FR｜CARRIER_A｜ROAD
A9: R_FR_FR_B_ROAD | B9: FR | C9: FR_FC | D9: CARRIER_B | E9: ROAD | F9: 46023 | H9: NOT_VALIDATED_MVP | I9: 法国 | J9: FR_FC → FR｜CARRIER_B｜ROAD
A10: R_GB_DE_A_ROAD | B10: GB | C10: DE_FC | D10: CARRIER_A | E10: ROAD | F10: 46023 | H10: NOT_VALIDATED_MVP | I10: 英国 | J10: DE_FC → GB｜CARRIER_A｜ROAD
A11: R_GB_DE_B_ROAD | B11: GB | C11: DE_FC | D11: CARRIER_B | E11: ROAD | F11: 46023 | H11: NOT_VALIDATED_MVP | I11: 英国 | J11: DE_FC → GB｜CARRIER_B｜ROAD
A12: R_GB_DE_B_AIR | B12: GB | C12: DE_FC | D12: CARRIER_B | E12: AIR | F12: 46023 | H12: NOT_VALIDATED_MVP | I12: 英国 | J12: DE_FC → GB｜CARRIER_B｜AIR
A13: R_GB_DE_C_AIR | B13: GB | C13: DE_FC | D13: CARRIER_C | E13: AIR | F13: 46023 | H13: NOT_VALIDATED_MVP | I13: 英国 | J13: DE_FC → GB｜CARRIER_C｜AIR
A14: R_GB_FR_B_AIR | B14: GB | C14: FR_FC | D14: CARRIER_B | E14: AIR | F14: 46023 | H14: NOT_VALIDATED_MVP | I14: 英国 | J14: FR_FC → GB｜CARRIER_B｜AIR

Sheet Model_Calc
A1: 线路驱动与公式计算
A2: 浅黄色列为输入；浅蓝色列为公式结果。工作簿公式用于审阅，权威高精度结果保存在生成 JSON。
A4: Version | B4: Type | C4: Scenario | D4: Month | E4: Route | F4: Destination | G4: FC | H4: Carrier | I4: Mode | J4: Total Orders | K4: Destination Share | L4: Warehouse Share | M4: Route Package Share | N4: Equivalent Orders | O4: Avg Packages/Order | P4: Packages | Q4: Avg Chargeable Weight kg | R4: Chargeable Weight kg | S4: Return Rate | T4: Return Packages | U4: Events/Package | V4: Billable Events | W4: Transport Currency | X4: Base Rate/kg | Y4: Fuel Basis | Z4: Fuel Rate/Unit | AA4: EUR/CNY | AB4: GBP/CNY | AC4: Transport FX | AD4: Base Freight Original | AE4: Fuel Original | AF4: Base Freight CNY | AG4: Fuel CNY | AH4: Variable Labor Currency | AI4: Variable Labor Unit Price | AJ4: Variable Labor FX | AK4: Variable Labor Original | AL4: Variable Labor CNY | AM4: Packaging Currency | AN4: Packaging Unit Price | AO4: Packaging FX | AP4: Packaging Original | AQ4: Packaging CNY | AR4: Return Currency | AS4: Return Unit Price | AT4: Return FX | AU4: Return Original | AV4: Return CNY | AW4: Exception Currency | AX4: Exception Unit Price | AY4: Exception FX | AZ4: Exception Original | BA4: Exception CNY | BB4: Variable Cost CNY | BC4: Expected On-time Rate | BD4: Event Note | BE4: Management Action Note | BF4: Scenario Note | BG4: Capacity Assumption
A5: BUDGET_2026_V1 | B5: BUDGET | D5: 46023 | E5: R_DE_DE_A_ROAD | F5: DE | G5: DE_FC | H5: CARRIER_A | I5: ROAD | J5: 14000 | K5: 0.42 | L5: 0.97 | M5: 0.6 | N5: =J5*K5*L5*M5 -> 3422.16 | O5: 1.05 | P5: =N5*O5 -> 3593.268 | Q5: 0.78 | R5: =P5*Q5 -> 2802.749 | S5: 0.05 | T5: =N5*S5 -> 171.108 | U5: 0.016 | V5: =P5*U5 -> 57.492288 | W5: EUR | X5: 2.2 | Y5: PERCENTAGE_OF_BASE_FREIGHT | Z5: 0.095 | AA5: 7.8 | AB5: 9 | AC5: =IF(W5="EUR",AA5,IF(W5="GBP",AB5,1)) -> 7.8 | AD5: =R5*X5 -> 6166.0479 | AE5: =IF(Y5="PERCENTAGE_OF_BASE_FREIGHT",AD5*Z5,IF(Y5="PER_CHARGEABLE_KG",R5*Z5,P5*Z5)) -> 585.77455 | AF5: =AD5*AC5 -> 48095.174 | AG5: =AE5*AC5 -> 4569.0415 | AH5: EUR | AI5: 1.18 | AJ5: =IF(AH5="EUR",AA5,IF(AH5="GBP",AB5,1)) -> 7.8 | AK5: =N5*AI5 -> 4038.1488 | AL5: =AK5*AJ5 -> 31497.561 | AM5: EUR | AN5: 0.42 | AO5: =IF(AM5="EUR",AA5,IF(AM5="GBP",AB5,1)) -> 7.8 | AP5: =P5*AN5 -> 1509.1726 | AQ5: =AP5*AO5 -> 11771.546 | AR5: EUR | AS5: 3.2 | AT5: =IF(AR5="EUR",AA5,IF(AR5="GBP",AB5,1)) -> 7.8 | AU5: =T5*AS5 -> 547.5456 | AV5: =AU5*AT5 -> 4270.8557 | AW5: EUR | AX5: 2.3 | AY5: =IF(AW5="EUR",AA5,IF(AW5="GBP",AB5,1)) -> 7.8 | AZ5: =V5*AX5 -> 132.23226 | BA5: =AZ5*AY5 -> 1031.4116 | BB5: =AF5+AG5+AL5+AQ5+AV5+BA5 -> 101235.59 | BC5: 0.965 | BG5: UNVERIFIED_UNLIMITED_FOR_MVP
A6: BUDGET_2026_V1 | B6: BUDGET | D6: 46023 | E6: R_DE_DE_B_ROAD | F6: DE | G6: DE_FC | H6: CARRIER_B | I6: ROAD | J6: 14000 | K6: 0.42 | L6: 0.97 | M6: 0.4 | N6: =J6*K6*L6*M6 -> 2281.44 | O6: 1.05 | P6: =N6*O6 -> 2395.512 | Q6: 0.8 | R6: =P6*Q6 -> 1916.4096 | S6: 0.05 | T6: =N6*S6 -> 114.072 | U6: 0.013 | V6: =P6*U6 -> 31.141656 | W6: EUR | X6: 2.75 | Y6: PER_CHARGEABLE_KG | Z6: 0.21 | AA6: 7.8 | AB6: 9 | AC6: =IF(W6="EUR",AA6,IF(W6="GBP",AB6,1)) -> 7.8 | AD6: =R6*X6 -> 5270.1264 | AE6: =IF(Y6="PERCENTAGE_OF_BASE_FREIGHT",AD6*Z6,IF(Y6="PER_CHARGEABLE_KG",R6*Z6,P6*Z6)) -> 402.44602 | AF6: =AD6*AC6 -> 41106.986 | AG6: =AE6*AC6 -> 3139.0789 | AH6: EUR | AI6: 1.18 | AJ6: =IF(AH6="EUR",AA6,IF(AH6="GBP",AB6,1)) -> 7.8 | AK6: =N6*AI6 -> 2692.0992 | AL6: =AK6*AJ6 -> 20998.374 | AM6: EUR | AN6: 0.42 | AO6: =IF(AM6="EUR",AA6,IF(AM6="GBP",AB6,1)) -> 7.8 | AP6: =P6*AN6 -> 1006.115 | AQ6: =AP6*AO6 -> 7847.6973 | AR6: EUR | AS6: 3.2 | AT6: =IF(AR6="EUR",AA6,IF(AR6="GBP",AB6,1)) -> 7.8 | AU6: =T6*AS6 -> 365.0304 | AV6: =AU6*AT6 -> 2847.2371 | AW6: EUR | AX6: 2.3 | AY6: =IF(AW6="EUR",AA6,IF(AW6="GBP",AB6,1)) -> 7.8 | AZ6: =V6*AX6 -> 71.625809 | BA6: =AZ6*AY6 -> 558.68131 | BB6: =AF6+AG6+AL6+AQ6+AV6+BA6 -> 76498.054 | BC6: 0.976 | BG6: UNVERIFIED_UNLIMITED_FOR_MVP
A7: BUDGET_2026_V1 | B7: BUDGET | D7: 46023 | E7: R_DE_FR_B_ROAD | F7: DE | G7: FR_FC | H7: CARRIER_B | I7: ROAD | J7: 14000 | K7: 0.42 | L7: 0.03 | M7: 1 | N7: =J7*K7*L7*M7 -> 176.4 | O7: 1.08 | P7: =N7*O7 -> 190.512 | Q7: 0.86 | R7: =P7*Q7 -> 163.84032 | S7: 0.05 | T7: =N7*S7 -> 8.82 | U7: 0.014 | V7: =P7*U7 -> 2.667168 | W7: EUR | X7: 3.3 | Y7: PER_CHARGEABLE_KG | Z7: 0.24 | AA7: 7.8 | AB7: 9 | AC7: =IF(W7="EUR",AA7,IF(W7="GBP",AB7,1)) -> 7.8 | AD7: =R7*X7 -> 540.67306 | AE7: =IF(Y7="PERCENTAGE_OF_BASE_FREIGHT",AD7*Z7,IF(Y7="PER_CHARGEABLE_KG",R7*Z7,P7*Z7)) -> 39.321677 | AF7: =AD7*AC7 -> 4217.2498 | AG7: =AE7*AC7 -> 306.70908 | AH7: EUR | AI7: 1.05 | AJ7: =IF(AH7="EUR",AA7,IF(AH7="GBP",AB7,1)) -> 7.8 | AK7: =N7*AI7 -> 185.22 | AL7: =AK7*AJ7 -> 1444.716 | AM7: EUR | AN7: 0.38 | AO7: =IF(AM7="EUR",AA7,IF(AM7="GBP",AB7,1)) -> 7.8 | AP7: =P7*AN7 -> 72.39456 | AQ7: =AP7*AO7 -> 564.67757 | AR7: EUR | AS7: 3.8 | AT7: =IF(AR7="EUR",AA7,IF(AR7="GBP",AB7,1)) -> 7.8 | AU7: =T7*AS7 -> 33.516 | AV7: =AU7*AT7 -> 261.4248 | AW7: EUR | AX7: 2.3 | AY7: =IF(AW7="EUR",AA7,IF(AW7="GBP",AB7,1)) -> 7.8 | AZ7: =V7*AX7 -> 6.1344864 | BA7: =AZ7*AY7 -> 47.848994 | BB7: =AF7+AG7+AL7+AQ7+AV7+BA7 -> 6842.6263 | BC7: 0.968 | BG7: UNVERIFIED_UNLIMITED_FOR_MVP
A8: BUDGET_2026_V1 | B8: BUDGET | D8: 46023 | E8: R_FR_FR_A_ROAD | F8: FR | G8: FR_FC | H8: CARRIER_A | I8: ROAD | J8: 14000 | K8: 0.32 | L8: 1 | M8: 0.35 | N8: =J8*K8*L8*M8 -> 1568 | O8: 1.06 | P8: =N8*O8 -> 1662.08 | Q8: 0.76 | R8: =P8*Q8 -> 1263.1808 | S8: 0.06 | T8: =N8*S8 -> 94.08 | U8: 0.017 | V8: =P8*U8 -> 28.25536 | W8: EUR | X8: 2.1 | Y8: PERCENTAGE_OF_BASE_FREIGHT | Z8: 0.09 | AA8: 7.8 | AB8: 9 | AC8: =IF(W8="EUR",AA8,IF(W8="GBP",AB8,1)) -> 7.8 | AD8: =R8*X8 -> 2652.6797 | AE8: =IF(Y8="PERCENTAGE_OF_BASE_FREIGHT",AD8*Z8,IF(Y8="PER_CHARGEABLE_KG",R8*Z8,P8*Z8)) -> 238.74117 | AF8: =AD8*AC8 -> 20690.902 | AG8: =AE8*AC8 -> 1862.1811 | AH8: EUR | AI8: 1.05 | AJ8: =IF(AH8="EUR",AA8,IF(AH8="GBP",AB8,1)) -> 7.8 | AK8: =N8*AI8 -> 1646.4 | AL8: =AK8*AJ8 -> 12841.92 | AM8: EUR | AN8: 0.38 | AO8: =IF(AM8="EUR",AA8,IF(AM8="GBP",AB8,1)) -> 7.8 | AP8: =P8*AN8 -> 631.5904 | AQ8: =AP8*AO8 -> 4926.4051 | AR8: EUR | AS8: 3 | AT8: =IF(AR8="EUR",AA8,IF(AR8="GBP",AB8,1)) -> 7.8 | AU8: =T8*AS8 -> 282.24 | AV8: =AU8*AT8 -> 2201.472 | AW8: EUR | AX8: 2.3 | AY8: =IF(AW8="EUR",AA8,IF(AW8="GBP",AB8,1)) -> 7.8 | AZ8: =V8*AX8 -> 64.987328 | BA8: =AZ8*AY8 -> 506.90116 | BB8: =AF8+AG8+AL8+AQ8+AV8+BA8 -> 43029.781 | BC8: 0.961 | BG8: UNVERIFIED_UNLIMITED_FOR_MVP
A9: BUDGET_2026_V1 | B9: BUDGET | D9: 46023 | E9: R_FR_FR_B_ROAD | F9: FR | G9: FR_FC | H9: CARRIER_B | I9: ROAD | J9: 14000 | K9: 0.32 | L9: 1 | M9: 0.65 | N9: =J9*K9*L9*M9 -> 2912 | O9: 1.06 | P9: =N9*O9 -> 3086.72 | Q9: 0.79 | R9: =P9*Q9 -> 2438.5088 | S9: 0.06 | T9: =N9*S9 -> 174.72 | U9: 0.014 | V9: =P9*U9 -> 43.21408 | W9: EUR | X9: 2.6 | Y9: PER_CHARGEABLE_KG | Z9: 0.2 | AA9: 7.8 | AB9: 9 | AC9: =IF(W9="EUR",AA9,IF(W9="GBP",AB9,1)) -> 7.8 | AD9: =R9*X9 -> 6340.1229 | AE9: =IF(Y9="PERCENTAGE_OF_BASE_FREIGHT",AD9*Z9,IF(Y9="PER_CHARGEABLE_KG",R9*Z9,P9*Z9)) -> 487.70176 | AF9: =AD9*AC9 -> 49452.958 | AG9: =AE9*AC9 -> 3804.0737 | AH9: EUR | AI9: 1.05 | AJ9: =IF(AH9="EUR",AA9,IF(AH9="GBP",AB9,1)) -> 7.8 | AK9: =N9*AI9 -> 3057.6 | AL9: =AK9*AJ9 -> 23849.28 | AM9: EUR | AN9: 0.38 | AO9: =IF(AM9="EUR",AA9,IF(AM9="GBP",AB9,1)) -> 7.8 | AP9: =P9*AN9 -> 1172.9536 | AQ9: =AP9*AO9 -> 9149.0381 | AR9: EUR | AS9: 3 | AT9: =IF(AR9="EUR",AA9,IF(AR9="GBP",AB9,1)) -> 7.8 | AU9: =T9*AS9 -> 524.16 | AV9: =AU9*AT9 -> 4088.448 | AW9: EUR | AX9: 2.3 | AY9: =IF(AW9="EUR",AA9,IF(AW9="GBP",AB9,1)) -> 7.8 | AZ9: =V9*AX9 -> 99.392384 | BA9: =AZ9*AY9 -> 775.2606 | BB9: =AF9+AG9+AL9+AQ9+AV9+BA9 -> 91119.059 | BC9: 0.973 | BG9: UNVERIFIED_UNLIMITED_FOR_MVP
A10: BUDGET_2026_V1 | B10: BUDGET | D10: 46023 | E10: R_GB_DE_A_ROAD | F10: GB | G10: DE_FC | H10: CARRIER_A | I10: ROAD | J10: 14000 | K10: 0.26 | L10: 0.96 | M10: 0.65 | N10: =J10*K10*L10*M10 -> 2271.36 | O10: 1.12 | P10: =N10*O10 -> 2543.9232 | Q10: 1.02 | R10: =P10*Q10 -> 2594.8017 | S10: 0.08 | T10: =N10*S10 -> 181.7088 | U10: 0.022 | V10: =P10*U10 -> 55.96631 | W10: GBP | X10: 4 | Y10: PERCENTAGE_OF_BASE_FREIGHT | Z10: 0.1 | AA10: 7.8 | AB10: 9 | AC10: =IF(W10="EUR",AA10,IF(W10="GBP",AB10,1)) -> 9 | AD10: =R10*X10 -> 10379.207 | AE10: =IF(Y10="PERCENTAGE_OF_BASE_FREIGHT",AD10*Z10,IF(Y10="PER_CHARGEABLE_KG",R10*Z10,P10*Z10)) -> 1037.9207 | AF10: =AD10*AC10 -> 93412.86 | AG10: =AE10*AC10 -> 9341.286 | AH10: EUR | AI10: 1.18 | AJ10: =IF(AH10="EUR",AA10,IF(AH10="GBP",AB10,1)) -> 7.8 | AK10: =N10*AI10 -> 2680.2048 | AL10: =AK10*AJ10 -> 20905.597 | AM10: EUR | AN10: 0.42 | AO10: =IF(AM10="EUR",AA10,IF(AM10="GBP",AB10,1)) -> 7.8 | AP10: =P10*AN10 -> 1068.4477 | AQ10: =AP10*AO10 -> 8333.8924 | AR10: GBP | AS10: 4.8 | AT10: =IF(AR10="EUR",AA10,IF(AR10="GBP",AB10,1)) -> 9 | AU10: =T10*AS10 -> 872.20224 | AV10: =AU10*AT10 -> 7849.8202 | AW10: GBP | AX10: 2.3 | AY10: =IF(AW10="EUR",AA10,IF(AW10="GBP",AB10,1)) -> 9 | AZ10: =V10*AX10 -> 128.72251 | BA10: =AZ10*AY10 -> 1158.5026 | BB10: =AF10+AG10+AL10+AQ10+AV10+BA10 -> 141001.96 | BC10: 0.93 | BG10: UNVERIFIED_UNLIMITED_FOR_MVP
A11: BUDGET_2026_V1 | B11: BUDGET | D11: 46023 | E11: R_GB_DE_B_ROAD | F11: GB | G11: DE_FC | H11: CARRIER_B | I11: ROAD | J11: 14000 | K11: 0.26 | L11: 0.96 | M11: 0.25 | N11: =J11*K11*L11*M11 -> 873.6 | O11: 1.12 | P11: =N11*O11 -> 978.432 | Q11: 1 | R11: =P11*Q11 -> 978.432 | S11: 0.08 | T11: =N11*S11 -> 69.888 | U11: 0.017 | V11: =P11*U11 -> 16.633344 | W11: GBP | X11: 4.7 | Y11: PER_CHARGEABLE_KG | Z11: 0.33 | AA11: 7.8 | AB11: 9 | AC11: =IF(W11="EUR",AA11,IF(W11="GBP",AB11,1)) -> 9 | AD11: =R11*X11 -> 4598.6304 | AE11: =IF(Y11="PERCENTAGE_OF_BASE_FREIGHT",AD11*Z11,IF(Y11="PER_CHARGEABLE_KG",R11*Z11,P11*Z11)) -> 322.88256 | AF11: =AD11*AC11 -> 41387.674 | AG11: =AE11*AC11 -> 2905.943 | AH11: EUR | AI11: 1.18 | AJ11: =IF(AH11="EUR",AA11,IF(AH11="GBP",AB11,1)) -> 7.8 | AK11: =N11*AI11 -> 1030.848 | AL11: =AK11*AJ11 -> 8040.6144 | AM11: EUR | AN11: 0.42 | AO11: =IF(AM11="EUR",AA11,IF(AM11="GBP",AB11,1)) -> 7.8 | AP11: =P11*AN11 -> 410.94144 | AQ11: =AP11*AO11 -> 3205.3432 | AR11: GBP | AS11: 4.8 | AT11: =IF(AR11="EUR",AA11,IF(AR11="GBP",AB11,1)) -> 9 | AU11: =T11*AS11 -> 335.4624 | AV11: =AU11*AT11 -> 3019.1616 | AW11: GBP | AX11: 2.3 | AY11: =IF(AW11="EUR",AA11,IF(AW11="GBP",AB11,1)) -> 9 | AZ11: =V11*AX11 -> 38.256691 | BA11: =AZ11*AY11 -> 344.31022 | BB11: =AF11+AG11+AL11+AQ11+AV11+BA11 -> 58903.046 | BC11: 0.95 | BG11: UNVERIFIED_UNLIMITED_FOR_MVP
A12: BUDGET_2026_V1 | B12: BUDGET | D12: 46023 | E12: R_GB_DE_B_AIR | F12: GB | G12: DE_FC | H12: CARRIER_B | I12: AIR | J12: 14000 | K12: 0.26 | L12: 0.96 | M12: 0.07 | N12: =J12*K12*L12*M12 -> 244.608 | O12: 1.12 | P12: =N12*O12 -> 273.96096 | Q12: 0.94 | R12: =P12*Q12 -> 257.5233 | S12: 0.08 | T12: =N12*S12 -> 19.56864 | U12: 0.013 | V12: =P12*U12 -> 3.5614925 | W12: GBP | X12: 6.2 | Y12: PERCENTAGE_OF_BASE_FREIGHT | Z12: 0.115 | AA12: 7.8 | AB12: 9 | AC12: =IF(W12="EUR",AA12,IF(W12="GBP",AB12,1)) -> 9 | AD12: =R12*X12 -> 1596.6445 | AE12: =IF(Y12="PERCENTAGE_OF_BASE_FREIGHT",AD12*Z12,IF(Y12="PER_CHARGEABLE_KG",R12*Z12,P12*Z12)) -> 183.61411 | AF12: =AD12*AC12 -> 14369.8 | AG12: =AE12*AC12 -> 1652.527 | AH12: EUR | AI12: 1.18 | AJ12: =IF(AH12="EUR",AA12,IF(AH12="GBP",AB12,1)) -> 7.8 | AK12: =N12*AI12 -> 288.63744 | AL12: =AK12*AJ12 -> 2251.372 | AM12: EUR | AN12: 0.42 | AO12: =IF(AM12="EUR",AA12,IF(AM12="GBP",AB12,1)) -> 7.8 | AP12: =P12*AN12 -> 115.0636 | AQ12: =AP12*AO12 -> 897.4961 | AR12: GBP | AS12: 4.8 | AT12: =IF(AR12="EUR",AA12,IF(AR12="GBP",AB12,1)) -> 9 | AU12: =T12*AS12 -> 93.929472 | AV12: =AU12*AT12 -> 845.36525 | AW12: GBP | AX12: 2.8 | AY12: =IF(AW12="EUR",AA12,IF(AW12="GBP",AB12,1)) -> 9 | AZ12: =V12*AX12 -> 9.9721789 | BA12: =AZ12*AY12 -> 89.74961 | BB12: =AF12+AG12+AL12+AQ12+AV12+BA12 -> 20106.31 | BC12: 0.974 | BG12: UNVERIFIED_UNLIMITED_FOR_MVP
A13: BUDGET_2026_V1 | B13: BUDGET | D13: 46023 | E13: R_GB_DE_C_AIR | F13: GB | G13: DE_FC | H13: CARRIER_C | I13: AIR | J13: 14000 | K13: 0.26 | L13: 0.96 | M13: 0.03 | N13: =J13*K13*L13*M13 -> 104.832 | O13: 1.12 | P13: =N13*O13 -> 117.41184 | Q13: 0.92 | R13: =P13*Q13 -> 108.01889 | S13: 0.08 | T13: =N13*S13 -> 8.38656 | U13: 0.009 | V13: =P13*U13 -> 1.0567066 | W13: GBP | X13: 7.5 | Y13: PER_CHARGEABLE_KG | Z13: 0.58 | AA13: 7.8 | AB13: 9 | AC13: =IF(W13="EUR",AA13,IF(W13="GBP",AB13,1)) -> 9 | AD13: =R13*X13 -> 810.1417 | AE13: =IF(Y13="PERCENTAGE_OF_BASE_FREIGHT",AD13*Z13,IF(Y13="PER_CHARGEABLE_KG",R13*Z13,P13*Z13)) -> 62.650958 | AF13: =AD13*AC13 -> 7291.2753 | AG13: =AE13*AC13 -> 563.85862 | AH13: EUR | AI13: 1.18 | AJ13: =IF(AH13="EUR",AA13,IF(AH13="GBP",AB13,1)) -> 7.8 | AK13: =N13*AI13 -> 123.70176 | AL13: =AK13*AJ13 -> 964.87373 | AM13: EUR | AN13: 0.42 | AO13: =IF(AM13="EUR",AA13,IF(AM13="GBP",AB13,1)) -> 7.8 | AP13: =P13*AN13 -> 49.312973 | AQ13: =AP13*AO13 -> 384.64119 | AR13: GBP | AS13: 4.8 | AT13: =IF(AR13="EUR",AA13,IF(AR13="GBP",AB13,1)) -> 9 | AU13: =T13*AS13 -> 40.255488 | AV13: =AU13*AT13 -> 362.29939 | AW13: GBP | AX13: 3.6 | AY13: =IF(AW13="EUR",AA13,IF(AW13="GBP",AB13,1)) -> 9 | AZ13: =V13*AX13 -> 3.8041436 | BA13: =AZ13*AY13 -> 34.237293 | BB13: =AF13+AG13+AL13+AQ13+AV13+BA13 -> 9601.1855 | BC13: 0.988 | BG13: UNVERIFIED_UNLIMITED_FOR_MVP
A14: BUDGET_2026_V1 | B14: BUDGET | D14: 46023 | E14: R_GB_FR_B_AIR | F14: GB | G14: FR_FC | H14: CARRIER_B | I14: AIR | J14: 14000 | K14: 0.26 | L14: 0.04 | M14: 1 | N14: =J14*K14*L14*M14 -> 145.6 | O14: 1.15 | P14: =N14*O14 -> 167.44 | Q14: 0.9 | R14: =P14*Q14 -> 150.696 | S14: 0.08 | T14: =N14*S14 -> 11.648 | U14: 0.012 | V14: =P14*U14 -> 2.00928 | W14: EUR | X14: 6.7 | Y14: PERCENTAGE_OF_BASE_FREIGHT | Z14: 0.105 | AA14: 7.8 | AB14: 9 | AC14: =IF(W14="EUR",AA14,IF(W14="GBP",AB14,1)) -> 7.8 | AD14: =R14*X14 -> 1009.6632 | AE14: =IF(Y14="PERCENTAGE_OF_BASE_FREIGHT",AD14*Z14,IF(Y14="PER_CHARGEABLE_KG",R14*Z14,P14*Z14)) -> 106.01464 | AF14: =AD14*AC14 -> 7875.373 | AG14: =AE14*AC14 -> 826.91416 | AH14: EUR | AI14: 1.05 | AJ14: =IF(AH14="EUR",AA14,IF(AH14="GBP",AB14,1)) -> 7.8 | AK14: =N14*AI14 -> 152.88 | AL14: =AK14*AJ14 -> 1192.464 | AM14: EUR | AN14: 0.38 | AO14: =IF(AM14="EUR",AA14,IF(AM14="GBP",AB14,1)) -> 7.8 | AP14: =P14*AN14 -> 63.6272 | AQ14: =AP14*AO14 -> 496.29216 | AR14: EUR | AS14: 5.2 | AT14: =IF(AR14="EUR",AA14,IF(AR14="GBP",AB14,1)) -> 7.8 | AU14: =T14*AS14 -> 60.5696 | AV14: =AU14*AT14 -> 472.44288 | AW14: EUR | AX14: 2.8 | AY14: =IF(AW14="EUR",AA14,IF(AW14="GBP",AB14,1)) -> 7.8 | AZ14: =V14*AX14 -> 5.625984 | BA14: =AZ14*AY14 -> 43.882675 | BB14: =AF14+AG14+AL14+AQ14+AV14+BA14 -> 10907.369 | BC14: 0.971 | BG14: UNVERIFIED_UNLIMITED_FOR_MVP
A15: BUDGET_2026_V1 | B15: BUDGET | D15: 46054 | E15: R_DE_DE_A_ROAD | F15: DE | G15: DE_FC | H15: CARRIER_A | I15: ROAD | J15: 13500 | K15: 0.42 | L15: 0.97 | M15: 0.6 | N15: =J15*K15*L15*M15 -> 3299.94 | O15: 1.05 | P15: =N15*O15 -> 3464.937 | Q15: 0.78 | R15: =P15*Q15 -> 2702.6509 | S15: 0.05 | T15: =N15*S15 -> 164.997 | U15: 0.016 | V15: =P15*U15 -> 55.438992 | W15: EUR | X15: 2.2 | Y15: PERCENTAGE_OF_BASE_FREIGHT | Z15: 0.095 | AA15: 7.8 | AB15: 9 | AC15: =IF(W15="EUR",AA15,IF(W15="GBP",AB15,1)) -> 7.8 | AD15: =R15*X15 -> 5945.8319 | AE15: =IF(Y15="PERCENTAGE_OF_BASE_FREIGHT",AD15*Z15,IF(Y15="PER_CHARGEABLE_KG",R15*Z15,P15*Z15)) -> 564.85403 | AF15: =AD15*AC15 -> 46377.489 | AG15: =AE15*AC15 -> 4405.8614 | AH15: EUR | AI15: 1.18 | AJ15: =IF(AH15="EUR",AA15,IF(AH15="GBP",AB15,1)) -> 7.8 | AK15: =N15*AI15 -> 3893.9292 | AL15: =AK15*AJ15 -> 30372.648 | AM15: EUR | AN15: 0.42 | AO15: =IF(AM15="EUR",AA15,IF(AM15="GBP",AB15,1)) -> 7.8 | AP15: =P15*AN15 -> 1455.2735 | AQ15: =AP15*AO15 -> 11351.134 | AR15: EUR | AS15: 3.2 | AT15: =IF(AR15="EUR",AA15,IF(AR15="GBP",AB15,1)) -> 7.8 | AU15: =T15*AS15 -> 527.9904 | AV15: =AU15*AT15 -> 4118.3251 | AW15: EUR | AX15: 2.3 | AY15: =IF(AW15="EUR",AA15,IF(AW15="GBP",AB15,1)) -> 7.8 | AZ15: =V15*AX15 -> 127.50968 | BA15: =AZ15*AY15 -> 994.57552 | BB15: =AF15+AG15+AL15+AQ15+AV15+BA15 -> 97620.032 | BC15: 0.965 | BG15: UNVERIFIED_UNLIMITED_FOR_MVP
A16: BUDGET_2026_V1 | B16: BUDGET | D16: 46054 | E16: R_DE_DE_B_ROAD | F16: DE | G16: DE_FC | H16: CARRIER_B | I16: ROAD | J16: 13500 | K16: 0.42 | L16: 0.97 | M16: 0.4 | N16: =J16*K16*L16*M16 -> 2199.96 | O16: 1.05 | P16: =N16*O16 -> 2309.958 | Q16: 0.8 | R16: =P16*Q16 -> 1847.9664 | S16: 0.05 | T16: =N16*S16 -> 109.998 | U16: 0.013 | V16: =P16*U16 -> 30.029454 | W16: EUR | X16: 2.75 | Y16: PER_CHARGEABLE_KG | Z16: 0.21 | AA16: 7.8 | AB16: 9 | AC16: =IF(W16="EUR",AA16,IF(W16="GBP",AB16,1)) -> 7.8 | AD16: =R16*X16 -> 5081.9076 | AE16: =IF(Y16="PERCENTAGE_OF_BASE_FREIGHT",AD16*Z16,IF(Y16="PER_CHARGEABLE_KG",R16*Z16,P16*Z16)) -> 388.07294 | AF16: =AD16*AC16 -> 39638.879 | AG16: =AE16*AC16 -> 3026.969 | AH16: EUR | AI16: 1.18 | AJ16: =IF(AH16="EUR",AA16,IF(AH16="GBP",AB16,1)) -> 7.8 | AK16: =N16*AI16 -> 2595.9528 | AL16: =AK16*AJ16 -> 20248.432 | AM16: EUR | AN16: 0.42 | AO16: =IF(AM16="EUR",AA16,IF(AM16="GBP",AB16,1)) -> 7.8 | AP16: =P16*AN16 -> 970.18236 | AQ16: =AP16*AO16 -> 7567.4224 | AR16: EUR | AS16: 3.2 | AT16: =IF(AR16="EUR",AA16,IF(AR16="GBP",AB16,1)) -> 7.8 | AU16: =T16*AS16 -> 351.9936 | AV16: =AU16*AT16 -> 2745.5501 | AW16: EUR | AX16: 2.3 | AY16: =IF(AW16="EUR",AA16,IF(AW16="GBP",AB16,1)) -> 7.8 | AZ16: =V16*AX16 -> 69.067744 | BA16: =AZ16*AY16 -> 538.7284 | BB16: =AF16+AG16+AL16+AQ16+AV16+BA16 -> 73765.981 | BC16: 0.976 | BG16: UNVERIFIED_UNLIMITED_FOR_MVP
... A74: BUDGET_2026_V1 | B74: BUDGET | D74: 46204 | E74: R_GB_FR_B_AIR | F74: GB | G74: FR_FC | H74: CARRIER_B | I74: AIR | J74: 17000 | K74: 0.3 | L74: 0.04 | M74: 1 | N74: =J74*K74*L74*M74 -> 204 | O74: 1.15 | P74: =N74*O74 -> 234.6 | Q74: 0.9 | R74: =P74*Q74 -> 211.14 | S74: 0.08 | T74: =N74*S74 -> 16.32 | U74: 0.012 | V74: =P74*U74 -> 2.8152 | W74: EUR | X74: 6.7 | Y74: PERCENTAGE_OF_BASE_FREIGHT | Z74: 0.105 | AA74: 7.8 | AB74: 9 | AC74: =IF(W74="EUR",AA74,IF(W74="GBP",AB74,1)) -> 7.8 | AD74: =R74*X74 -> 1414.638 | AE74: =IF(Y74="PERCENTAGE_OF_BASE_FREIGHT",AD74*Z74,IF(Y74="PER_CHARGEABLE_KG",R74*Z74,P74*Z74)) -> 148.53699 | AF74: =AD74*AC74 -> 11034.176 | AG74: =AE74*AC74 -> 1158.5885 | AH74: EUR | AI74: 1.05 | AJ74: =IF(AH74="EUR",AA74,IF(AH74="GBP",AB74,1)) -> 7.8 | AK74: =N74*AI74 -> 214.2 | AL74: =AK74*AJ74 -> 1670.76 | AM74: EUR | AN74: 0.38 | AO74: =IF(AM74="EUR",AA74,IF(AM74="GBP",AB74,1)) -> 7.8 | AP74: =P74*AN74 -> 89.148 | AQ74: =AP74*AO74 -> 695.3544 | AR74: EUR | AS74: 5.2 | AT74: =IF(AR74="EUR",AA74,IF(AR74="GBP",AB74,1)) -> 7.8 | AU74: =T74*AS74 -> 84.864 | AV74: =AU74*AT74 -> 661.9392 | AW74: EUR | AX74: 2.8 | AY74: =IF(AW74="EUR",AA74,IF(AW74="GBP",AB74,1)) -> 7.8 | AZ74: =V74*AX74 -> 7.88256 | BA74: =AZ74*AY74 -> 61.483968 | BB74: =AF74+AG74+AL74+AQ74+AV74+BA74 -> 15282.302 | BC74: 0.971 | BG74: UNVERIFIED_UNLIMITED_FOR_MVP
A75: BUDGET_2026_V1 | B75: BUDGET | D75: 46235 | E75: R_DE_DE_A_ROAD | F75: DE | G75: DE_FC | H75: CARRIER_A | I75: ROAD | J75: 16000 | K75: 0.38 | L75: 0.97 | M75: 0.6 | N75: =J75*K75*L75*M75 -> 3538.56 | O75: 1.05 | P75: =N75*O75 -> 3715.488 | Q75: 0.78 | R75: =P75*Q75 -> 2898.0806 | S75: 0.05 | T75: =N75*S75 -> 176.928 | U75: 0.016 | V75: =P75*U75 -> 59.447808 | W75: EUR | X75: 2.2 | Y75: PERCENTAGE_OF_BASE_FREIGHT | Z75: 0.095 | AA75: 7.8 | AB75: 9 | AC75: =IF(W75="EUR",AA75,IF(W75="GBP",AB75,1)) -> 7.8 | AD75: =R75*X75 -> 6375.7774 | AE75: =IF(Y75="PERCENTAGE_OF_BASE_FREIGHT",AD75*Z75,IF(Y75="PER_CHARGEABLE_KG",R75*Z75,P75*Z75)) -> 605.69885 | AF75: =AD75*AC75 -> 49731.064 | AG75: =AE75*AC75 -> 4724.4511 | AH75: EUR | AI75: 1.18 | AJ75: =IF(AH75="EUR",AA75,IF(AH75="GBP",AB75,1)) -> 7.8 | AK75: =N75*AI75 -> 4175.5008 | AL75: =AK75*AJ75 -> 32568.906 | AM75: EUR | AN75: 0.42 | AO75: =IF(AM75="EUR",AA75,IF(AM75="GBP",AB75,1)) -> 7.8 | AP75: =P75*AN75 -> 1560.505 | AQ75: =AP75*AO75 -> 12171.939 | AR75: EUR | AS75: 3.2 | AT75: =IF(AR75="EUR",AA75,IF(AR75="GBP",AB75,1)) -> 7.8 | AU75: =T75*AS75 -> 566.1696 | AV75: =AU75*AT75 -> 4416.1229 | AW75: EUR | AX75: 2.3 | AY75: =IF(AW75="EUR",AA75,IF(AW75="GBP",AB75,1)) -> 7.8 | AZ75: =V75*AX75 -> 136.72996 | BA75: =AZ75*AY75 -> 1066.4937 | BB75: =AF75+AG75+AL75+AQ75+AV75+BA75 -> 104678.98 | BC75: 0.965 | BD75: UK promotion | BG75: UNVERIFIED_UNLIMITED_FOR_MVP
A76: BUDGET_2026_V1 | B76: BUDGET | D76: 46235 | E76: R_DE_DE_B_ROAD | F76: DE | G76: DE_FC | H76: CARRIER_B | I76: ROAD | J76: 16000 | K76: 0.38 | L76: 0.97 | M76: 0.4 | N76: =J76*K76*L76*M76 -> 2359.04 | O76: 1.05 | P76: =N76*O76 -> 2476.992 | Q76: 0.8 | R76: =P76*Q76 -> 1981.5936 | S76: 0.05 | T76: =N76*S76 -> 117.952 | U76: 0.013 | V76: =P76*U76 -> 32.200896 | W76: EUR | X76: 2.75 | Y76: PER_CHARGEABLE_KG | Z76: 0.21 | AA76: 7.8 | AB76: 9 | AC76: =IF(W76="EUR",AA76,IF(W76="GBP",AB76,1)) -> 7.8 | AD76: =R76*X76 -> 5449.3824 | AE76: =IF(Y76="PERCENTAGE_OF_BASE_FREIGHT",AD76*Z76,IF(Y76="PER_CHARGEABLE_KG",R76*Z76,P76*Z76)) -> 416.13466 | AF76: =AD76*AC76 -> 42505.183 | AG76: =AE76*AC76 -> 3245.8503 | AH76: EUR | AI76: 1.18 | AJ76: =IF(AH76="EUR",AA76,IF(AH76="GBP",AB76,1)) -> 7.8 | AK76: =N76*AI76 -> 2783.6672 | AL76: =AK76*AJ76 -> 21712.604 | AM76: EUR | AN76: 0.42 | AO76: =IF(AM76="EUR",AA76,IF(AM76="GBP",AB76,1)) -> 7.8 | AP76: =P76*AN76 -> 1040.3366 | AQ76: =AP76*AO76 -> 8114.6258 | AR76: EUR | AS76: 3.2 | AT76: =IF(AR76="EUR",AA76,IF(AR76="GBP",AB76,1)) -> 7.8 | AU76: =T76*AS76 -> 377.4464 | AV76: =AU76*AT76 -> 2944.0819 | AW76: EUR | AX76: 2.3 | AY76: =IF(AW76="EUR",AA76,IF(AW76="GBP",AB76,1)) -> 7.8 | AZ76: =V76*AX76 -> 74.062061 | BA76: =AZ76*AY76 -> 577.68407 | BB76: =AF76+AG76+AL76+AQ76+AV76+BA76 -> 79100.029 | BC76: 0.976 | BD76: UK promotion | BG76: UNVERIFIED_UNLIMITED_FOR_MVP
A77: BUDGET_2026_V1 | B77: BUDGET | D77: 46235 | E77: R_DE_FR_B_ROAD | F77: DE | G77: FR_FC | H77: CARRIER_B | I77: ROAD | J77: 16000 | K77: 0.38 | L77: 0.03 | M77: 1 | N77: =J77*K77*L77*M77 -> 182.4 | O77: 1.08 | P77: =N77*O77 -> 196.992 | Q77: 0.86 | R77: =P77*Q77 -> 169.41312 | S77: 0.05 | T77: =N77*S77 -> 9.12 | U77: 0.014 | V77: =P77*U77 -> 2.757888 | W77: EUR | X77: 3.3 | Y77: PER_CHARGEABLE_KG | Z77: 0.24 | AA77: 7.8 | AB77: 9 | AC77: =IF(W77="EUR",AA77,IF(W77="GBP",AB77,1)) -> 7.8 | AD77: =R77*X77 -> 559.0633 | AE77: =IF(Y77="PERCENTAGE_OF_BASE_FREIGHT",AD77*Z77,IF(Y77="PER_CHARGEABLE_KG",R77*Z77,P77*Z77)) -> 40.659149 | AF77: =AD77*AC77 -> 4360.6937 | AG77: =AE77*AC77 -> 317.14136 | AH77: EUR | AI77: 1.05 | AJ77: =IF(AH77="EUR",AA77,IF(AH77="GBP",AB77,1)) -> 7.8 | AK77: =N77*AI77 -> 191.52 | AL77: =AK77*AJ77 -> 1493.856 | AM77: EUR | AN77: 0.38 | AO77: =IF(AM77="EUR",AA77,IF(AM77="GBP",AB77,1)) -> 7.8 | AP77: =P77*AN77 -> 74.85696 | AQ77: =AP77*AO77 -> 583.88429 | AR77: EUR | AS77: 3.8 | AT77: =IF(AR77="EUR",AA77,IF(AR77="GBP",AB77,1)) -> 7.8 | AU77: =T77*AS77 -> 34.656 | AV77: =AU77*AT77 -> 270.3168 | AW77: EUR | AX77: 2.3 | AY77: =IF(AW77="EUR",AA77,IF(AW77="GBP",AB77,1)) -> 7.8 | AZ77: =V77*AX77 -> 6.3431424 | BA77: =AZ77*AY77 -> 49.476511 | BB77: =AF77+AG77+AL77+AQ77+AV77+BA77 -> 7075.3687 | BC77: 0.968 | BD77: UK promotion | BG77: UNVERIFIED_UNLIMITED_FOR_MVP
A78: BUDGET_2026_V1 | B78: BUDGET | D78: 46235 | E78: R_FR_FR_A_ROAD | F78: FR | G78: FR_FC | H78: CARRIER_A | I78: ROAD | J78: 16000 | K78: 0.32 | L78: 1 | M78: 0.35 | N78: =J78*K78*L78*M78 -> 1792 | O78: 1.06 | P78: =N78*O78 -> 1899.52 | Q78: 0.76 | R78: =P78*Q78 -> 1443.6352 | S78: 0.06 | T78: =N78*S78 -> 107.52 | U78: 0.017 | V78: =P78*U78 -> 32.29184 | W78: EUR | X78: 2.1 | Y78: PERCENTAGE_OF_BASE_FREIGHT | Z78: 0.09 | AA78: 7.8 | AB78: 9 | AC78: =IF(W78="EUR",AA78,IF(W78="GBP",AB78,1)) -> 7.8 | AD78: =R78*X78 -> 3031.6339 | AE78: =IF(Y78="PERCENTAGE_OF_BASE_FREIGHT",AD78*Z78,IF(Y78="PER_CHARGEABLE_KG",R78*Z78,P78*Z78)) -> 272.84705 | AF78: =AD78*AC78 -> 23646.745 | AG78: =AE78*AC78 -> 2128.207 | AH78: EUR | AI78: 1.05 | AJ78: =IF(AH78="EUR",AA78,IF(AH78="GBP",AB78,1)) -> 7.8 | AK78: =N78*AI78 -> 1881.6 | AL78: =AK78*AJ78 -> 14676.48 | AM78: EUR | AN78: 0.38 | AO78: =IF(AM78="EUR",AA78,IF(AM78="GBP",AB78,1)) -> 7.8 | AP78: =P78*AN78 -> 721.8176 | AQ78: =AP78*AO78 -> 5630.1773 | AR78: EUR | AS78: 3 | AT78: =IF(AR78="EUR",AA78,IF(AR78="GBP",AB78,1)) -> 7.8 | AU78: =T78*AS78 -> 322.56 | AV78: =AU78*AT78 -> 2515.968 | AW78: EUR | AX78: 2.3 | AY78: =IF(AW78="EUR",AA78,IF(AW78="GBP",AB78,1)) -> 7.8 | AZ78: =V78*AX78 -> 74.271232 | BA78: =AZ78*AY78 -> 579.31561 | BB78: =AF78+AG78+AL78+AQ78+AV78+BA78 -> 49176.892 | BC78: 0.961 | BD78: UK promotion | BG78: UNVERIFIED_UNLIMITED_FOR_MVP
A79: BUDGET_2026_V1 | B79: BUDGET | D79: 46235 | E79: R_FR_FR_B_ROAD | F79: FR | G79: FR_FC | H79: CARRIER_B | I79: ROAD | J79: 16000 | K79: 0.32 | L79: 1 | M79: 0.65 | N79: =J79*K79*L79*M79 -> 3328 | O79: 1.06 | P79: =N79*O79 -> 3527.68 | Q79: 0.79 | R79: =P79*Q79 -> 2786.8672 | S79: 0.06 | T79: =N79*S79 -> 199.68 | U79: 0.014 | V79: =P79*U79 -> 49.38752 | W79: EUR | X79: 2.6 | Y79: PER_CHARGEABLE_KG | Z79: 0.2 | AA79: 7.8 | AB79: 9 | AC79: =IF(W79="EUR",AA79,IF(W79="GBP",AB79,1)) -> 7.8 | AD79: =R79*X79 -> 7245.8547 | AE79: =IF(Y79="PERCENTAGE_OF_BASE_FREIGHT",AD79*Z79,IF(Y79="PER_CHARGEABLE_KG",R79*Z79,P79*Z79)) -> 557.37344 | AF79: =AD79*AC79 -> 56517.667 | AG79: =AE79*AC79 -> 4347.5128 | AH79: EUR | AI79: 1.05 | AJ79: =IF(AH79="EUR",AA79,IF(AH79="GBP",AB79,1)) -> 7.8 | AK79: =N79*AI79 -> 3494.4 | AL79: =AK79*AJ79 -> 27256.32 | AM79: EUR | AN79: 0.38 | AO79: =IF(AM79="EUR",AA79,IF(AM79="GBP",AB79,1)) -> 7.8 | AP79: =P79*AN79 -> 1340.5184 | AQ79: =AP79*AO79 -> 10456.044 | AR79: EUR | AS79: 3 | AT79: =IF(AR79="EUR",AA79,IF(AR79="GBP",AB79,1)) -> 7.8 | AU79: =T79*AS79 -> 599.04 | AV79: =AU79*AT79 -> 4672.512 | AW79: EUR | AX79: 2.3 | AY79: =IF(AW79="EUR",AA79,IF(AW79="GBP",AB79,1)) -> 7.8 | AZ79: =V79*AX79 -> 113.5913 | BA79: =AZ79*AY79 -> 886.01211 | BB79: =AF79+AG79+AL79+AQ79+AV79+BA79 -> 104136.07 | BC79: 0.973 | BD79: UK promotion | BG79: UNVERIFIED_UNLIMITED_FOR_MVP
A80: BUDGET_2026_V1 | B80: BUDGET | D80: 46235 | E80: R_GB_DE_A_ROAD | F80: GB | G80: DE_FC | H80: CARRIER_A | I80: ROAD | J80: 16000 | K80: 0.3 | L80: 0.96 | M80: 0.65 | N80: =J80*K80*L80*M80 -> 2995.2 | O80: 1.12 | P80: =N80*O80 -> 3354.624 | Q80: 1.02 | R80: =P80*Q80 -> 3421.7165 | S80: 0.08 | T80: =N80*S80 -> 239.616 | U80: 0.022 | V80: =P80*U80 -> 73.801728 | W80: GBP | X80: 4 | Y80: PERCENTAGE_OF_BASE_FREIGHT | Z80: 0.1 | AA80: 7.8 | AB80: 9 | AC80: =IF(W80="EUR",AA80,IF(W80="GBP",AB80,1)) -> 9 | AD80: =R80*X80 -> 13686.866 | AE80: =IF(Y80="PERCENTAGE_OF_BASE_FREIGHT",AD80*Z80,IF(Y80="PER_CHARGEABLE_KG",R80*Z80,P80*Z80)) -> 1368.6866 | AF80: =AD80*AC80 -> 123181.79 | AG80: =AE80*AC80 -> 12318.179 | AH80: EUR | AI80: 1.18 | AJ80: =IF(AH80="EUR",AA80,IF(AH80="GBP",AB80,1)) -> 7.8 | AK80: =N80*AI80 -> 3534.336 | AL80: =AK80*AJ80 -> 27567.821 | AM80: EUR | AN80: 0.42 | AO80: =IF(AM80="EUR",AA80,IF(AM80="GBP",AB80,1)) -> 7.8 | AP80: =P80*AN80 -> 1408.9421 | AQ80: =AP80*AO80 -> 10989.748 | AR80: GBP | AS80: 4.8 | AT80: =IF(AR80="EUR",AA80,IF(AR80="GBP",AB80,1)) -> 9 | AU80: =T80*AS80 -> 1150.1568 | AV80: =AU80*AT80 -> 10351.411 | AW80: GBP | AX80: 2.3 | AY80: =IF(AW80="EUR",AA80,IF(AW80="GBP",AB80,1)) -> 9 | AZ80: =V80*AX80 -> 169.74397 | BA80: =AZ80*AY80 -> 1527.6958 | BB80: =AF80+AG80+AL80+AQ80+AV80+BA80 -> 185936.65 | BC80: 0.93 | BD80: UK promotion | BG80: UNVERIFIED_UNLIMITED_FOR_MVP
A81: BUDGET_2026_V1 | B81: BUDGET | D81: 46235 | E81: R_GB_DE_B_ROAD | F81: GB | G81: DE_FC | H81: CARRIER_B | I81: ROAD | J81: 16000 | K81: 0.3 | L81: 0.96 | M81: 0.25 | N81: =J81*K81*L81*M81 -> 1152 | O81: 1.12 | P81: =N81*O81 -> 1290.24 | Q81: 1 | R81: =P81*Q81 -> 1290.24 | S81: 0.08 | T81: =N81*S81 -> 92.16 | U81: 0.017 | V81: =P81*U81 -> 21.93408 | W81: GBP | X81: 4.7 | Y81: PER_CHARGEABLE_KG | Z81: 0.33 | AA81: 7.8 | AB81: 9 | AC81: =IF(W81="EUR",AA81,IF(W81="GBP",AB81,1)) -> 9 | AD81: =R81*X81 -> 6064.128 | AE81: =IF(Y81="PERCENTAGE_OF_BASE_FREIGHT",AD81*Z81,IF(Y81="PER_CHARGEABLE_KG",R81*Z81,P81*Z81)) -> 425.7792 | AF81: =AD81*AC81 -> 54577.152 | AG81: =AE81*AC81 -> 3832.0128 | AH81: EUR | AI81: 1.18 | AJ81: =IF(AH81="EUR",AA81,IF(AH81="GBP",AB81,1)) -> 7.8 | AK81: =N81*AI81 -> 1359.36 | AL81: =AK81*AJ81 -> 10603.008 | AM81: EUR | AN81: 0.42 | AO81: =IF(AM81="EUR",AA81,IF(AM81="GBP",AB81,1)) -> 7.8 | AP81: =P81*AN81 -> 541.9008 | AQ81: =AP81*AO81 -> 4226.8262 | AR81: GBP | AS81: 4.8 | AT81: =IF(AR81="EUR",AA81,IF(AR81="GBP",AB81,1)) -> 9 | AU81: =T81*AS81 -> 442.368 | AV81: =AU81*AT81 -> 3981.312 | AW81: GBP | AX81: 2.3 | AY81: =IF(AW81="EUR",AA81,IF(AW81="GBP",AB81,1)) -> 9 | AZ81: =V81*AX81 -> 50.448384 | BA81: =AZ81*AY81 -> 454.03546 | BB81: =AF81+AG81+AL81+AQ81+AV81+BA81 -> 77674.346 | BC81: 0.95 | BD81: UK promotion | BG81: UNVERIFIED_UNLIMITED_FOR_MVP
A82: BUDGET_2026_V1 | B82: BUDGET | D82: 46235 | E82: R_GB_DE_B_AIR | F82: GB | G82: DE_FC | H82: CARRIER_B | I82: AIR | J82: 16000 | K82: 0.3 | L82: 0.96 | M82: 0.07 | N82: =J82*K82*L82*M82 -> 322.56 | O82: 1.12 | P82: =N82*O82 -> 361.2672 | Q82: 0.94 | R82: =P82*Q82 -> 339.59117 | S82: 0.08 | T82: =N82*S82 -> 25.8048 | U82: 0.013 | V82: =P82*U82 -> 4.6964736 | W82: GBP | X82: 6.2 | Y82: PERCENTAGE_OF_BASE_FREIGHT | Z82: 0.115 | AA82: 7.8 | AB82: 9 | AC82: =IF(W82="EUR",AA82,IF(W82="GBP",AB82,1)) -> 9 | AD82: =R82*X82 -> 2105.4652 | AE82: =IF(Y82="PERCENTAGE_OF_BASE_FREIGHT",AD82*Z82,IF(Y82="PER_CHARGEABLE_KG",R82*Z82,P82*Z82)) -> 242.1285 | AF82: =AD82*AC82 -> 18949.187 | AG82: =AE82*AC82 -> 2179.1565 | AH82: EUR | AI82: 1.18 | AJ82: =IF(AH82="EUR",AA82,IF(AH82="GBP",AB82,1)) -> 7.8 | AK82: =N82*AI82 -> 380.6208 | AL82: =AK82*AJ82 -> 2968.8422 | AM82: EUR | AN82: 0.42 | AO82: =IF(AM82="EUR",AA82,IF(AM82="GBP",AB82,1)) -> 7.8 | AP82: =P82*AN82 -> 151.73222 | AQ82: =AP82*AO82 -> 1183.5113 | AR82: GBP | AS82: 4.8 | AT82: =IF(AR82="EUR",AA82,IF(AR82="GBP",AB82,1)) -> 9 | AU82: =T82*AS82 -> 123.86304 | AV82: =AU82*AT82 -> 1114.7674 | AW82: GBP | AX82: 2.8 | AY82: =IF(AW82="EUR",AA82,IF(AW82="GBP",AB82,1)) -> 9 | AZ82: =V82*AX82 -> 13.150126 | BA82: =AZ82*AY82 -> 118.35113 | BB82: =AF82+AG82+AL82+AQ82+AV82+BA82 -> 26513.816 | BC82: 0.974 | BD82: UK promotion | BG82: UNVERIFIED_UNLIMITED_FOR_MVP
A83: BUDGET_2026_V1 | B83: BUDGET | D83: 46235 | E83: R_GB_DE_C_AIR | F83: GB | G83: DE_FC | H83: CARRIER_C | I83: AIR | J83: 16000 | K83: 0.3 | L83: 0.96 | M83: 0.03 | N83: =J83*K83*L83*M83 -> 138.24 | O83: 1.12 | P83: =N83*O83 -> 154.8288 | Q83: 0.92 | R83: =P83*Q83 -> 142.4425 | S83: 0.08 | T83: =N83*S83 -> 11.0592 | U83: 0.009 | V83: =P83*U83 -> 1.3934592 | W83: GBP | X83: 7.5 | Y83: PER_CHARGEABLE_KG | Z83: 0.58 | AA83: 7.8 | AB83: 9 | AC83: =IF(W83="EUR",AA83,IF(W83="GBP",AB83,1)) -> 9 | AD83: =R83*X83 -> 1068.3187 | AE83: =IF(Y83="PERCENTAGE_OF_BASE_FREIGHT",AD83*Z83,IF(Y83="PER_CHARGEABLE_KG",R83*Z83,P83*Z83)) -> 82.616648 | AF83: =AD83*AC83 -> 9614.8685 | AG83: =AE83*AC83 -> 743.54983 | AH83: EUR | AI83: 1.18 | AJ83: =IF(AH83="EUR",AA83,IF(AH83="GBP",AB83,1)) -> 7.8 | AK83: =N83*AI83 -> 163.1232 | AL83: =AK83*AJ83 -> 1272.361 | AM83: EUR | AN83: 0.42 | AO83: =IF(AM83="EUR",AA83,IF(AM83="GBP",AB83,1)) -> 7.8 | AP83: =P83*AN83 -> 65.028096 | AQ83: =AP83*AO83 -> 507.21915 | AR83: GBP | AS83: 4.8 | AT83: =IF(AR83="EUR",AA83,IF(AR83="GBP",AB83,1)) -> 9 | AU83: =T83*AS83 -> 53.08416 | AV83: =AU83*AT83 -> 477.75744 | AW83: GBP | AX83: 3.6 | AY83: =IF(AW83="EUR",AA83,IF(AW83="GBP",AB83,1)) -> 9 | AZ83: =V83*AX83 -> 5.0164531 | BA83: =AZ83*AY83 -> 45.148078 | BB83: =AF83+AG83+AL83+AQ83+AV83+BA83 -> 12660.904 | BC83: 0.988 | BD83: UK promotion | BG83: UNVERIFIED_UNLIMITED_FOR_MVP
A84: BUDGET_2026_V1 | B84: BUDGET | D84: 46235 | E84: R_GB_FR_B_AIR | F84: GB | G84: FR_FC | H84: CARRIER_B | I84: AIR | J84: 16000 | K84: 0.3 | L84: 0.04 | M84: 1 | N84: =J84*K84*L84*M84 -> 192 | O84: 1.15 | P84: =N84*O84 -> 220.8 | Q84: 0.9 | R84: =P84*Q84 -> 198.72 | S84: 0.08 | T84: =N84*S84 -> 15.36 | U84: 0.012 | V84: =P84*U84 -> 2.6496 | W84: EUR | X84: 6.7 | Y84: PERCENTAGE_OF_BASE_FREIGHT | Z84: 0.105 | AA84: 7.8 | AB84: 9 | AC84: =IF(W84="EUR",AA84,IF(W84="GBP",AB84,1)) -> 7.8 | AD84: =R84*X84 -> 1331.424 | AE84: =IF(Y84="PERCENTAGE_OF_BASE_FREIGHT",AD84*Z84,IF(Y84="PER_CHARGEABLE_KG",R84*Z84,P84*Z84)) -> 139.79952 | AF84: =AD84*AC84 -> 10385.107 | AG84: =AE84*AC84 -> 1090.4363 | AH84: EUR | AI84: 1.05 | AJ84: =IF(AH84="EUR",AA84,IF(AH84="GBP",AB84,1)) -> 7.8 | AK84: =N84*AI84 -> 201.6 | AL84: =AK84*AJ84 -> 1572.48 | AM84: EUR | AN84: 0.38 | AO84: =IF(AM84="EUR",AA84,IF(AM84="GBP",AB84,1)) -> 7.8 | AP84: =P84*AN84 -> 83.904 | AQ84: =AP84*AO84 -> 654.4512 | AR84: EUR | AS84: 5.2 | AT84: =IF(AR84="EUR",AA84,IF(AR84="GBP",AB84,1)) -> 7.8 | AU84: =T84*AS84 -> 79.872 | AV84: =AU84*AT84 -> 623.0016 | AW84: EUR | AX84: 2.8 | AY84: =IF(AW84="EUR",AA84,IF(AW84="GBP",AB84,1)) -> 7.8 | AZ84: =V84*AX84 -> 7.41888 | BA84: =AZ84*AY84 -> 57.867264 | BB84: =AF84+AG84+AL84+AQ84+AV84+BA84 -> 14383.344 | BC84: 0.971 | BD84: UK promotion | BG84: UNVERIFIED_UNLIMITED_FOR_MVP
A85: BUDGET_2026_V1 | B85: BUDGET | D85: 46266 | E85: R_DE_DE_A_ROAD | F85: DE | G85: DE_FC | H85: CARRIER_A | I85: ROAD | J85: 16000 | K85: 0.38 | L85: 0.97 | M85: 0.6 | N85: =J85*K85*L85*M85 -> 3538.56 | O85: 1.05 | P85: =N85*O85 -> 3715.488 | Q85: 0.78 | R85: =P85*Q85 -> 2898.0806 | S85: 0.05 | T85: =N85*S85 -> 176.928 | U85: 0.016 | V85: =P85*U85 -> 59.447808 | W85: EUR | X85: 2.2 | Y85: PERCENTAGE_OF_BASE_FREIGHT | Z85: 0.095 | AA85: 7.8 | AB85: 9 | AC85: =IF(W85="EUR",AA85,IF(W85="GBP",AB85,1)) -> 7.8 | AD85: =R85*X85 -> 6375.7774 | AE85: =IF(Y85="PERCENTAGE_OF_BASE_FREIGHT",AD85*Z85,IF(Y85="PER_CHARGEABLE_KG",R85*Z85,P85*Z85)) -> 605.69885 | AF85: =AD85*AC85 -> 49731.064 | AG85: =AE85*AC85 -> 4724.4511 | AH85: EUR | AI85: 1.18 | AJ85: =IF(AH85="EUR",AA85,IF(AH85="GBP",AB85,1)) -> 7.8 | AK85: =N85*AI85 -> 4175.5008 | AL85: =AK85*AJ85 -> 32568.906 | AM85: EUR | AN85: 0.42 | AO85: =IF(AM85="EUR",AA85,IF(AM85="GBP",AB85,1)) -> 7.8 | AP85: =P85*AN85 -> 1560.505 | AQ85: =AP85*AO85 -> 12171.939 | AR85: EUR | AS85: 3.2 | AT85: =IF(AR85="EUR",AA85,IF(AR85="GBP",AB85,1)) -> 7.8 | AU85: =T85*AS85 -> 566.1696 | AV85: =AU85*AT85 -> 4416.1229 | AW85: EUR | AX85: 2.3 | AY85: =IF(AW85="EUR",AA85,IF(AW85="GBP",AB85,1)) -> 7.8 | AZ85: =V85*AX85 -> 136.72996 | BA85: =AZ85*AY85 -> 1066.4937 | BB85: =AF85+AG85+AL85+AQ85+AV85+BA85 -> 104678.98 | BC85: 0.965 | BG85: UNVERIFIED_UNLIMITED_FOR_MVP
A86: BUDGET_2026_V1 | B86: BUDGET | D86: 46266 | E86: R_DE_DE_B_ROAD | F86: DE | G86: DE_FC | H86: CARRIER_B | I86: ROAD | J86: 16000 | K86: 0.38 | L86: 0.97 | M86: 0.4 | N86: =J86*K86*L86*M86 -> 2359.04 | O86: 1.05 | P86: =N86*O86 -> 2476.992 | Q86: 0.8 | R86: =P86*Q86 -> 1981.5936 | S86: 0.05 | T86: =N86*S86 -> 117.952 | U86: 0.013 | V86: =P86*U86 -> 32.200896 | W86: EUR | X86: 2.75 | Y86: PER_CHARGEABLE_KG | Z86: 0.21 | AA86: 7.8 | AB86: 9 | AC86: =IF(W86="EUR",AA86,IF(W86="GBP",AB86,1)) -> 7.8 | AD86: =R86*X86 -> 5449.3824 | AE86: =IF(Y86="PERCENTAGE_OF_BASE_FREIGHT",AD86*Z86,IF(Y86="PER_CHARGEABLE_KG",R86*Z86,P86*Z86)) -> 416.13466 | AF86: =AD86*AC86 -> 42505.183 | AG86: =AE86*AC86 -> 3245.8503 | AH86: EUR | AI86: 1.18 | AJ86: =IF(AH86="EUR",AA86,IF(AH86="GBP",AB86,1)) -> 7.8 | AK86: =N86*AI86 -> 2783.6672 | AL86: =AK86*AJ86 -> 21712.604 | AM86: EUR | AN86: 0.42 | AO86: =IF(AM86="EUR",AA86,IF(AM86="GBP",AB86,1)) -> 7.8 | AP86: =P86*AN86 -> 1040.3366 | AQ86: =AP86*AO86 -> 8114.6258 | AR86: EUR | AS86: 3.2 | AT86: =IF(AR86="EUR",AA86,IF(AR86="GBP",AB86,1)) -> 7.8 | AU86: =T86*AS86 -> 377.4464 | AV86: =AU86*AT86 -> 2944.0819 | AW86: EUR | AX86: 2.3 | AY86: =IF(AW86="EUR",AA86,IF(AW86="GBP",AB86,1)) -> 7.8 | AZ86: =V86*AX86 -> 74.062061 | BA86: =AZ86*AY86 -> 577.68407 | BB86: =AF86+AG86+AL86+AQ86+AV86+BA86 -> 79100.029 | BC86: 0.976 | BG86: UNVERIFIED_UNLIMITED_FOR_MVP
A87: BUDGET_2026_V1 | B87: BUDGET | D87: 46266 | E87: R_DE_FR_B_ROAD | F87: DE | G87: FR_FC | H87: CARRIER_B | I87: ROAD | J87: 16000 | K87: 0.38 | L87: 0.03 | M87: 1 | N87: =J87*K87*L87*M87 -> 182.4 | O87: 1.08 | P87: =N87*O87 -> 196.992 | Q87: 0.86 | R87: =P87*Q87 -> 169.41312 | S87: 0.05 | T87: =N87*S87 -> 9.12 | U87: 0.014 | V87: =P87*U87 -> 2.757888 | W87: EUR | X87: 3.3 | Y87: PER_CHARGEABLE_KG | Z87: 0.24 | AA87: 7.8 | AB87: 9 | AC87: =IF(W87="EUR",AA87,IF(W87="GBP",AB87,1)) -> 7.8 | AD87: =R87*X87 -> 559.0633 | AE87: =IF(Y87="PERCENTAGE_OF_BASE_FREIGHT",AD87*Z87,IF(Y87="PER_CHARGEABLE_KG",R87*Z87,P87*Z87)) -> 40.659149 | AF87: =AD87*AC87 -> 4360.6937 | AG87: =AE87*AC87 -> 317.14136 | AH87: EUR | AI87: 1.05 | AJ87: =IF(AH87="EUR",AA87,IF(AH87="GBP",AB87,1)) -> 7.8 | AK87: =N87*AI87 -> 191.52 | AL87: =AK87*AJ87 -> 1493.856 | AM87: EUR | AN87: 0.38 | AO87: =IF(AM87="EUR",AA87,IF(AM87="GBP",AB87,1)) -> 7.8 | AP87: =P87*AN87 -> 74.85696 | AQ87: =AP87*AO87 -> 583.88429 | AR87: EUR | AS87: 3.8 | AT87: =IF(AR87="EUR",AA87,IF(AR87="GBP",AB87,1)) -> 7.8 | AU87: =T87*AS87 -> 34.656 | AV87: =AU87*AT87 -> 270.3168 | AW87: EUR | AX87: 2.3 | AY87: =IF(AW87="EUR",AA87,IF(AW87="GBP",AB87,1)) -> 7.8 | AZ87: =V87*AX87 -> 6.3431424 | BA87: =AZ87*AY87 -> 49.476511 | BB87: =AF87+AG87+AL87+AQ87+AV87+BA87 -> 7075.3687 | BC87: 0.968 | BG87: UNVERIFIED_UNLIMITED_FOR_MVP
A88: BUDGET_2026_V1 | B88: BUDGET | D88: 46266 | E88: R_FR_FR_A_ROAD | F88: FR | G88: FR_FC | H88: CARRIER_A | I88: ROAD | J88: 16000 | K88: 0.31 | L88: 1 | M88: 0.35 | N88: =J88*K88*L88*M88 -> 1736 | O88: 1.06 | P88: =N88*O88 -> 1840.16 | Q88: 0.76 | R88: =P88*Q88 -> 1398.5216 | S88: 0.06 | T88: =N88*S88 -> 104.16 | U88: 0.017 | V88: =P88*U88 -> 31.28272 | W88: EUR | X88: 2.1 | Y88: PERCENTAGE_OF_BASE_FREIGHT | Z88: 0.09 | AA88: 7.8 | AB88: 9 | AC88: =IF(W88="EUR",AA88,IF(W88="GBP",AB88,1)) -> 7.8 | AD88: =R88*X88 -> 2936.8954 | AE88: =IF(Y88="PERCENTAGE_OF_BASE_FREIGHT",AD88*Z88,IF(Y88="PER_CHARGEABLE_KG",R88*Z88,P88*Z88)) -> 264.32058 | AF88: =AD88*AC88 -> 22907.784 | AG88: =AE88*AC88 -> 2061.7005 | AH88: EUR | AI88: 1.05 | AJ88: =IF(AH88="EUR",AA88,IF(AH88="GBP",AB88,1)) -> 7.8 | AK88: =N88*AI88 -> 1822.8 | AL88: =AK88*AJ88 -> 14217.84 | AM88: EUR | AN88: 0.38 | AO88: =IF(AM88="EUR",AA88,IF(AM88="GBP",AB88,1)) -> 7.8 | AP88: =P88*AN88 -> 699.2608 | AQ88: =AP88*AO88 -> 5454.2342 | AR88: EUR | AS88: 3 | AT88: =IF(AR88="EUR",AA88,IF(AR88="GBP",AB88,1)) -> 7.8 | AU88: =T88*AS88 -> 312.48 | AV88: =AU88*AT88 -> 2437.344 | AW88: EUR | AX88: 2.3 | AY88: =IF(AW88="EUR",AA88,IF(AW88="GBP",AB88,1)) -> 7.8 | AZ88: =V88*AX88 -> 71.950256 | BA88: =AZ88*AY88 -> 561.212 | BB88: =AF88+AG88+AL88+AQ88+AV88+BA88 -> 47640.115 | BC88: 0.961 | BG88: UNVERIFIED_UNLIMITED_FOR_MVP
A89: BUDGET_2026_V1 | B89: BUDGET | D89: 46266 | E89: R_FR_FR_B_ROAD | F89: FR | G89: FR_FC | H89: CARRIER_B | I89: ROAD | J89: 16000 | K89: 0.31 | L89: 1 | M89: 0.65 | N89: =J89*K89*L89*M89 -> 3224 | O89: 1.06 | P89: =N89*O89 -> 3417.44 | Q89: 0.79 | R89: =P89*Q89 -> 2699.7776 | S89: 0.06 | T89: =N89*S89 -> 193.44 | U89: 0.014 | V89: =P89*U89 -> 47.84416 | W89: EUR | X89: 2.6 | Y89: PER_CHARGEABLE_KG | Z89: 0.2 | AA89: 7.8 | AB89: 9 | AC89: =IF(W89="EUR",AA89,IF(W89="GBP",AB89,1)) -> 7.8 | AD89: =R89*X89 -> 7019.4218 | AE89: =IF(Y89="PERCENTAGE_OF_BASE_FREIGHT",AD89*Z89,IF(Y89="PER_CHARGEABLE_KG",R89*Z89,P89*Z89)) -> 539.95552 | AF89: =AD89*AC89 -> 54751.49 | AG89: =AE89*AC89 -> 4211.6531 | AH89: EUR | AI89: 1.05 | AJ89: =IF(AH89="EUR",AA89,IF(AH89="GBP",AB89,1)) -> 7.8 | AK89: =N89*AI89 -> 3385.2 | AL89: =AK89*AJ89 -> 26404.56 | AM89: EUR | AN89: 0.38 | AO89: =IF(AM89="EUR",AA89,IF(AM89="GBP",AB89,1)) -> 7.8 | AP89: =P89*AN89 -> 1298.6272 | AQ89: =AP89*AO89 -> 10129.292 | AR89: EUR | AS89: 3 | AT89: =IF(AR89="EUR",AA89,IF(AR89="GBP",AB89,1)) -> 7.8 | AU89: =T89*AS89 -> 580.32 | AV89: =AU89*AT89 -> 4526.496 | AW89: EUR | AX89: 2.3 | AY89: =IF(AW89="EUR",AA89,IF(AW89="GBP",AB89,1)) -> 7.8 | AZ89: =V89*AX89 -> 110.04157 | BA89: =AZ89*AY89 -> 858.32423 | BB89: =AF89+AG89+AL89+AQ89+AV89+BA89 -> 100881.82 | BC89: 0.973 | BG89: UNVERIFIED_UNLIMITED_FOR_MVP
A90: BUDGET_2026_V1 | B90: BUDGET | D90: 46266 | E90: R_GB_DE_A_ROAD | F90: GB | G90: DE_FC | H90: CARRIER_A | I90: ROAD | J90: 16000 | K90: 0.31 | L90: 0.96 | M90: 0.65 | N90: =J90*K90*L90*M90 -> 3095.04 | O90: 1.12 | P90: =N90*O90 -> 3466.4448 | Q90: 1.02 | R90: =P90*Q90 -> 3535.7737 | S90: 0.08 | T90: =N90*S90 -> 247.6032 | U90: 0.022 | V90: =P90*U90 -> 76.261786 | W90: GBP | X90: 4 | Y90: PERCENTAGE_OF_BASE_FREIGHT | Z90: 0.1 | AA90: 7.8 | AB90: 9 | AC90: =IF(W90="EUR",AA90,IF(W90="GBP",AB90,1)) -> 9 | AD90: =R90*X90 -> 14143.095 | AE90: =IF(Y90="PERCENTAGE_OF_BASE_FREIGHT",AD90*Z90,IF(Y90="PER_CHARGEABLE_KG",R90*Z90,P90*Z90)) -> 1414.3095 | AF90: =AD90*AC90 -> 127287.85 | AG90: =AE90*AC90 -> 12728.785 | AH90: EUR | AI90: 1.18 | AJ90: =IF(AH90="EUR",AA90,IF(AH90="GBP",AB90,1)) -> 7.8 | AK90: =N90*AI90 -> 3652.1472 | AL90: =AK90*AJ90 -> 28486.748 | AM90: EUR | AN90: 0.42 | AO90: =IF(AM90="EUR",AA90,IF(AM90="GBP",AB90,1)) -> 7.8 | AP90: =P90*AN90 -> 1455.9068 | AQ90: =AP90*AO90 -> 11356.073 | AR90: GBP | AS90: 4.8 | AT90: =IF(AR90="EUR",AA90,IF(AR90="GBP",AB90,1)) -> 9 | AU90: =T90*AS90 -> 1188.4954 | AV90: =AU90*AT90 -> 10696.458 | AW90: GBP | AX90: 2.3 | AY90: =IF(AW90="EUR",AA90,IF(AW90="GBP",AB90,1)) -> 9 | AZ90: =V90*AX90 -> 175.40211 | BA90: =AZ90*AY90 -> 1578.619 | BB90: =AF90+AG90+AL90+AQ90+AV90+BA90 -> 192134.54 | BC90: 0.93 | BG90: UNVERIFIED_UNLIMITED_FOR_MVP
A91: BUDGET_2026_V1 | B91: BUDGET | D91: 46266 | E91: R_GB_DE_B_ROAD | F91: GB | G91: DE_FC | H91: CARRIER_B | I91: ROAD | J91: 16000 | K91: 0.31 | L91: 0.96 | M91: 0.25 | N91: =J91*K91*L91*M91 -> 1190.4 | O91: 1.12 | P91: =N91*O91 -> 1333.248 | Q91: 1 | R91: =P91*Q91 -> 1333.248 | S91: 0.08 | T91: =N91*S91 -> 95.232 | U91: 0.017 | V91: =P91*U91 -> 22.665216 | W91: GBP | X91: 4.7 | Y91: PER_CHARGEABLE_KG | Z91: 0.33 | AA91: 7.8 | AB91: 9 | AC91: =IF(W91="EUR",AA91,IF(W91="GBP",AB91,1)) -> 9 | AD91: =R91*X91 -> 6266.2656 | AE91: =IF(Y91="PERCENTAGE_OF_BASE_FREIGHT",AD91*Z91,IF(Y91="PER_CHARGEABLE_KG",R91*Z91,P91*Z91)) -> 439.97184 | AF91: =AD91*AC91 -> 56396.39 | AG91: =AE91*AC91 -> 3959.7466 | AH91: EUR | AI91: 1.18 | AJ91: =IF(AH91="EUR",AA91,IF(AH91="GBP",AB91,1)) -> 7.8 | AK91: =N91*AI91 -> 1404.672 | AL91: =AK91*AJ91 -> 10956.442 | AM91: EUR | AN91: 0.42 | AO91: =IF(AM91="EUR",AA91,IF(AM91="GBP",AB91,1)) -> 7.8 | AP91: =P91*AN91 -> 559.96416 | AQ91: =AP91*AO91 -> 4367.7204 | AR91: GBP | AS91: 4.8 | AT91: =IF(AR91="EUR",AA91,IF(AR91="GBP",AB91,1)) -> 9 | AU91: =T91*AS91 -> 457.1136 | AV91: =AU91*AT91 -> 4114.0224 | AW91: GBP | AX91: 2.3 | AY91: =IF(AW91="EUR",AA91,IF(AW91="GBP",AB91,1)) -> 9 | AZ91: =V91*AX91 -> 52.129997 | BA91: =AZ91*AY91 -> 469.16997 | BB91: =AF91+AG91+AL91+AQ91+AV91+BA91 -> 80263.491 | BC91: 0.95 | BG91: UNVERIFIED_UNLIMITED_FOR_MVP
A92: BUDGET_2026_V1 | B92: BUDGET | D92: 46266 | E92: R_GB_DE_B_AIR | F92: GB | G92: DE_FC | H92: CARRIER_B | I92: AIR | J92: 16000 | K92: 0.31 | L92: 0.96 | M92: 0.07 | N92: =J92*K92*L92*M92 -> 333.312 | O92: 1.12 | P92: =N92*O92 -> 373.30944 | Q92: 0.94 | R92: =P92*Q92 -> 350.91087 | S92: 0.08 | T92: =N92*S92 -> 26.66496 | U92: 0.013 | V92: =P92*U92 -> 4.8530227 | W92: GBP | X92: 6.2 | Y92: PERCENTAGE_OF_BASE_FREIGHT | Z92: 0.115 | AA92: 7.8 | AB92: 9 | AC92: =IF(W92="EUR",AA92,IF(W92="GBP",AB92,1)) -> 9 | AD92: =R92*X92 -> 2175.6474 | AE92: =IF(Y92="PERCENTAGE_OF_BASE_FREIGHT",AD92*Z92,IF(Y92="PER_CHARGEABLE_KG",R92*Z92,P92*Z92)) -> 250.19945 | AF92: =AD92*AC92 -> 19580.827 | AG92: =AE92*AC92 -> 2251.7951 | AH92: EUR | AI92: 1.18 | AJ92: =IF(AH92="EUR",AA92,IF(AH92="GBP",AB92,1)) -> 7.8 | AK92: =N92*AI92 -> 393.30816 | AL92: =AK92*AJ92 -> 3067.8036 | AM92: EUR | AN92: 0.42 | AO92: =IF(AM92="EUR",AA92,IF(AM92="GBP",AB92,1)) -> 7.8 | AP92: =P92*AN92 -> 156.78996 | AQ92: =AP92*AO92 -> 1222.9617 | AR92: GBP | AS92: 4.8 | AT92: =IF(AR92="EUR",AA92,IF(AR92="GBP",AB92,1)) -> 9 | AU92: =T92*AS92 -> 127.99181 | AV92: =AU92*AT92 -> 1151.9263 | AW92: GBP | AX92: 2.8 | AY92: =IF(AW92="EUR",AA92,IF(AW92="GBP",AB92,1)) -> 9 | AZ92: =V92*AX92 -> 13.588464 | BA92: =AZ92*AY92 -> 122.29617 | BB92: =AF92+AG92+AL92+AQ92+AV92+BA92 -> 27397.61 | BC92: 0.974 | BG92: UNVERIFIED_UNLIMITED_FOR_MVP
A93: BUDGET_2026_V1 | B93: BUDGET | D93: 46266 | E93: R_GB_DE_C_AIR | F93: GB | G93: DE_FC | H93: CARRIER_C | I93: AIR | J93: 16000 | K93: 0.31 | L93: 0.96 | M93: 0.03 | N93: =J93*K93*L93*M93 -> 142.848 | O93: 1.12 | P93: =N93*O93 -> 159.98976 | Q93: 0.92 | R93: =P93*Q93 -> 147.19058 | S93: 0.08 | T93: =N93*S93 -> 11.42784 | U93: 0.009 | V93: =P93*U93 -> 1.4399078 | W93: GBP | X93: 7.5 | Y93: PER_CHARGEABLE_KG | Z93: 0.58 | AA93: 7.8 | AB93: 9 | AC93: =IF(W93="EUR",AA93,IF(W93="GBP",AB93,1)) -> 9 | AD93: =R93*X93 -> 1103.9293 | AE93: =IF(Y93="PERCENTAGE_OF_BASE_FREIGHT",AD93*Z93,IF(Y93="PER_CHARGEABLE_KG",R93*Z93,P93*Z93)) -> 85.370536 | AF93: =AD93*AC93 -> 9935.3641 | AG93: =AE93*AC93 -> 768.33482 | AH93: EUR | AI93: 1.18 | AJ93: =IF(AH93="EUR",AA93,IF(AH93="GBP",AB93,1)) -> 7.8 | AK93: =N93*AI93 -> 168.56064 | AL93: =AK93*AJ93 -> 1314.773 | AM93: EUR | AN93: 0.42 | AO93: =IF(AM93="EUR",AA93,IF(AM93="GBP",AB93,1)) -> 7.8 | AP93: =P93*AN93 -> 67.195699 | AQ93: =AP93*AO93 -> 524.12645 | AR93: GBP | AS93: 4.8 | AT93: =IF(AR93="EUR",AA93,IF(AR93="GBP",AB93,1)) -> 9 | AU93: =T93*AS93 -> 54.853632 | AV93: =AU93*AT93 -> 493.68269 | AW93: GBP | AX93: 3.6 | AY93: =IF(AW93="EUR",AA93,IF(AW93="GBP",AB93,1)) -> 9 | AZ93: =V93*AX93 -> 5.1836682 | BA93: =AZ93*AY93 -> 46.653014 | BB93: =AF93+AG93+AL93+AQ93+AV93+BA93 -> 13082.934 | BC93: 0.988 | BG93: UNVERIFIED_UNLIMITED_FOR_MVP
A94: BUDGET_2026_V1 | B94: BUDGET | D94: 46266 | E94: R_GB_FR_B_AIR | F94: GB | G94: FR_FC | H94: CARRIER_B | I94: AIR | J94: 16000 | K94: 0.31 | L94: 0.04 | M94: 1 | N94: =J94*K94*L94*M94 -> 198.4 | O94: 1.15 | P94: =N94*O94 -> 228.16 | Q94: 0.9 | R94: =P94*Q94 -> 205.344 | S94: 0.08 | T94: =N94*S94 -> 15.872 | U94: 0.012 | V94: =P94*U94 -> 2.73792 | W94: EUR | X94: 6.7 | Y94: PERCENTAGE_OF_BASE_FREIGHT | Z94: 0.105 | AA94: 7.8 | AB94: 9 | AC94: =IF(W94="EUR",AA94,IF(W94="GBP",AB94,1)) -> 7.8 | AD94: =R94*X94 -> 1375.8048 | AE94: =IF(Y94="PERCENTAGE_OF_BASE_FREIGHT",AD94*Z94,IF(Y94="PER_CHARGEABLE_KG",R94*Z94,P94*Z94)) -> 144.4595 | AF94: =AD94*AC94 -> 10731.277 | AG94: =AE94*AC94 -> 1126.7841 | AH94: EUR | AI94: 1.05 | AJ94: =IF(AH94="EUR",AA94,IF(AH94="GBP",AB94,1)) -> 7.8 | AK94: =N94*AI94 -> 208.32 | AL94: =AK94*AJ94 -> 1624.896 | AM94: EUR | AN94: 0.38 | AO94: =IF(AM94="EUR",AA94,IF(AM94="GBP",AB94,1)) -> 7.8 | AP94: =P94*AN94 -> 86.7008 | AQ94: =AP94*AO94 -> 676.26624 | AR94: EUR | AS94: 5.2 | AT94: =IF(AR94="EUR",AA94,IF(AR94="GBP",AB94,1)) -> 7.8 | AU94: =T94*AS94 -> 82.5344 | AV94: =AU94*AT94 -> 643.76832 | AW94: EUR | AX94: 2.8 | AY94: =IF(AW94="EUR",AA94,IF(AW94="GBP",AB94,1)) -> 7.8 | AZ94: =V94*AX94 -> 7.666176 | BA94: =AZ94*AY94 -> 59.796173 | BB94: =AF94+AG94+AL94+AQ94+AV94+BA94 -> 14862.788 | BC94: 0.971 | BG94: UNVERIFIED_UNLIMITED_FOR_MVP
A95: BUDGET_2026_V1 | B95: BUDGET | D95: 46296 | E95: R_DE_DE_A_ROAD | F95: DE | G95: DE_FC | H95: CARRIER_A | I95: ROAD | J95: 18000 | K95: 0.36 | L95: 0.97 | M95: 0.6 | N95: =J95*K95*L95*M95 -> 3771.36 | O95: 1.05 | P95: =N95*O95 -> 3959.928 | Q95: 0.7878 | R95: =P95*Q95 -> 3119.6313 | S95: 0.05 | T95: =N95*S95 -> 188.568 | U95: 0.016 | V95: =P95*U95 -> 63.358848 | W95: EUR | X95: 2.2 | Y95: PERCENTAGE_OF_BASE_FREIGHT | Z95: 0.095 | AA95: 7.8 | AB95: 9 | AC95: =IF(W95="EUR",AA95,IF(W95="GBP",AB95,1)) -> 7.8 | AD95: =R95*X95 -> 6863.1888 | AE95: =IF(Y95="PERCENTAGE_OF_BASE_FREIGHT",AD95*Z95,IF(Y95="PER_CHARGEABLE_KG",R95*Z95,P95*Z95)) -> 652.00294 | AF95: =AD95*AC95 -> 53532.873 | AG95: =AE95*AC95 -> 5085.6229 | AH95: EUR | AI95: 1.18 | AJ95: =IF(AH95="EUR",AA95,IF(AH95="GBP",AB95,1)) -> 7.8 | AK95: =N95*AI95 -> 4450.2048 | AL95: =AK95*AJ95 -> 34711.597 | AM95: EUR | AN95: 0.42 | AO95: =IF(AM95="EUR",AA95,IF(AM95="GBP",AB95,1)) -> 7.8 | AP95: =P95*AN95 -> 1663.1698 | AQ95: =AP95*AO95 -> 12972.724 | AR95: EUR | AS95: 3.2 | AT95: =IF(AR95="EUR",AA95,IF(AR95="GBP",AB95,1)) -> 7.8 | AU95: =T95*AS95 -> 603.4176 | AV95: =AU95*AT95 -> 4706.6573 | AW95: EUR | AX95: 2.3 | AY95: =IF(AW95="EUR",AA95,IF(AW95="GBP",AB95,1)) -> 7.8 | AZ95: =V95*AX95 -> 145.72535 | BA95: =AZ95*AY95 -> 1136.6577 | BB95: =AF95+AG95+AL95+AQ95+AV95+BA95 -> 112146.13 | BC95: 0.965 | BG95: UNVERIFIED_UNLIMITED_FOR_MVP
A96: BUDGET_2026_V1 | B96: BUDGET | D96: 46296 | E96: R_DE_DE_B_ROAD | F96: DE | G96: DE_FC | H96: CARRIER_B | I96: ROAD | J96: 18000 | K96: 0.36 | L96: 0.97 | M96: 0.4 | N96: =J96*K96*L96*M96 -> 2514.24 | O96: 1.05 | P96: =N96*O96 -> 2639.952 | Q96: 0.808 | R96: =P96*Q96 -> 2133.0812 | S96: 0.05 | T96: =N96*S96 -> 125.712 | U96: 0.013 | V96: =P96*U96 -> 34.319376 | W96: EUR | X96: 2.75 | Y96: PER_CHARGEABLE_KG | Z96: 0.21 | AA96: 7.8 | AB96: 9 | AC96: =IF(W96="EUR",AA96,IF(W96="GBP",AB96,1)) -> 7.8 | AD96: =R96*X96 -> 5865.9733 | AE96: =IF(Y96="PERCENTAGE_OF_BASE_FREIGHT",AD96*Z96,IF(Y96="PER_CHARGEABLE_KG",R96*Z96,P96*Z96)) -> 447.94706 | AF96: =AD96*AC96 -> 45754.592 | AG96: =AE96*AC96 -> 3493.987 | AH96: EUR | AI96: 1.18 | AJ96: =IF(AH96="EUR",AA96,IF(AH96="GBP",AB96,1)) -> 7.8 | AK96: =N96*AI96 -> 2966.8032 | AL96: =AK96*AJ96 -> 23141.065 | AM96: EUR | AN96: 0.42 | AO96: =IF(AM96="EUR",AA96,IF(AM96="GBP",AB96,1)) -> 7.8 | AP96: =P96*AN96 -> 1108.7798 | AQ96: =AP96*AO96 -> 8648.4828 | AR96: EUR | AS96: 3.2 | AT96: =IF(AR96="EUR",AA96,IF(AR96="GBP",AB96,1)) -> 7.8 | AU96: =T96*AS96 -> 402.2784 | AV96: =AU96*AT96 -> 3137.7715 | AW96: EUR | AX96: 2.3 | AY96: =IF(AW96="EUR",AA96,IF(AW96="GBP",AB96,1)) -> 7.8 | AZ96: =V96*AX96 -> 78.934565 | BA96: =AZ96*AY96 -> 615.68961 | BB96: =AF96+AG96+AL96+AQ96+AV96+BA96 -> 84791.588 | BC96: 0.976 | BG96: UNVERIFIED_UNLIMITED_FOR_MVP
... A194: ACTUAL_2026_08_CLOSE_V1 | B194: ACTUAL | D194: 46204 | E194: R_GB_FR_B_AIR | F194: GB | G194: FR_FC | H194: CARRIER_B | I194: AIR | J194: 18000 | K194: 0.33 | L194: 0.04 | M194: 1 | N194: =J194*K194*L194*M194 -> 237.6 | O194: 1.1569 | P194: =N194*O194 -> 274.87944 | Q194: 0.9045 | R194: =P194*Q194 -> 248.62845 | S194: 0.08 | T194: =N194*S194 -> 19.008 | U194: 0.01224 | V194: =P194*U194 -> 3.3645243 | W194: EUR | X194: 6.7938 | Y194: PERCENTAGE_OF_BASE_FREIGHT | Z194: 0.10647 | AA194: 7.91 | AB194: 9.18 | AC194: =IF(W194="EUR",AA194,IF(W194="GBP",AB194,1)) -> 7.91 | AD194: =R194*X194 -> 1689.132 | AE194: =IF(Y194="PERCENTAGE_OF_BASE_FREIGHT",AD194*Z194,IF(Y194="PER_CHARGEABLE_KG",R194*Z194,P194*Z194)) -> 179.84188 | AF194: =AD194*AC194 -> 13361.034 | AG194: =AE194*AC194 -> 1422.5493 | AH194: EUR | AI194: 1.0647 | AJ194: =IF(AH194="EUR",AA194,IF(AH194="GBP",AB194,1)) -> 7.91 | AK194: =N194*AI194 -> 252.97272 | AL194: =AK194*AJ194 -> 2001.0142 | AM194: EUR | AN194: 0.38532 | AO194: =IF(AM194="EUR",AA194,IF(AM194="GBP",AB194,1)) -> 7.91 | AP194: =P194*AN194 -> 105.91655 | AQ194: =AP194*AO194 -> 837.79988 | AR194: EUR | AS194: 5.2728 | AT194: =IF(AR194="EUR",AA194,IF(AR194="GBP",AB194,1)) -> 7.91 | AU194: =T194*AS194 -> 100.22538 | AV194: =AU194*AT194 -> 792.78277 | AW194: EUR | AX194: 2.8392 | AY194: =IF(AW194="EUR",AA194,IF(AW194="GBP",AB194,1)) -> 7.91 | AZ194: =V194*AX194 -> 9.5525575 | BA194: =AZ194*AY194 -> 75.56073 | BB194: =AF194+AG194+AL194+AQ194+AV194+BA194 -> 18490.741 | BC194: 0.968 | BG194: UNVERIFIED_UNLIMITED_FOR_MVP
A195: ACTUAL_2026_08_CLOSE_V1 | B195: ACTUAL | D195: 46235 | E195: R_DE_DE_A_ROAD | F195: DE | G195: DE_FC | H195: CARRIER_A | I195: ROAD | J195: 20300 | K195: 0.31 | L195: 0.97 | M195: 0.6 | N195: =J195*K195*L195*M195 -> 3662.526 | O195: 1.05 | P195: =N195*O195 -> 3845.6523 | Q195: 0.78 | R195: =P195*Q195 -> 2999.6088 | S195: 0.05 | T195: =N195*S195 -> 183.1263 | U195: 0.016 | V195: =P195*U195 -> 61.530437 | W195: EUR | X195: 2.2352 | Y195: PERCENTAGE_OF_BASE_FREIGHT | Z195: 0.09652 | AA195: 7.95 | AB195: 9.22 | AC195: =IF(W195="EUR",AA195,IF(W195="GBP",AB195,1)) -> 7.95 | AD195: =R195*X195 -> 6704.7256 | AE195: =IF(Y195="PERCENTAGE_OF_BASE_FREIGHT",AD195*Z195,IF(Y195="PER_CHARGEABLE_KG",R195*Z195,P195*Z195)) -> 647.14011 | AF195: =AD195*AC195 -> 53302.568 | AG195: =AE195*AC195 -> 5144.7639 | AH195: EUR | AI195: 1.3884759 | AJ195: =IF(AH195="EUR",AA195,IF(AH195="GBP",AB195,1)) -> 7.95 | AK195: =N195*AI195 -> 5085.3292 | AL195: =AK195*AJ195 -> 40428.367 | AM195: EUR | AN195: 0.42672 | AO195: =IF(AM195="EUR",AA195,IF(AM195="GBP",AB195,1)) -> 7.95 | AP195: =P195*AN195 -> 1641.0167 | AQ195: =AP195*AO195 -> 13046.083 | AR195: EUR | AS195: 3.2512 | AT195: =IF(AR195="EUR",AA195,IF(AR195="GBP",AB195,1)) -> 7.95 | AU195: =T195*AS195 -> 595.38023 | AV195: =AU195*AT195 -> 4733.2728 | AW195: EUR | AX195: 2.3368 | AY195: =IF(AW195="EUR",AA195,IF(AW195="GBP",AB195,1)) -> 7.95 | AZ195: =V195*AX195 -> 143.78432 | BA195: =AZ195*AY195 -> 1143.0854 | BB195: =AF195+AG195+AL195+AQ195+AV195+BA195 -> 117798.14 | BC195: 0.962 | BD195: UK promotion | BE195: 为维持促销期间履约时效，提高德国仓至英国的空运和 Carrier C 份额 | BG195: UNVERIFIED_UNLIMITED_FOR_MVP
A196: ACTUAL_2026_08_CLOSE_V1 | B196: ACTUAL | D196: 46235 | E196: R_DE_DE_B_ROAD | F196: DE | G196: DE_FC | H196: CARRIER_B | I196: ROAD | J196: 20300 | K196: 0.31 | L196: 0.97 | M196: 0.4 | N196: =J196*K196*L196*M196 -> 2441.684 | O196: 1.05 | P196: =N196*O196 -> 2563.7682 | Q196: 0.8 | R196: =P196*Q196 -> 2051.0146 | S196: 0.05 | T196: =N196*S196 -> 122.0842 | U196: 0.013 | V196: =P196*U196 -> 33.328987 | W196: EUR | X196: 2.794 | Y196: PER_CHARGEABLE_KG | Z196: 0.21336 | AA196: 7.95 | AB196: 9.22 | AC196: =IF(W196="EUR",AA196,IF(W196="GBP",AB196,1)) -> 7.95 | AD196: =R196*X196 -> 5730.5347 | AE196: =IF(Y196="PERCENTAGE_OF_BASE_FREIGHT",AD196*Z196,IF(Y196="PER_CHARGEABLE_KG",R196*Z196,P196*Z196)) -> 437.60447 | AF196: =AD196*AC196 -> 45557.751 | AG196: =AE196*AC196 -> 3478.9555 | AH196: EUR | AI196: 1.3884759 | AJ196: =IF(AH196="EUR",AA196,IF(AH196="GBP",AB196,1)) -> 7.95 | AK196: =N196*AI196 -> 3390.2194 | AL196: =AK196*AJ196 -> 26952.245 | AM196: EUR | AN196: 0.42672 | AO196: =IF(AM196="EUR",AA196,IF(AM196="GBP",AB196,1)) -> 7.95 | AP196: =P196*AN196 -> 1094.0112 | AQ196: =AP196*AO196 -> 8697.3888 | AR196: EUR | AS196: 3.2512 | AT196: =IF(AR196="EUR",AA196,IF(AR196="GBP",AB196,1)) -> 7.95 | AU196: =T196*AS196 -> 396.92015 | AV196: =AU196*AT196 -> 3155.5152 | AW196: EUR | AX196: 2.3368 | AY196: =IF(AW196="EUR",AA196,IF(AW196="GBP",AB196,1)) -> 7.95 | AZ196: =V196*AX196 -> 77.883176 | BA196: =AZ196*AY196 -> 619.17125 | BB196: =AF196+AG196+AL196+AQ196+AV196+BA196 -> 88461.026 | BC196: 0.973 | BD196: UK promotion | BE196: 为维持促销期间履约时效，提高德国仓至英国的空运和 Carrier C 份额 | BG196: UNVERIFIED_UNLIMITED_FOR_MVP
A197: ACTUAL_2026_08_CLOSE_V1 | B197: ACTUAL | D197: 46235 | E197: R_DE_FR_B_ROAD | F197: DE | G197: FR_FC | H197: CARRIER_B | I197: ROAD | J197: 20300 | K197: 0.31 | L197: 0.03 | M197: 1 | N197: =J197*K197*L197*M197 -> 188.79 | O197: 1.08 | P197: =N197*O197 -> 203.8932 | Q197: 0.86 | R197: =P197*Q197 -> 175.34815 | S197: 0.05 | T197: =N197*S197 -> 9.4395 | U197: 0.014 | V197: =P197*U197 -> 2.8545048 | W197: EUR | X197: 3.3528 | Y197: PER_CHARGEABLE_KG | Z197: 0.24384 | AA197: 7.95 | AB197: 9.22 | AC197: =IF(W197="EUR",AA197,IF(W197="GBP",AB197,1)) -> 7.95 | AD197: =R197*X197 -> 587.90728 | AE197: =IF(Y197="PERCENTAGE_OF_BASE_FREIGHT",AD197*Z197,IF(Y197="PER_CHARGEABLE_KG",R197*Z197,P197*Z197)) -> 42.756893 | AF197: =AD197*AC197 -> 4673.8629 | AG197: =AE197*AC197 -> 339.9173 | AH197: EUR | AI197: 1.0668 | AJ197: =IF(AH197="EUR",AA197,IF(AH197="GBP",AB197,1)) -> 7.95 | AK197: =N197*AI197 -> 201.40117 | AL197: =AK197*AJ197 -> 1601.1393 | AM197: EUR | AN197: 0.38608 | AO197: =IF(AM197="EUR",AA197,IF(AM197="GBP",AB197,1)) -> 7.95 | AP197: =P197*AN197 -> 78.719087 | AQ197: =AP197*AO197 -> 625.81674 | AR197: EUR | AS197: 3.8608 | AT197: =IF(AR197="EUR",AA197,IF(AR197="GBP",AB197,1)) -> 7.95 | AU197: =T197*AS197 -> 36.444022 | AV197: =AU197*AT197 -> 289.72997 | AW197: EUR | AX197: 2.3368 | AY197: =IF(AW197="EUR",AA197,IF(AW197="GBP",AB197,1)) -> 7.95 | AZ197: =V197*AX197 -> 6.6704068 | BA197: =AZ197*AY197 -> 53.029734 | BB197: =AF197+AG197+AL197+AQ197+AV197+BA197 -> 7583.496 | BC197: 0.965 | BD197: UK promotion | BE197: 为维持促销期间履约时效，提高德国仓至英国的空运和 Carrier C 份额 | BG197: UNVERIFIED_UNLIMITED_FOR_MVP
A198: ACTUAL_2026_08_CLOSE_V1 | B198: ACTUAL | D198: 46235 | E198: R_FR_FR_A_ROAD | F198: FR | G198: FR_FC | H198: CARRIER_A | I198: ROAD | J198: 20300 | K198: 0.25 | L198: 1 | M198: 0.35 | N198: =J198*K198*L198*M198 -> 1776.25 | O198: 1.06 | P198: =N198*O198 -> 1882.825 | Q198: 0.76 | R198: =P198*Q198 -> 1430.947 | S198: 0.06 | T198: =N198*S198 -> 106.575 | U198: 0.017 | V198: =P198*U198 -> 32.008025 | W198: EUR | X198: 2.1336 | Y198: PERCENTAGE_OF_BASE_FREIGHT | Z198: 0.09144 | AA198: 7.95 | AB198: 9.22 | AC198: =IF(W198="EUR",AA198,IF(W198="GBP",AB198,1)) -> 7.95 | AD198: =R198*X198 -> 3053.0685 | AE198: =IF(Y198="PERCENTAGE_OF_BASE_FREIGHT",AD198*Z198,IF(Y198="PER_CHARGEABLE_KG",R198*Z198,P198*Z198)) -> 279.17259 | AF198: =AD198*AC198 -> 24271.895 | AG198: =AE198*AC198 -> 2219.4221 | AH198: EUR | AI198: 1.0668 | AJ198: =IF(AH198="EUR",AA198,IF(AH198="GBP",AB198,1)) -> 7.95 | AK198: =N198*AI198 -> 1894.9035 | AL198: =AK198*AJ198 -> 15064.483 | AM198: EUR | AN198: 0.38608 | AO198: =IF(AM198="EUR",AA198,IF(AM198="GBP",AB198,1)) -> 7.95 | AP198: =P198*AN198 -> 726.92108 | AQ198: =AP198*AO198 -> 5779.0226 | AR198: EUR | AS198: 3.048 | AT198: =IF(AR198="EUR",AA198,IF(AR198="GBP",AB198,1)) -> 7.95 | AU198: =T198*AS198 -> 324.8406 | AV198: =AU198*AT198 -> 2582.4828 | AW198: EUR | AX198: 2.3368 | AY198: =IF(AW198="EUR",AA198,IF(AW198="GBP",AB198,1)) -> 7.95 | AZ198: =V198*AX198 -> 74.796353 | BA198: =AZ198*AY198 -> 594.631 | BB198: =AF198+AG198+AL198+AQ198+AV198+BA198 -> 50511.936 | BC198: 0.958 | BD198: UK promotion | BE198: 为维持促销期间履约时效，提高德国仓至英国的空运和 Carrier C 份额 | BG198: UNVERIFIED_UNLIMITED_FOR_MVP
A199: ACTUAL_2026_08_CLOSE_V1 | B199: ACTUAL | D199: 46235 | E199: R_FR_FR_B_ROAD | F199: FR | G199: FR_FC | H199: CARRIER_B | I199: ROAD | J199: 20300 | K199: 0.25 | L199: 1 | M199: 0.65 | N199: =J199*K199*L199*M199 -> 3298.75 | O199: 1.06 | P199: =N199*O199 -> 3496.675 | Q199: 0.79 | R199: =P199*Q199 -> 2762.3733 | S199: 0.06 | T199: =N199*S199 -> 197.925 | U199: 0.014 | V199: =P199*U199 -> 48.95345 | W199: EUR | X199: 2.6416 | Y199: PER_CHARGEABLE_KG | Z199: 0.2032 | AA199: 7.95 | AB199: 9.22 | AC199: =IF(W199="EUR",AA199,IF(W199="GBP",AB199,1)) -> 7.95 | AD199: =R199*X199 -> 7297.0852 | AE199: =IF(Y199="PERCENTAGE_OF_BASE_FREIGHT",AD199*Z199,IF(Y199="PER_CHARGEABLE_KG",R199*Z199,P199*Z199)) -> 561.31424 | AF199: =AD199*AC199 -> 58011.827 | AG199: =AE199*AC199 -> 4462.4482 | AH199: EUR | AI199: 1.0668 | AJ199: =IF(AH199="EUR",AA199,IF(AH199="GBP",AB199,1)) -> 7.95 | AK199: =N199*AI199 -> 3519.1065 | AL199: =AK199*AJ199 -> 27976.897 | AM199: EUR | AN199: 0.38608 | AO199: =IF(AM199="EUR",AA199,IF(AM199="GBP",AB199,1)) -> 7.95 | AP199: =P199*AN199 -> 1349.9963 | AQ199: =AP199*AO199 -> 10732.47 | AR199: EUR | AS199: 3.048 | AT199: =IF(AR199="EUR",AA199,IF(AR199="GBP",AB199,1)) -> 7.95 | AU199: =T199*AS199 -> 603.2754 | AV199: =AU199*AT199 -> 4796.0394 | AW199: EUR | AX199: 2.3368 | AY199: =IF(AW199="EUR",AA199,IF(AW199="GBP",AB199,1)) -> 7.95 | AZ199: =V199*AX199 -> 114.39442 | BA199: =AZ199*AY199 -> 909.43565 | BB199: =AF199+AG199+AL199+AQ199+AV199+BA199 -> 106889.12 | BC199: 0.97 | BD199: UK promotion | BE199: 为维持促销期间履约时效，提高德国仓至英国的空运和 Carrier C 份额 | BG199: UNVERIFIED_UNLIMITED_FOR_MVP
A200: ACTUAL_2026_08_CLOSE_V1 | B200: ACTUAL | D200: 46235 | E200: R_GB_DE_A_ROAD | F200: GB | G200: DE_FC | H200: CARRIER_A | I200: ROAD | J200: 20300 | K200: 0.44 | L200: 0.97 | M200: 0.22 | N200: =J200*K200*L200*M200 -> 1906.0888 | O200: 1.22 | P200: =N200*O200 -> 2325.4283 | Q200: 1.0506 | R200: =P200*Q200 -> 2443.095 | S200: 0.105 | T200: =N200*S200 -> 200.13932 | U200: 0.03 | V200: =P200*U200 -> 69.76285 | W200: GBP | X200: 4.14528 | Y200: PERCENTAGE_OF_BASE_FREIGHT | Z200: 0.103632 | AA200: 7.95 | AB200: 9.22 | AC200: =IF(W200="EUR",AA200,IF(W200="GBP",AB200,1)) -> 9.22 | AD200: =R200*X200 -> 10127.313 | AE200: =IF(Y200="PERCENTAGE_OF_BASE_FREIGHT",AD200*Z200,IF(Y200="PER_CHARGEABLE_KG",R200*Z200,P200*Z200)) -> 1049.5137 | AF200: =AD200*AC200 -> 93373.825 | AG200: =AE200*AC200 -> 9676.5162 | AH200: EUR | AI200: 1.3884759 | AJ200: =IF(AH200="EUR",AA200,IF(AH200="GBP",AB200,1)) -> 7.95 | AK200: =N200*AI200 -> 2646.5584 | AL200: =AK200*AJ200 -> 21040.139 | AM200: EUR | AN200: 0.42672 | AO200: =IF(AM200="EUR",AA200,IF(AM200="GBP",AB200,1)) -> 7.95 | AP200: =P200*AN200 -> 992.30678 | AQ200: =AP200*AO200 -> 7888.8389 | AR200: GBP | AS200: 4.8768 | AT200: =IF(AR200="EUR",AA200,IF(AR200="GBP",AB200,1)) -> 9.22 | AU200: =T200*AS200 -> 976.03946 | AV200: =AU200*AT200 -> 8999.0838 | AW200: GBP | AX200: 2.3368 | AY200: =IF(AW200="EUR",AA200,IF(AW200="GBP",AB200,1)) -> 9.22 | AZ200: =V200*AX200 -> 163.02183 | BA200: =AZ200*AY200 -> 1503.0613 | BB200: =AF200+AG200+AL200+AQ200+AV200+BA200 -> 142481.46 | BC200: 0.918 | BD200: UK promotion | BE200: 为维持促销期间履约时效，提高德国仓至英国的空运和 Carrier C 份额 | BG200: UNVERIFIED_UNLIMITED_FOR_MVP
A201: ACTUAL_2026_08_CLOSE_V1 | B201: ACTUAL | D201: 46235 | E201: R_GB_DE_B_ROAD | F201: GB | G201: DE_FC | H201: CARRIER_B | I201: ROAD | J201: 20300 | K201: 0.44 | L201: 0.97 | M201: 0.13 | N201: =J201*K201*L201*M201 -> 1126.3252 | O201: 1.22 | P201: =N201*O201 -> 1374.1167 | Q201: 1.03 | R201: =P201*Q201 -> 1415.3402 | S201: 0.105 | T201: =N201*S201 -> 118.26415 | U201: 0.022 | V201: =P201*U201 -> 30.230568 | W201: GBP | X201: 4.918456 | Y201: PER_CHARGEABLE_KG | Z201: 0.3453384 | AA201: 7.95 | AB201: 9.22 | AC201: =IF(W201="EUR",AA201,IF(W201="GBP",AB201,1)) -> 9.22 | AD201: =R201*X201 -> 6961.2887 | AE201: =IF(Y201="PERCENTAGE_OF_BASE_FREIGHT",AD201*Z201,IF(Y201="PER_CHARGEABLE_KG",R201*Z201,P201*Z201)) -> 488.77134 | AF201: =AD201*AC201 -> 64183.082 | AG201: =AE201*AC201 -> 4506.4717 | AH201: EUR | AI201: 1.3884759 | AJ201: =IF(AH201="EUR",AA201,IF(AH201="GBP",AB201,1)) -> 7.95 | AK201: =N201*AI201 -> 1563.8754 | AL201: =AK201*AJ201 -> 12432.81 | AM201: EUR | AN201: 0.42672 | AO201: =IF(AM201="EUR",AA201,IF(AM201="GBP",AB201,1)) -> 7.95 | AP201: =P201*AN201 -> 586.3631 | AQ201: =AP201*AO201 -> 4661.5866 | AR201: GBP | AS201: 4.8768 | AT201: =IF(AR201="EUR",AA201,IF(AR201="GBP",AB201,1)) -> 9.22 | AU201: =T201*AS201 -> 576.75059 | AV201: =AU201*AT201 -> 5317.6404 | AW201: GBP | AX201: 2.3368 | AY201: =IF(AW201="EUR",AA201,IF(AW201="GBP",AB201,1)) -> 9.22 | AZ201: =V201*AX201 -> 70.642792 | BA201: =AZ201*AY201 -> 651.32654 | BB201: =AF201+AG201+AL201+AQ201+AV201+BA201 -> 91752.917 | BC201: 0.944 | BD201: UK promotion | BE201: 为维持促销期间履约时效，提高德国仓至英国的空运和 Carrier C 份额 | BG201: UNVERIFIED_UNLIMITED_FOR_MVP
A202: ACTUAL_2026_08_CLOSE_V1 | B202: ACTUAL | D202: 46235 | E202: R_GB_DE_B_AIR | F202: GB | G202: DE_FC | H202: CARRIER_B | I202: AIR | J202: 20300 | K202: 0.44 | L202: 0.97 | M202: 0.25 | N202: =J202*K202*L202*M202 -> 2166.01 | O202: 1.22 | P202: =N202*O202 -> 2642.5322 | Q202: 0.9682 | R202: =P202*Q202 -> 2558.4997 | S202: 0.105 | T202: =N202*S202 -> 227.43105 | U202: 0.017 | V202: =P202*U202 -> 44.923047 | W202: GBP | X202: 6.803136 | Y202: PERCENTAGE_OF_BASE_FREIGHT | Z202: 0.1261872 | AA202: 7.95 | AB202: 9.22 | AC202: =IF(W202="EUR",AA202,IF(W202="GBP",AB202,1)) -> 9.22 | AD202: =R202*X202 -> 17405.821 | AE202: =IF(Y202="PERCENTAGE_OF_BASE_FREIGHT",AD202*Z202,IF(Y202="PER_CHARGEABLE_KG",R202*Z202,P202*Z202)) -> 2196.3918 | AF202: =AD202*AC202 -> 160481.67 | AG202: =AE202*AC202 -> 20250.733 | AH202: EUR | AI202: 1.3884759 | AJ202: =IF(AH202="EUR",AA202,IF(AH202="GBP",AB202,1)) -> 7.95 | AK202: =N202*AI202 -> 3007.4527 | AL202: =AK202*AJ202 -> 23909.249 | AM202: EUR | AN202: 0.42672 | AO202: =IF(AM202="EUR",AA202,IF(AM202="GBP",AB202,1)) -> 7.95 | AP202: =P202*AN202 -> 1127.6213 | AQ202: =AP202*AO202 -> 8964.5897 | AR202: GBP | AS202: 4.8768 | AT202: =IF(AR202="EUR",AA202,IF(AR202="GBP",AB202,1)) -> 9.22 | AU202: =T202*AS202 -> 1109.1357 | AV202: =AU202*AT202 -> 10226.232 | AW202: GBP | AX202: 2.8448 | AY202: =IF(AW202="EUR",AA202,IF(AW202="GBP",AB202,1)) -> 9.22 | AZ202: =V202*AX202 -> 127.79709 | BA202: =AZ202*AY202 -> 1178.2891 | BB202: =AF202+AG202+AL202+AQ202+AV202+BA202 -> 225010.76 | BC202: 0.971 | BD202: UK promotion | BE202: 为维持促销期间履约时效，提高德国仓至英国的空运和 Carrier C 份额 | BG202: UNVERIFIED_UNLIMITED_FOR_MVP
A203: ACTUAL_2026_08_CLOSE_V1 | B203: ACTUAL | D203: 46235 | E203: R_GB_DE_C_AIR | F203: GB | G203: DE_FC | H203: CARRIER_C | I203: AIR | J203: 20300 | K203: 0.44 | L203: 0.97 | M203: 0.4 | N203: =J203*K203*L203*M203 -> 3465.616 | O203: 1.22 | P203: =N203*O203 -> 4228.0515 | Q203: 0.9476 | R203: =P203*Q203 -> 4006.5016 | S203: 0.105 | T203: =N203*S203 -> 363.88968 | U203: 0.012 | V203: =P203*U203 -> 50.736618 | W203: GBP | X203: 8.5344 | Y203: PER_CHARGEABLE_KG | Z203: 0.6599936 | AA203: 7.95 | AB203: 9.22 | AC203: =IF(W203="EUR",AA203,IF(W203="GBP",AB203,1)) -> 9.22 | AD203: =R203*X203 -> 34193.087 | AE203: =IF(Y203="PERCENTAGE_OF_BASE_FREIGHT",AD203*Z203,IF(Y203="PER_CHARGEABLE_KG",R203*Z203,P203*Z203)) -> 2644.2654 | AF203: =AD203*AC203 -> 315260.27 | AG203: =AE203*AC203 -> 24380.127 | AH203: EUR | AI203: 1.3884759 | AJ203: =IF(AH203="EUR",AA203,IF(AH203="GBP",AB203,1)) -> 7.95 | AK203: =N203*AI203 -> 4811.9244 | AL203: =AK203*AJ203 -> 38254.799 | AM203: EUR | AN203: 0.42672 | AO203: =IF(AM203="EUR",AA203,IF(AM203="GBP",AB203,1)) -> 7.95 | AP203: =P203*AN203 -> 1804.1941 | AQ203: =AP203*AO203 -> 14343.343 | AR203: GBP | AS203: 4.8768 | AT203: =IF(AR203="EUR",AA203,IF(AR203="GBP",AB203,1)) -> 9.22 | AU203: =T203*AS203 -> 1774.6172 | AV203: =AU203*AT203 -> 16361.971 | AW203: GBP | AX203: 3.6576 | AY203: =IF(AW203="EUR",AA203,IF(AW203="GBP",AB203,1)) -> 9.22 | AZ203: =V203*AX203 -> 185.57425 | BA203: =AZ203*AY203 -> 1710.9946 | BB203: =AF203+AG203+AL203+AQ203+AV203+BA203 -> 410311.5 | BC203: 0.985 | BD203: UK promotion | BE203: 为维持促销期间履约时效，提高德国仓至英国的空运和 Carrier C 份额 | BG203: UNVERIFIED_UNLIMITED_FOR_MVP
A204: ACTUAL_2026_08_CLOSE_V1 | B204: ACTUAL | D204: 46235 | E204: R_GB_FR_B_AIR | F204: GB | G204: FR_FC | H204: CARRIER_B | I204: AIR | J204: 20300 | K204: 0.44 | L204: 0.03 | M204: 1 | N204: =J204*K204*L204*M204 -> 267.96 | O204: 1.18 | P204: =N204*O204 -> 316.1928 | Q204: 0.927 | R204: =P204*Q204 -> 293.11073 | S204: 0.105 | T204: =N204*S204 -> 28.1358 | U204: 0.015 | V204: =P204*U204 -> 4.742892 | W204: EUR | X204: 6.8072 | Y204: PERCENTAGE_OF_BASE_FREIGHT | Z204: 0.10668 | AA204: 7.95 | AB204: 9.22 | AC204: =IF(W204="EUR",AA204,IF(W204="GBP",AB204,1)) -> 7.95 | AD204: =R204*X204 -> 1995.2633 | AE204: =IF(Y204="PERCENTAGE_OF_BASE_FREIGHT",AD204*Z204,IF(Y204="PER_CHARGEABLE_KG",R204*Z204,P204*Z204)) -> 212.85469 | AF204: =AD204*AC204 -> 15862.343 | AG204: =AE204*AC204 -> 1692.1948 | AH204: EUR | AI204: 1.0668 | AJ204: =IF(AH204="EUR",AA204,IF(AH204="GBP",AB204,1)) -> 7.95 | AK204: =N204*AI204 -> 285.85973 | AL204: =AK204*AJ204 -> 2272.5848 | AM204: EUR | AN204: 0.38608 | AO204: =IF(AM204="EUR",AA204,IF(AM204="GBP",AB204,1)) -> 7.95 | AP204: =P204*AN204 -> 122.07572 | AQ204: =AP204*AO204 -> 970.50194 | AR204: EUR | AS204: 5.2832 | AT204: =IF(AR204="EUR",AA204,IF(AR204="GBP",AB204,1)) -> 7.95 | AU204: =T204*AS204 -> 148.64706 | AV204: =AU204*AT204 -> 1181.7441 | AW204: EUR | AX204: 2.8448 | AY204: =IF(AW204="EUR",AA204,IF(AW204="GBP",AB204,1)) -> 7.95 | AZ204: =V204*AX204 -> 13.492579 | BA204: =AZ204*AY204 -> 107.266 | BB204: =AF204+AG204+AL204+AQ204+AV204+BA204 -> 22086.635 | BC204: 0.968 | BD204: UK promotion | BE204: 为维持促销期间履约时效，提高德国仓至英国的空运和 Carrier C 份额 | BG204: UNVERIFIED_UNLIMITED_FOR_MVP
A205: FORECAST_2026_08_V1 | B205: FORECAST | D205: 46266 | E205: R_DE_DE_A_ROAD | F205: DE | G205: DE_FC | H205: CARRIER_A | I205: ROAD | J205: 17200 | K205: 0.36 | L205: 0.97 | M205: 0.6 | N205: =J205*K205*L205*M205 -> 3603.744 | O205: 1.05 | P205: =N205*O205 -> 3783.9312 | Q205: 0.78 | R205: =P205*Q205 -> 2951.4663 | S205: 0.05 | T205: =N205*S205 -> 180.1872 | U205: 0.016 | V205: =P205*U205 -> 60.542899 | W205: EUR | X205: 2.277 | Y205: PERCENTAGE_OF_BASE_FREIGHT | Z205: 0.098325 | AA205: 7.92 | AB205: 9.15 | AC205: =IF(W205="EUR",AA205,IF(W205="GBP",AB205,1)) -> 7.92 | AD205: =R205*X205 -> 6720.4888 | AE205: =IF(Y205="PERCENTAGE_OF_BASE_FREIGHT",AD205*Z205,IF(Y205="PER_CHARGEABLE_KG",R205*Z205,P205*Z205)) -> 660.79207 | AF205: =AD205*AC205 -> 53226.272 | AG205: =AE205*AC205 -> 5233.4732 | AH205: EUR | AI205: 1.3762011 | AJ205: =IF(AH205="EUR",AA205,IF(AH205="GBP",AB205,1)) -> 7.92 | AK205: =N205*AI205 -> 4959.4763 | AL205: =AK205*AJ205 -> 39279.053 | AM205: EUR | AN205: 0.4347 | AO205: =IF(AM205="EUR",AA205,IF(AM205="GBP",AB205,1)) -> 7.92 | AP205: =P205*AN205 -> 1644.8749 | AQ205: =AP205*AO205 -> 13027.409 | AR205: EUR | AS205: 3.312 | AT205: =IF(AR205="EUR",AA205,IF(AR205="GBP",AB205,1)) -> 7.92 | AU205: =T205*AS205 -> 596.78001 | AV205: =AU205*AT205 -> 4726.4977 | AW205: EUR | AX205: 2.3805 | AY205: =IF(AW205="EUR",AA205,IF(AW205="GBP",AB205,1)) -> 7.92 | AZ205: =V205*AX205 -> 144.12237 | BA205: =AZ205*AY205 -> 1141.4492 | BB205: =AF205+AG205+AL205+AQ205+AV205+BA205 -> 116634.15 | BC205: 0.965 | BE205: 正式 Forecast 逐月降低英国空运及 Carrier C 份额，但仍高于 Budget | BG205: UNVERIFIED_UNLIMITED_FOR_MVP
A206: FORECAST_2026_08_V1 | B206: FORECAST | D206: 46266 | E206: R_DE_DE_B_ROAD | F206: DE | G206: DE_FC | H206: CARRIER_B | I206: ROAD | J206: 17200 | K206: 0.36 | L206: 0.97 | M206: 0.4 | N206: =J206*K206*L206*M206 -> 2402.496 | O206: 1.05 | P206: =N206*O206 -> 2522.6208 | Q206: 0.8 | R206: =P206*Q206 -> 2018.0966 | S206: 0.05 | T206: =N206*S206 -> 120.1248 | U206: 0.013 | V206: =P206*U206 -> 32.79407 | W206: EUR | X206: 2.84625 | Y206: PER_CHARGEABLE_KG | Z206: 0.21735 | AA206: 7.92 | AB206: 9.15 | AC206: =IF(W206="EUR",AA206,IF(W206="GBP",AB206,1)) -> 7.92 | AD206: =R206*X206 -> 5744.0076 | AE206: =IF(Y206="PERCENTAGE_OF_BASE_FREIGHT",AD206*Z206,IF(Y206="PER_CHARGEABLE_KG",R206*Z206,P206*Z206)) -> 438.6333 | AF206: =AD206*AC206 -> 45492.54 | AG206: =AE206*AC206 -> 3473.9758 | AH206: EUR | AI206: 1.3762011 | AJ206: =IF(AH206="EUR",AA206,IF(AH206="GBP",AB206,1)) -> 7.92 | AK206: =N206*AI206 -> 3306.3176 | AL206: =AK206*AJ206 -> 26186.035 | AM206: EUR | AN206: 0.4347 | AO206: =IF(AM206="EUR",AA206,IF(AM206="GBP",AB206,1)) -> 7.92 | AP206: =P206*AN206 -> 1096.5833 | AQ206: =AP206*AO206 -> 8684.9394 | AR206: EUR | AS206: 3.312 | AT206: =IF(AR206="EUR",AA206,IF(AR206="GBP",AB206,1)) -> 7.92 | AU206: =T206*AS206 -> 397.85334 | AV206: =AU206*AT206 -> 3150.9984 | AW206: EUR | AX206: 2.3805 | AY206: =IF(AW206="EUR",AA206,IF(AW206="GBP",AB206,1)) -> 7.92 | AZ206: =V206*AX206 -> 78.066285 | BA206: =AZ206*AY206 -> 618.28497 | BB206: =AF206+AG206+AL206+AQ206+AV206+BA206 -> 87606.774 | BC206: 0.976 | BE206: 正式 Forecast 逐月降低英国空运及 Carrier C 份额，但仍高于 Budget | BG206: UNVERIFIED_UNLIMITED_FOR_MVP
A207: FORECAST_2026_08_V1 | B207: FORECAST | D207: 46266 | E207: R_DE_FR_B_ROAD | F207: DE | G207: FR_FC | H207: CARRIER_B | I207: ROAD | J207: 17200 | K207: 0.36 | L207: 0.03 | M207: 1 | N207: =J207*K207*L207*M207 -> 185.76 | O207: 1.08 | P207: =N207*O207 -> 200.6208 | Q207: 0.86 | R207: =P207*Q207 -> 172.53389 | S207: 0.05 | T207: =N207*S207 -> 9.288 | U207: 0.014 | V207: =P207*U207 -> 2.8086912 | W207: EUR | X207: 3.4155 | Y207: PER_CHARGEABLE_KG | Z207: 0.2484 | AA207: 7.92 | AB207: 9.15 | AC207: =IF(W207="EUR",AA207,IF(W207="GBP",AB207,1)) -> 7.92 | AD207: =R207*X207 -> 589.28949 | AE207: =IF(Y207="PERCENTAGE_OF_BASE_FREIGHT",AD207*Z207,IF(Y207="PER_CHARGEABLE_KG",R207*Z207,P207*Z207)) -> 42.857418 | AF207: =AD207*AC207 -> 4667.1728 | AG207: =AE207*AC207 -> 339.43075 | AH207: EUR | AI207: 1.08675 | AJ207: =IF(AH207="EUR",AA207,IF(AH207="GBP",AB207,1)) -> 7.92 | AK207: =N207*AI207 -> 201.87468 | AL207: =AK207*AJ207 -> 1598.8475 | AM207: EUR | AN207: 0.3933 | AO207: =IF(AM207="EUR",AA207,IF(AM207="GBP",AB207,1)) -> 7.92 | AP207: =P207*AN207 -> 78.904161 | AQ207: =AP207*AO207 -> 624.92095 | AR207: EUR | AS207: 3.933 | AT207: =IF(AR207="EUR",AA207,IF(AR207="GBP",AB207,1)) -> 7.92 | AU207: =T207*AS207 -> 36.529704 | AV207: =AU207*AT207 -> 289.31526 | AW207: EUR | AX207: 2.3805 | AY207: =IF(AW207="EUR",AA207,IF(AW207="GBP",AB207,1)) -> 7.92 | AZ207: =V207*AX207 -> 6.6860894 | BA207: =AZ207*AY207 -> 52.953828 | BB207: =AF207+AG207+AL207+AQ207+AV207+BA207 -> 7572.641 | BC207: 0.968 | BE207: 正式 Forecast 逐月降低英国空运及 Carrier C 份额，但仍高于 Budget | BG207: UNVERIFIED_UNLIMITED_FOR_MVP
A208: FORECAST_2026_08_V1 | B208: FORECAST | D208: 46266 | E208: R_FR_FR_A_ROAD | F208: FR | G208: FR_FC | H208: CARRIER_A | I208: ROAD | J208: 17200 | K208: 0.3 | L208: 1 | M208: 0.35 | N208: =J208*K208*L208*M208 -> 1806 | O208: 1.06 | P208: =N208*O208 -> 1914.36 | Q208: 0.76 | R208: =P208*Q208 -> 1454.9136 | S208: 0.06 | T208: =N208*S208 -> 108.36 | U208: 0.017 | V208: =P208*U208 -> 32.54412 | W208: EUR | X208: 2.1735 | Y208: PERCENTAGE_OF_BASE_FREIGHT | Z208: 0.09315 | AA208: 7.92 | AB208: 9.15 | AC208: =IF(W208="EUR",AA208,IF(W208="GBP",AB208,1)) -> 7.92 | AD208: =R208*X208 -> 3162.2547 | AE208: =IF(Y208="PERCENTAGE_OF_BASE_FREIGHT",AD208*Z208,IF(Y208="PER_CHARGEABLE_KG",R208*Z208,P208*Z208)) -> 294.56403 | AF208: =AD208*AC208 -> 25045.057 | AG208: =AE208*AC208 -> 2332.9471 | AH208: EUR | AI208: 1.08675 | AJ208: =IF(AH208="EUR",AA208,IF(AH208="GBP",AB208,1)) -> 7.92 | AK208: =N208*AI208 -> 1962.6705 | AL208: =AK208*AJ208 -> 15544.35 | AM208: EUR | AN208: 0.3933 | AO208: =IF(AM208="EUR",AA208,IF(AM208="GBP",AB208,1)) -> 7.92 | AP208: =P208*AN208 -> 752.91779 | AQ208: =AP208*AO208 -> 5963.1089 | AR208: EUR | AS208: 3.105 | AT208: =IF(AR208="EUR",AA208,IF(AR208="GBP",AB208,1)) -> 7.92 | AU208: =T208*AS208 -> 336.4578 | AV208: =AU208*AT208 -> 2664.7458 | AW208: EUR | AX208: 2.3805 | AY208: =IF(AW208="EUR",AA208,IF(AW208="GBP",AB208,1)) -> 7.92 | AZ208: =V208*AX208 -> 77.471278 | BA208: =AZ208*AY208 -> 613.57252 | BB208: =AF208+AG208+AL208+AQ208+AV208+BA208 -> 52163.782 | BC208: 0.961 | BE208: 正式 Forecast 逐月降低英国空运及 Carrier C 份额，但仍高于 Budget | BG208: UNVERIFIED_UNLIMITED_FOR_MVP
A209: FORECAST_2026_08_V1 | B209: FORECAST | D209: 46266 | E209: R_FR_FR_B_ROAD | F209: FR | G209: FR_FC | H209: CARRIER_B | I209: ROAD | J209: 17200 | K209: 0.3 | L209: 1 | M209: 0.65 | N209: =J209*K209*L209*M209 -> 3354 | O209: 1.06 | P209: =N209*O209 -> 3555.24 | Q209: 0.79 | R209: =P209*Q209 -> 2808.6396 | S209: 0.06 | T209: =N209*S209 -> 201.24 | U209: 0.014 | V209: =P209*U209 -> 49.77336 | W209: EUR | X209: 2.691 | Y209: PER_CHARGEABLE_KG | Z209: 0.207 | AA209: 7.92 | AB209: 9.15 | AC209: =IF(W209="EUR",AA209,IF(W209="GBP",AB209,1)) -> 7.92 | AD209: =R209*X209 -> 7558.0492 | AE209: =IF(Y209="PERCENTAGE_OF_BASE_FREIGHT",AD209*Z209,IF(Y209="PER_CHARGEABLE_KG",R209*Z209,P209*Z209)) -> 581.3884 | AF209: =AD209*AC209 -> 59859.749 | AG209: =AE209*AC209 -> 4604.5961 | AH209: EUR | AI209: 1.08675 | AJ209: =IF(AH209="EUR",AA209,IF(AH209="GBP",AB209,1)) -> 7.92 | AK209: =N209*AI209 -> 3644.9595 | AL209: =AK209*AJ209 -> 28868.079 | AM209: EUR | AN209: 0.3933 | AO209: =IF(AM209="EUR",AA209,IF(AM209="GBP",AB209,1)) -> 7.92 | AP209: =P209*AN209 -> 1398.2759 | AQ209: =AP209*AO209 -> 11074.345 | AR209: EUR | AS209: 3.105 | AT209: =IF(AR209="EUR",AA209,IF(AR209="GBP",AB209,1)) -> 7.92 | AU209: =T209*AS209 -> 624.8502 | AV209: =AU209*AT209 -> 4948.8136 | AW209: EUR | AX209: 2.3805 | AY209: =IF(AW209="EUR",AA209,IF(AW209="GBP",AB209,1)) -> 7.92 | AZ209: =V209*AX209 -> 118.48548 | BA209: =AZ209*AY209 -> 938.40503 | BB209: =AF209+AG209+AL209+AQ209+AV209+BA209 -> 110293.99 | BC209: 0.973 | BE209: 正式 Forecast 逐月降低英国空运及 Carrier C 份额，但仍高于 Budget | BG209: UNVERIFIED_UNLIMITED_FOR_MVP
A210: FORECAST_2026_08_V1 | B210: FORECAST | D210: 46266 | E210: R_GB_DE_A_ROAD | F210: GB | G210: DE_FC | H210: CARRIER_A | I210: ROAD | J210: 17200 | K210: 0.34 | L210: 0.96 | M210: 0.3 | N210: =J210*K210*L210*M210 -> 1684.224 | O210: 1.19 | P210: =N210*O210 -> 2004.2266 | Q210: 1.0404 | R210: =P210*Q210 -> 2085.1973 | S210: 0.095 | T210: =N210*S210 -> 160.00128 | U210: 0.027 | V210: =P210*U210 -> 54.114117 | W210: GBP | X210: 4.14 | Y210: PERCENTAGE_OF_BASE_FREIGHT | Z210: 0.1035 | AA210: 7.92 | AB210: 9.15 | AC210: =IF(W210="EUR",AA210,IF(W210="GBP",AB210,1)) -> 9.15 | AD210: =R210*X210 -> 8632.7169 | AE210: =IF(Y210="PERCENTAGE_OF_BASE_FREIGHT",AD210*Z210,IF(Y210="PER_CHARGEABLE_KG",R210*Z210,P210*Z210)) -> 893.4862 | AF210: =AD210*AC210 -> 78989.359 | AG210: =AE210*AC210 -> 8175.3987 | AH210: EUR | AI210: 1.3762011 | AJ210: =IF(AH210="EUR",AA210,IF(AH210="GBP",AB210,1)) -> 7.92 | AK210: =N210*AI210 -> 2317.8309 | AL210: =AK210*AJ210 -> 18357.22 | AM210: EUR | AN210: 0.4347 | AO210: =IF(AM210="EUR",AA210,IF(AM210="GBP",AB210,1)) -> 7.92 | AP210: =P210*AN210 -> 871.23729 | AQ210: =AP210*AO210 -> 6900.1993 | AR210: GBP | AS210: 4.968 | AT210: =IF(AR210="EUR",AA210,IF(AR210="GBP",AB210,1)) -> 9.15 | AU210: =T210*AS210 -> 794.88636 | AV210: =AU210*AT210 -> 7273.2102 | AW210: GBP | AX210: 2.3805 | AY210: =IF(AW210="EUR",AA210,IF(AW210="GBP",AB210,1)) -> 9.15 | AZ210: =V210*AX210 -> 128.81866 | BA210: =AZ210*AY210 -> 1178.6907 | BB210: =AF210+AG210+AL210+AQ210+AV210+BA210 -> 120874.08 | BC210: 0.93 | BE210: 正式 Forecast 逐月降低英国空运及 Carrier C 份额，但仍高于 Budget | BG210: UNVERIFIED_UNLIMITED_FOR_MVP
A211: FORECAST_2026_08_V1 | B211: FORECAST | D211: 46266 | E211: R_GB_DE_B_ROAD | F211: GB | G211: DE_FC | H211: CARRIER_B | I211: ROAD | J211: 17200 | K211: 0.34 | L211: 0.96 | M211: 0.17 | N211: =J211*K211*L211*M211 -> 954.3936 | O211: 1.19 | P211: =N211*O211 -> 1135.7284 | Q211: 1.02 | R211: =P211*Q211 -> 1158.443 | S211: 0.095 | T211: =N211*S211 -> 90.667392 | U211: 0.02 | V211: =P211*U211 -> 22.714568 | W211: GBP | X211: 4.8645 | Y211: PER_CHARGEABLE_KG | Z211: 0.34155 | AA211: 7.92 | AB211: 9.15 | AC211: =IF(W211="EUR",AA211,IF(W211="GBP",AB211,1)) -> 9.15 | AD211: =R211*X211 -> 5635.2457 | AE211: =IF(Y211="PERCENTAGE_OF_BASE_FREIGHT",AD211*Z211,IF(Y211="PER_CHARGEABLE_KG",R211*Z211,P211*Z211)) -> 395.66619 | AF211: =AD211*AC211 -> 51562.499 | AG211: =AE211*AC211 -> 3620.3456 | AH211: EUR | AI211: 1.3762011 | AJ211: =IF(AH211="EUR",AA211,IF(AH211="GBP",AB211,1)) -> 7.92 | AK211: =N211*AI211 -> 1313.4375 | AL211: =AK211*AJ211 -> 10402.425 | AM211: EUR | AN211: 0.4347 | AO211: =IF(AM211="EUR",AA211,IF(AM211="GBP",AB211,1)) -> 7.92 | AP211: =P211*AN211 -> 493.70113 | AQ211: =AP211*AO211 -> 3910.1129 | AR211: GBP | AS211: 4.968 | AT211: =IF(AR211="EUR",AA211,IF(AR211="GBP",AB211,1)) -> 9.15 | AU211: =T211*AS211 -> 450.4356 | AV211: =AU211*AT211 -> 4121.4858 | AW211: GBP | AX211: 2.3805 | AY211: =IF(AW211="EUR",AA211,IF(AW211="GBP",AB211,1)) -> 9.15 | AZ211: =V211*AX211 -> 54.072028 | BA211: =AZ211*AY211 -> 494.75906 | BB211: =AF211+AG211+AL211+AQ211+AV211+BA211 -> 74111.627 | BC211: 0.95 | BE211: 正式 Forecast 逐月降低英国空运及 Carrier C 份额，但仍高于 Budget | BG211: UNVERIFIED_UNLIMITED_FOR_MVP
A212: FORECAST_2026_08_V1 | B212: FORECAST | D212: 46266 | E212: R_GB_DE_B_AIR | F212: GB | G212: DE_FC | H212: CARRIER_B | I212: AIR | J212: 17200 | K212: 0.34 | L212: 0.96 | M212: 0.25 | N212: =J212*K212*L212*M212 -> 1403.52 | O212: 1.19 | P212: =N212*O212 -> 1670.1888 | Q212: 0.9588 | R212: =P212*Q212 -> 1601.377 | S212: 0.095 | T212: =N212*S212 -> 133.3344 | U212: 0.016 | V212: =P212*U212 -> 26.723021 | W212: GBP | X212: 6.67368 | Y212: PERCENTAGE_OF_BASE_FREIGHT | Z212: 0.123786 | AA212: 7.92 | AB212: 9.15 | AC212: =IF(W212="EUR",AA212,IF(W212="GBP",AB212,1)) -> 9.15 | AD212: =R212*X212 -> 10687.078 | AE212: =IF(Y212="PERCENTAGE_OF_BASE_FREIGHT",AD212*Z212,IF(Y212="PER_CHARGEABLE_KG",R212*Z212,P212*Z212)) -> 1322.9106 | AF212: =AD212*AC212 -> 97786.762 | AG212: =AE212*AC212 -> 12104.632 | AH212: EUR | AI212: 1.3762011 | AJ212: =IF(AH212="EUR",AA212,IF(AH212="GBP",AB212,1)) -> 7.92 | AK212: =N212*AI212 -> 1931.5257 | AL212: =AK212*AJ212 -> 15297.684 | AM212: EUR | AN212: 0.4347 | AO212: =IF(AM212="EUR",AA212,IF(AM212="GBP",AB212,1)) -> 7.92 | AP212: =P212*AN212 -> 726.03107 | AQ212: =AP212*AO212 -> 5750.1661 | AR212: GBP | AS212: 4.968 | AT212: =IF(AR212="EUR",AA212,IF(AR212="GBP",AB212,1)) -> 9.15 | AU212: =T212*AS212 -> 662.4053 | AV212: =AU212*AT212 -> 6061.0085 | AW212: GBP | AX212: 2.898 | AY212: =IF(AW212="EUR",AA212,IF(AW212="GBP",AB212,1)) -> 9.15 | AZ212: =V212*AX212 -> 77.443314 | BA212: =AZ212*AY212 -> 708.60633 | BB212: =AF212+AG212+AL212+AQ212+AV212+BA212 -> 137708.86 | BC212: 0.974 | BE212: 正式 Forecast 逐月降低英国空运及 Carrier C 份额，但仍高于 Budget | BG212: UNVERIFIED_UNLIMITED_FOR_MVP
A213: FORECAST_2026_08_V1 | B213: FORECAST | D213: 46266 | E213: R_GB_DE_C_AIR | F213: GB | G213: DE_FC | H213: CARRIER_C | I213: AIR | J213: 17200 | K213: 0.34 | L213: 0.96 | M213: 0.28 | N213: =J213*K213*L213*M213 -> 1571.9424 | O213: 1.19 | P213: =N213*O213 -> 1870.6115 | Q213: 0.9384 | R213: =P213*Q213 -> 1755.3818 | S213: 0.095 | T213: =N213*S213 -> 149.33453 | U213: 0.011 | V213: =P213*U213 -> 20.576726 | W213: GBP | X213: 8.22825 | Y213: PER_CHARGEABLE_KG | Z213: 0.636318 | AA213: 7.92 | AB213: 9.15 | AC213: =IF(W213="EUR",AA213,IF(W213="GBP",AB213,1)) -> 9.15 | AD213: =R213*X213 -> 14443.72 | AE213: =IF(Y213="PERCENTAGE_OF_BASE_FREIGHT",AD213*Z213,IF(Y213="PER_CHARGEABLE_KG",R213*Z213,P213*Z213)) -> 1116.981 | AF213: =AD213*AC213 -> 132160.04 | AG213: =AE213*AC213 -> 10220.376 | AH213: EUR | AI213: 1.3762011 | AJ213: =IF(AH213="EUR",AA213,IF(AH213="GBP",AB213,1)) -> 7.92 | AK213: =N213*AI213 -> 2163.3088 | AL213: =AK213*AJ213 -> 17133.406 | AM213: EUR | AN213: 0.4347 | AO213: =IF(AM213="EUR",AA213,IF(AM213="GBP",AB213,1)) -> 7.92 | AP213: =P213*AN213 -> 813.1548 | AQ213: =AP213*AO213 -> 6440.186 | AR213: GBP | AS213: 4.968 | AT213: =IF(AR213="EUR",AA213,IF(AR213="GBP",AB213,1)) -> 9.15 | AU213: =T213*AS213 -> 741.89394 | AV213: =AU213*AT213 -> 6788.3295 | AW213: GBP | AX213: 3.726 | AY213: =IF(AW213="EUR",AA213,IF(AW213="GBP",AB213,1)) -> 9.15 | AZ213: =V213*AX213 -> 76.668881 | BA213: =AZ213*AY213 -> 701.52026 | BB213: =AF213+AG213+AL213+AQ213+AV213+BA213 -> 173443.86 | BC213: 0.988 | BE213: 正式 Forecast 逐月降低英国空运及 Carrier C 份额，但仍高于 Budget | BG213: UNVERIFIED_UNLIMITED_FOR_MVP
A214: FORECAST_2026_08_V1 | B214: FORECAST | D214: 46266 | E214: R_GB_FR_B_AIR | F214: GB | G214: FR_FC | H214: CARRIER_B | I214: AIR | J214: 17200 | K214: 0.34 | L214: 0.04 | M214: 1 | N214: =J214*K214*L214*M214 -> 233.92 | O214: 1.17 | P214: =N214*O214 -> 273.6864 | Q214: 0.918 | R214: =P214*Q214 -> 251.24412 | S214: 0.095 | T214: =N214*S214 -> 22.2224 | U214: 0.014 | V214: =P214*U214 -> 3.8316096 | W214: EUR | X214: 6.9345 | Y214: PERCENTAGE_OF_BASE_FREIGHT | Z214: 0.108675 | AA214: 7.92 | AB214: 9.15 | AC214: =IF(W214="EUR",AA214,IF(W214="GBP",AB214,1)) -> 7.92 | AD214: =R214*X214 -> 1742.2523 | AE214: =IF(Y214="PERCENTAGE_OF_BASE_FREIGHT",AD214*Z214,IF(Y214="PER_CHARGEABLE_KG",R214*Z214,P214*Z214)) -> 189.33927 | AF214: =AD214*AC214 -> 13798.638 | AG214: =AE214*AC214 -> 1499.567 | AH214: EUR | AI214: 1.08675 | AJ214: =IF(AH214="EUR",AA214,IF(AH214="GBP",AB214,1)) -> 7.92 | AK214: =N214*AI214 -> 254.21256 | AL214: =AK214*AJ214 -> 2013.3635 | AM214: EUR | AN214: 0.3933 | AO214: =IF(AM214="EUR",AA214,IF(AM214="GBP",AB214,1)) -> 7.92 | AP214: =P214*AN214 -> 107.64086 | AQ214: =AP214*AO214 -> 852.51562 | AR214: EUR | AS214: 5.382 | AT214: =IF(AR214="EUR",AA214,IF(AR214="GBP",AB214,1)) -> 7.92 | AU214: =T214*AS214 -> 119.60096 | AV214: =AU214*AT214 -> 947.23958 | AW214: EUR | AX214: 2.898 | AY214: =IF(AW214="EUR",AA214,IF(AW214="GBP",AB214,1)) -> 7.92 | AZ214: =V214*AX214 -> 11.104005 | BA214: =AZ214*AY214 -> 87.943717 | BB214: =AF214+AG214+AL214+AQ214+AV214+BA214 -> 19199.268 | BC214: 0.971 | BE214: 正式 Forecast 逐月降低英国空运及 Carrier C 份额，但仍高于 Budget | BG214: UNVERIFIED_UNLIMITED_FOR_MVP
A215: FORECAST_2026_08_V1 | B215: FORECAST | D215: 46296 | E215: R_DE_DE_A_ROAD | F215: DE | G215: DE_FC | H215: CARRIER_A | I215: ROAD | J215: 19500 | K215: 0.34 | L215: 0.97 | M215: 0.6 | N215: =J215*K215*L215*M215 -> 3858.66 | O215: 1.05 | P215: =N215*O215 -> 4051.593 | Q215: 0.7878 | R215: =P215*Q215 -> 3191.845 | S215: 0.05 | T215: =N215*S215 -> 192.933 | U215: 0.016 | V215: =P215*U215 -> 64.825488 | W215: EUR | X215: 2.277 | Y215: PERCENTAGE_OF_BASE_FREIGHT | Z215: 0.098325 | AA215: 7.9 | AB215: 9.1 | AC215: =IF(W215="EUR",AA215,IF(W215="GBP",AB215,1)) -> 7.9 | AD215: =R215*X215 -> 7267.831 | AE215: =IF(Y215="PERCENTAGE_OF_BASE_FREIGHT",AD215*Z215,IF(Y215="PER_CHARGEABLE_KG",R215*Z215,P215*Z215)) -> 714.60948 | AF215: =AD215*AC215 -> 57415.865 | AG215: =AE215*AC215 -> 5645.4149 | AH215: EUR | AI215: 1.3579711 | AJ215: =IF(AH215="EUR",AA215,IF(AH215="GBP",AB215,1)) -> 7.9 | AK215: =N215*AI215 -> 5239.9489 | AL215: =AK215*AJ215 -> 41395.597 | AM215: EUR | AN215: 0.4347 | AO215: =IF(AM215="EUR",AA215,IF(AM215="GBP",AB215,1)) -> 7.9 | AP215: =P215*AN215 -> 1761.2275 | AQ215: =AP215*AO215 -> 13913.697 | AR215: EUR | AS215: 3.312 | AT215: =IF(AR215="EUR",AA215,IF(AR215="GBP",AB215,1)) -> 7.9 | AU215: =T215*AS215 -> 638.9941 | AV215: =AU215*AT215 -> 5048.0534 | AW215: EUR | AX215: 2.3805 | AY215: =IF(AW215="EUR",AA215,IF(AW215="GBP",AB215,1)) -> 7.9 | AZ215: =V215*AX215 -> 154.31707 | BA215: =AZ215*AY215 -> 1219.1049 | BB215: =AF215+AG215+AL215+AQ215+AV215+BA215 -> 124637.73 | BC215: 0.965 | BE215: 正式 Forecast 逐月降低英国空运及 Carrier C 份额，但仍高于 Budget | BG215: UNVERIFIED_UNLIMITED_FOR_MVP
A216: FORECAST_2026_08_V1 | B216: FORECAST | D216: 46296 | E216: R_DE_DE_B_ROAD | F216: DE | G216: DE_FC | H216: CARRIER_B | I216: ROAD | J216: 19500 | K216: 0.34 | L216: 0.97 | M216: 0.4 | N216: =J216*K216*L216*M216 -> 2572.44 | O216: 1.05 | P216: =N216*O216 -> 2701.062 | Q216: 0.808 | R216: =P216*Q216 -> 2182.4581 | S216: 0.05 | T216: =N216*S216 -> 128.622 | U216: 0.013 | V216: =P216*U216 -> 35.113806 | W216: EUR | X216: 2.84625 | Y216: PER_CHARGEABLE_KG | Z216: 0.21735 | AA216: 7.9 | AB216: 9.1 | AC216: =IF(W216="EUR",AA216,IF(W216="GBP",AB216,1)) -> 7.9 | AD216: =R216*X216 -> 6211.8214 | AE216: =IF(Y216="PERCENTAGE_OF_BASE_FREIGHT",AD216*Z216,IF(Y216="PER_CHARGEABLE_KG",R216*Z216,P216*Z216)) -> 474.35727 | AF216: =AD216*AC216 -> 49073.389 | AG216: =AE216*AC216 -> 3747.4224 | AH216: EUR | AI216: 1.3579711 | AJ216: =IF(AH216="EUR",AA216,IF(AH216="GBP",AB216,1)) -> 7.9 | AK216: =N216*AI216 -> 3493.2993 | AL216: =AK216*AJ216 -> 27597.064 | AM216: EUR | AN216: 0.4347 | AO216: =IF(AM216="EUR",AA216,IF(AM216="GBP",AB216,1)) -> 7.9 | AP216: =P216*AN216 -> 1174.1517 | AQ216: =AP216*AO216 -> 9275.798 | AR216: EUR | AS216: 3.312 | AT216: =IF(AR216="EUR",AA216,IF(AR216="GBP",AB216,1)) -> 7.9 | AU216: =T216*AS216 -> 425.99606 | AV216: =AU216*AT216 -> 3365.3689 | AW216: EUR | AX216: 2.3805 | AY216: =IF(AW216="EUR",AA216,IF(AW216="GBP",AB216,1)) -> 7.9 | AZ216: =V216*AX216 -> 83.588415 | BA216: =AZ216*AY216 -> 660.34848 | BB216: =AF216+AG216+AL216+AQ216+AV216+BA216 -> 93719.391 | BC216: 0.976 | BE216: 正式 Forecast 逐月降低英国空运及 Carrier C 份额，但仍高于 Budget | BG216: UNVERIFIED_UNLIMITED_FOR_MVP
... A244: FORECAST_2026_08_V1 | B244: FORECAST | D244: 46357 | E244: R_GB_FR_B_AIR | F244: GB | G244: FR_FC | H244: CARRIER_B | I244: AIR | J244: 28600 | K244: 0.4 | L244: 0.04 | M244: 1 | N244: =J244*K244*L244*M244 -> 457.6 | O244: 1.17 | P244: =N244*O244 -> 535.392 | Q244: 0.92718 | R244: =P244*Q244 -> 496.40475 | S244: 0.09 | T244: =N244*S244 -> 41.184 | U244: 0.014 | V244: =P244*U244 -> 7.495488 | W244: EUR | X244: 6.9345 | Y244: PERCENTAGE_OF_BASE_FREIGHT | Z244: 0.108675 | AA244: 7.86 | AB244: 9 | AC244: =IF(W244="EUR",AA244,IF(W244="GBP",AB244,1)) -> 7.86 | AD244: =R244*X244 -> 3442.3188 | AE244: =IF(Y244="PERCENTAGE_OF_BASE_FREIGHT",AD244*Z244,IF(Y244="PER_CHARGEABLE_KG",R244*Z244,P244*Z244)) -> 374.09399 | AF244: =AD244*AC244 -> 27056.626 | AG244: =AE244*AC244 -> 2940.3788 | AH244: EUR | AI244: 1.08675 | AJ244: =IF(AH244="EUR",AA244,IF(AH244="GBP",AB244,1)) -> 7.86 | AK244: =N244*AI244 -> 497.2968 | AL244: =AK244*AJ244 -> 3908.7528 | AM244: EUR | AN244: 0.3933 | AO244: =IF(AM244="EUR",AA244,IF(AM244="GBP",AB244,1)) -> 7.86 | AP244: =P244*AN244 -> 210.56967 | AQ244: =AP244*AO244 -> 1655.0776 | AR244: EUR | AS244: 5.382 | AT244: =IF(AR244="EUR",AA244,IF(AR244="GBP",AB244,1)) -> 7.86 | AU244: =T244*AS244 -> 221.65229 | AV244: =AU244*AT244 -> 1742.187 | AW244: EUR | AX244: 2.898 | AY244: =IF(AW244="EUR",AA244,IF(AW244="GBP",AB244,1)) -> 7.86 | AZ244: =V244*AX244 -> 21.721924 | BA244: =AZ244*AY244 -> 170.73432 | BB244: =AF244+AG244+AL244+AQ244+AV244+BA244 -> 37473.756 | BC244: 0.971 | BE244: 正式 Forecast 逐月降低英国空运及 Carrier C 份额，但仍高于 Budget | BG244: UNVERIFIED_UNLIMITED_FOR_MVP
A245: SCENARIO_BASE_2026_08 | B245: SCENARIO | C245: BASE | D245: 46266 | E245: R_DE_DE_A_ROAD | F245: DE | G245: DE_FC | H245: CARRIER_A | I245: ROAD | J245: 17200 | K245: 0.36 | L245: 0.97 | M245: 0.6 | N245: =J245*K245*L245*M245 -> 3603.744 | O245: 1.05 | P245: =N245*O245 -> 3783.9312 | Q245: 0.78 | R245: =P245*Q245 -> 2951.4663 | S245: 0.05 | T245: =N245*S245 -> 180.1872 | U245: 0.016 | V245: =P245*U245 -> 60.542899 | W245: EUR | X245: 2.277 | Y245: PERCENTAGE_OF_BASE_FREIGHT | Z245: 0.098325 | AA245: 7.92 | AB245: 9.15 | AC245: =IF(W245="EUR",AA245,IF(W245="GBP",AB245,1)) -> 7.92 | AD245: =R245*X245 -> 6720.4888 | AE245: =IF(Y245="PERCENTAGE_OF_BASE_FREIGHT",AD245*Z245,IF(Y245="PER_CHARGEABLE_KG",R245*Z245,P245*Z245)) -> 660.79207 | AF245: =AD245*AC245 -> 53226.272 | AG245: =AE245*AC245 -> 5233.4732 | AH245: EUR | AI245: 1.3762011 | AJ245: =IF(AH245="EUR",AA245,IF(AH245="GBP",AB245,1)) -> 7.92 | AK245: =N245*AI245 -> 4959.4763 | AL245: =AK245*AJ245 -> 39279.053 | AM245: EUR | AN245: 0.4347 | AO245: =IF(AM245="EUR",AA245,IF(AM245="GBP",AB245,1)) -> 7.92 | AP245: =P245*AN245 -> 1644.8749 | AQ245: =AP245*AO245 -> 13027.409 | AR245: EUR | AS245: 3.312 | AT245: =IF(AR245="EUR",AA245,IF(AR245="GBP",AB245,1)) -> 7.92 | AU245: =T245*AS245 -> 596.78001 | AV245: =AU245*AT245 -> 4726.4977 | AW245: EUR | AX245: 2.3805 | AY245: =IF(AW245="EUR",AA245,IF(AW245="GBP",AB245,1)) -> 7.92 | AZ245: =V245*AX245 -> 144.12237 | BA245: =AZ245*AY245 -> 1141.4492 | BB245: =AF245+AG245+AL245+AQ245+AV245+BA245 -> 116634.15 | BC245: 0.965 | BE245: 正式 Forecast 逐月降低英国空运及 Carrier C 份额，但仍高于 Budget | BF245: 沿用当前正式 Forecast | BG245: UNVERIFIED_UNLIMITED_FOR_MVP
A246: SCENARIO_BASE_2026_08 | B246: SCENARIO | C246: BASE | D246: 46266 | E246: R_DE_DE_B_ROAD | F246: DE | G246: DE_FC | H246: CARRIER_B | I246: ROAD | J246: 17200 | K246: 0.36 | L246: 0.97 | M246: 0.4 | N246: =J246*K246*L246*M246 -> 2402.496 | O246: 1.05 | P246: =N246*O246 -> 2522.6208 | Q246: 0.8 | R246: =P246*Q246 -> 2018.0966 | S246: 0.05 | T246: =N246*S246 -> 120.1248 | U246: 0.013 | V246: =P246*U246 -> 32.79407 | W246: EUR | X246: 2.84625 | Y246: PER_CHARGEABLE_KG | Z246: 0.21735 | AA246: 7.92 | AB246: 9.15 | AC246: =IF(W246="EUR",AA246,IF(W246="GBP",AB246,1)) -> 7.92 | AD246: =R246*X246 -> 5744.0076 | AE246: =IF(Y246="PERCENTAGE_OF_BASE_FREIGHT",AD246*Z246,IF(Y246="PER_CHARGEABLE_KG",R246*Z246,P246*Z246)) -> 438.6333 | AF246: =AD246*AC246 -> 45492.54 | AG246: =AE246*AC246 -> 3473.9758 | AH246: EUR | AI246: 1.3762011 | AJ246: =IF(AH246="EUR",AA246,IF(AH246="GBP",AB246,1)) -> 7.92 | AK246: =N246*AI246 -> 3306.3176 | AL246: =AK246*AJ246 -> 26186.035 | AM246: EUR | AN246: 0.4347 | AO246: =IF(AM246="EUR",AA246,IF(AM246="GBP",AB246,1)) -> 7.92 | AP246: =P246*AN246 -> 1096.5833 | AQ246: =AP246*AO246 -> 8684.9394 | AR246: EUR | AS246: 3.312 | AT246: =IF(AR246="EUR",AA246,IF(AR246="GBP",AB246,1)) -> 7.92 | AU246: =T246*AS246 -> 397.85334 | AV246: =AU246*AT246 -> 3150.9984 | AW246: EUR | AX246: 2.3805 | AY246: =IF(AW246="EUR",AA246,IF(AW246="GBP",AB246,1)) -> 7.92 | AZ246: =V246*AX246 -> 78.066285 | BA246: =AZ246*AY246 -> 618.28497 | BB246: =AF246+AG246+AL246+AQ246+AV246+BA246 -> 87606.774 | BC246: 0.976 | BE246: 正式 Forecast 逐月降低英国空运及 Carrier C 份额，但仍高于 Budget | BF246: 沿用当前正式 Forecast | BG246: UNVERIFIED_UNLIMITED_FOR_MVP
A247: SCENARIO_BASE_2026_08 | B247: SCENARIO | C247: BASE | D247: 46266 | E247: R_DE_FR_B_ROAD | F247: DE | G247: FR_FC | H247: CARRIER_B | I247: ROAD | J247: 17200 | K247: 0.36 | L247: 0.03 | M247: 1 | N247: =J247*K247*L247*M247 -> 185.76 | O247: 1.08 | P247: =N247*O247 -> 200.6208 | Q247: 0.86 | R247: =P247*Q247 -> 172.53389 | S247: 0.05 | T247: =N247*S247 -> 9.288 | U247: 0.014 | V247: =P247*U247 -> 2.8086912 | W247: EUR | X247: 3.4155 | Y247: PER_CHARGEABLE_KG | Z247: 0.2484 | AA247: 7.92 | AB247: 9.15 | AC247: =IF(W247="EUR",AA247,IF(W247="GBP",AB247,1)) -> 7.92 | AD247: =R247*X247 -> 589.28949 | AE247: =IF(Y247="PERCENTAGE_OF_BASE_FREIGHT",AD247*Z247,IF(Y247="PER_CHARGEABLE_KG",R247*Z247,P247*Z247)) -> 42.857418 | AF247: =AD247*AC247 -> 4667.1728 | AG247: =AE247*AC247 -> 339.43075 | AH247: EUR | AI247: 1.08675 | AJ247: =IF(AH247="EUR",AA247,IF(AH247="GBP",AB247,1)) -> 7.92 | AK247: =N247*AI247 -> 201.87468 | AL247: =AK247*AJ247 -> 1598.8475 | AM247: EUR | AN247: 0.3933 | AO247: =IF(AM247="EUR",AA247,IF(AM247="GBP",AB247,1)) -> 7.92 | AP247: =P247*AN247 -> 78.904161 | AQ247: =AP247*AO247 -> 624.92095 | AR247: EUR | AS247: 3.933 | AT247: =IF(AR247="EUR",AA247,IF(AR247="GBP",AB247,1)) -> 7.92 | AU247: =T247*AS247 -> 36.529704 | AV247: =AU247*AT247 -> 289.31526 | AW247: EUR | AX247: 2.3805 | AY247: =IF(AW247="EUR",AA247,IF(AW247="GBP",AB247,1)) -> 7.92 | AZ247: =V247*AX247 -> 6.6860894 | BA247: =AZ247*AY247 -> 52.953828 | BB247: =AF247+AG247+AL247+AQ247+AV247+BA247 -> 7572.641 | BC247: 0.968 | BE247: 正式 Forecast 逐月降低英国空运及 Carrier C 份额，但仍高于 Budget | BF247: 沿用当前正式 Forecast | BG247: UNVERIFIED_UNLIMITED_FOR_MVP
A248: SCENARIO_BASE_2026_08 | B248: SCENARIO | C248: BASE | D248: 46266 | E248: R_FR_FR_A_ROAD | F248: FR | G248: FR_FC | H248: CARRIER_A | I248: ROAD | J248: 17200 | K248: 0.3 | L248: 1 | M248: 0.35 | N248: =J248*K248*L248*M248 -> 1806 | O248: 1.06 | P248: =N248*O248 -> 1914.36 | Q248: 0.76 | R248: =P248*Q248 -> 1454.9136 | S248: 0.06 | T248: =N248*S248 -> 108.36 | U248: 0.017 | V248: =P248*U248 -> 32.54412 | W248: EUR | X248: 2.1735 | Y248: PERCENTAGE_OF_BASE_FREIGHT | Z248: 0.09315 | AA248: 7.92 | AB248: 9.15 | AC248: =IF(W248="EUR",AA248,IF(W248="GBP",AB248,1)) -> 7.92 | AD248: =R248*X248 -> 3162.2547 | AE248: =IF(Y248="PERCENTAGE_OF_BASE_FREIGHT",AD248*Z248,IF(Y248="PER_CHARGEABLE_KG",R248*Z248,P248*Z248)) -> 294.56403 | AF248: =AD248*AC248 -> 25045.057 | AG248: =AE248*AC248 -> 2332.9471 | AH248: EUR | AI248: 1.08675 | AJ248: =IF(AH248="EUR",AA248,IF(AH248="GBP",AB248,1)) -> 7.92 | AK248: =N248*AI248 -> 1962.6705 | AL248: =AK248*AJ248 -> 15544.35 | AM248: EUR | AN248: 0.3933 | AO248: =IF(AM248="EUR",AA248,IF(AM248="GBP",AB248,1)) -> 7.92 | AP248: =P248*AN248 -> 752.91779 | AQ248: =AP248*AO248 -> 5963.1089 | AR248: EUR | AS248: 3.105 | AT248: =IF(AR248="EUR",AA248,IF(AR248="GBP",AB248,1)) -> 7.92 | AU248: =T248*AS248 -> 336.4578 | AV248: =AU248*AT248 -> 2664.7458 | AW248: EUR | AX248: 2.3805 | AY248: =IF(AW248="EUR",AA248,IF(AW248="GBP",AB248,1)) -> 7.92 | AZ248: =V248*AX248 -> 77.471278 | BA248: =AZ248*AY248 -> 613.57252 | BB248: =AF248+AG248+AL248+AQ248+AV248+BA248 -> 52163.782 | BC248: 0.961 | BE248: 正式 Forecast 逐月降低英国空运及 Carrier C 份额，但仍高于 Budget | BF248: 沿用当前正式 Forecast | BG248: UNVERIFIED_UNLIMITED_FOR_MVP
A249: SCENARIO_BASE_2026_08 | B249: SCENARIO | C249: BASE | D249: 46266 | E249: R_FR_FR_B_ROAD | F249: FR | G249: FR_FC | H249: CARRIER_B | I249: ROAD | J249: 17200 | K249: 0.3 | L249: 1 | M249: 0.65 | N249: =J249*K249*L249*M249 -> 3354 | O249: 1.06 | P249: =N249*O249 -> 3555.24 | Q249: 0.79 | R249: =P249*Q249 -> 2808.6396 | S249: 0.06 | T249: =N249*S249 -> 201.24 | U249: 0.014 | V249: =P249*U249 -> 49.77336 | W249: EUR | X249: 2.691 | Y249: PER_CHARGEABLE_KG | Z249: 0.207 | AA249: 7.92 | AB249: 9.15 | AC249: =IF(W249="EUR",AA249,IF(W249="GBP",AB249,1)) -> 7.92 | AD249: =R249*X249 -> 7558.0492 | AE249: =IF(Y249="PERCENTAGE_OF_BASE_FREIGHT",AD249*Z249,IF(Y249="PER_CHARGEABLE_KG",R249*Z249,P249*Z249)) -> 581.3884 | AF249: =AD249*AC249 -> 59859.749 | AG249: =AE249*AC249 -> 4604.5961 | AH249: EUR | AI249: 1.08675 | AJ249: =IF(AH249="EUR",AA249,IF(AH249="GBP",AB249,1)) -> 7.92 | AK249: =N249*AI249 -> 3644.9595 | AL249: =AK249*AJ249 -> 28868.079 | AM249: EUR | AN249: 0.3933 | AO249: =IF(AM249="EUR",AA249,IF(AM249="GBP",AB249,1)) -> 7.92 | AP249: =P249*AN249 -> 1398.2759 | AQ249: =AP249*AO249 -> 11074.345 | AR249: EUR | AS249: 3.105 | AT249: =IF(AR249="EUR",AA249,IF(AR249="GBP",AB249,1)) -> 7.92 | AU249: =T249*AS249 -> 624.8502 | AV249: =AU249*AT249 -> 4948.8136 | AW249: EUR | AX249: 2.3805 | AY249: =IF(AW249="EUR",AA249,IF(AW249="GBP",AB249,1)) -> 7.92 | AZ249: =V249*AX249 -> 118.48548 | BA249: =AZ249*AY249 -> 938.40503 | BB249: =AF249+AG249+AL249+AQ249+AV249+BA249 -> 110293.99 | BC249: 0.973 | BE249: 正式 Forecast 逐月降低英国空运及 Carrier C 份额，但仍高于 Budget | BF249: 沿用当前正式 Forecast | BG249: UNVERIFIED_UNLIMITED_FOR_MVP
A250: SCENARIO_BASE_2026_08 | B250: SCENARIO | C250: BASE | D250: 46266 | E250: R_GB_DE_A_ROAD | F250: GB | G250: DE_FC | H250: CARRIER_A | I250: ROAD | J250: 17200 | K250: 0.34 | L250: 0.96 | M250: 0.3 | N250: =J250*K250*L250*M250 -> 1684.224 | O250: 1.19 | P250: =N250*O250 -> 2004.2266 | Q250: 1.0404 | R250: =P250*Q250 -> 2085.1973 | S250: 0.095 | T250: =N250*S250 -> 160.00128 | U250: 0.027 | V250: =P250*U250 -> 54.114117 | W250: GBP | X250: 4.14 | Y250: PERCENTAGE_OF_BASE_FREIGHT | Z250: 0.1035 | AA250: 7.92 | AB250: 9.15 | AC250: =IF(W250="EUR",AA250,IF(W250="GBP",AB250,1)) -> 9.15 | AD250: =R250*X250 -> 8632.7169 | AE250: =IF(Y250="PERCENTAGE_OF_BASE_FREIGHT",AD250*Z250,IF(Y250="PER_CHARGEABLE_KG",R250*Z250,P250*Z250)) -> 893.4862 | AF250: =AD250*AC250 -> 78989.359 | AG250: =AE250*AC250 -> 8175.3987 | AH250: EUR | AI250: 1.3762011 | AJ250: =IF(AH250="EUR",AA250,IF(AH250="GBP",AB250,1)) -> 7.92 | AK250: =N250*AI250 -> 2317.8309 | AL250: =AK250*AJ250 -> 18357.22 | AM250: EUR | AN250: 0.4347 | AO250: =IF(AM250="EUR",AA250,IF(AM250="GBP",AB250,1)) -> 7.92 | AP250: =P250*AN250 -> 871.23729 | AQ250: =AP250*AO250 -> 6900.1993 | AR250: GBP | AS250: 4.968 | AT250: =IF(AR250="EUR",AA250,IF(AR250="GBP",AB250,1)) -> 9.15 | AU250: =T250*AS250 -> 794.88636 | AV250: =AU250*AT250 -> 7273.2102 | AW250: GBP | AX250: 2.3805 | AY250: =IF(AW250="EUR",AA250,IF(AW250="GBP",AB250,1)) -> 9.15 | AZ250: =V250*AX250 -> 128.81866 | BA250: =AZ250*AY250 -> 1178.6907 | BB250: =AF250+AG250+AL250+AQ250+AV250+BA250 -> 120874.08 | BC250: 0.93 | BE250: 正式 Forecast 逐月降低英国空运及 Carrier C 份额，但仍高于 Budget | BF250: 沿用当前正式 Forecast | BG250: UNVERIFIED_UNLIMITED_FOR_MVP
A251: SCENARIO_BASE_2026_08 | B251: SCENARIO | C251: BASE | D251: 46266 | E251: R_GB_DE_B_ROAD | F251: GB | G251: DE_FC | H251: CARRIER_B | I251: ROAD | J251: 17200 | K251: 0.34 | L251: 0.96 | M251: 0.17 | N251: =J251*K251*L251*M251 -> 954.3936 | O251: 1.19 | P251: =N251*O251 -> 1135.7284 | Q251: 1.02 | R251: =P251*Q251 -> 1158.443 | S251: 0.095 | T251: =N251*S251 -> 90.667392 | U251: 0.02 | V251: =P251*U251 -> 22.714568 | W251: GBP | X251: 4.8645 | Y251: PER_CHARGEABLE_KG | Z251: 0.34155 | AA251: 7.92 | AB251: 9.15 | AC251: =IF(W251="EUR",AA251,IF(W251="GBP",AB251,1)) -> 9.15 | AD251: =R251*X251 -> 5635.2457 | AE251: =IF(Y251="PERCENTAGE_OF_BASE_FREIGHT",AD251*Z251,IF(Y251="PER_CHARGEABLE_KG",R251*Z251,P251*Z251)) -> 395.66619 | AF251: =AD251*AC251 -> 51562.499 | AG251: =AE251*AC251 -> 3620.3456 | AH251: EUR | AI251: 1.3762011 | AJ251: =IF(AH251="EUR",AA251,IF(AH251="GBP",AB251,1)) -> 7.92 | AK251: =N251*AI251 -> 1313.4375 | AL251: =AK251*AJ251 -> 10402.425 | AM251: EUR | AN251: 0.4347 | AO251: =IF(AM251="EUR",AA251,IF(AM251="GBP",AB251,1)) -> 7.92 | AP251: =P251*AN251 -> 493.70113 | AQ251: =AP251*AO251 -> 3910.1129 | AR251: GBP | AS251: 4.968 | AT251: =IF(AR251="EUR",AA251,IF(AR251="GBP",AB251,1)) -> 9.15 | AU251: =T251*AS251 -> 450.4356 | AV251: =AU251*AT251 -> 4121.4858 | AW251: GBP | AX251: 2.3805 | AY251: =IF(AW251="EUR",AA251,IF(AW251="GBP",AB251,1)) -> 9.15 | AZ251: =V251*AX251 -> 54.072028 | BA251: =AZ251*AY251 -> 494.75906 | BB251: =AF251+AG251+AL251+AQ251+AV251+BA251 -> 74111.627 | BC251: 0.95 | BE251: 正式 Forecast 逐月降低英国空运及 Carrier C 份额，但仍高于 Budget | BF251: 沿用当前正式 Forecast | BG251: UNVERIFIED_UNLIMITED_FOR_MVP
A252: SCENARIO_BASE_2026_08 | B252: SCENARIO | C252: BASE | D252: 46266 | E252: R_GB_DE_B_AIR | F252: GB | G252: DE_FC | H252: CARRIER_B | I252: AIR | J252: 17200 | K252: 0.34 | L252: 0.96 | M252: 0.25 | N252: =J252*K252*L252*M252 -> 1403.52 | O252: 1.19 | P252: =N252*O252 -> 1670.1888 | Q252: 0.9588 | R252: =P252*Q252 -> 1601.377 | S252: 0.095 | T252: =N252*S252 -> 133.3344 | U252: 0.016 | V252: =P252*U252 -> 26.723021 | W252: GBP | X252: 6.67368 | Y252: PERCENTAGE_OF_BASE_FREIGHT | Z252: 0.123786 | AA252: 7.92 | AB252: 9.15 | AC252: =IF(W252="EUR",AA252,IF(W252="GBP",AB252,1)) -> 9.15 | AD252: =R252*X252 -> 10687.078 | AE252: =IF(Y252="PERCENTAGE_OF_BASE_FREIGHT",AD252*Z252,IF(Y252="PER_CHARGEABLE_KG",R252*Z252,P252*Z252)) -> 1322.9106 | AF252: =AD252*AC252 -> 97786.762 | AG252: =AE252*AC252 -> 12104.632 | AH252: EUR | AI252: 1.3762011 | AJ252: =IF(AH252="EUR",AA252,IF(AH252="GBP",AB252,1)) -> 7.92 | AK252: =N252*AI252 -> 1931.5257 | AL252: =AK252*AJ252 -> 15297.684 | AM252: EUR | AN252: 0.4347 | AO252: =IF(AM252="EUR",AA252,IF(AM252="GBP",AB252,1)) -> 7.92 | AP252: =P252*AN252 -> 726.03107 | AQ252: =AP252*AO252 -> 5750.1661 | AR252: GBP | AS252: 4.968 | AT252: =IF(AR252="EUR",AA252,IF(AR252="GBP",AB252,1)) -> 9.15 | AU252: =T252*AS252 -> 662.4053 | AV252: =AU252*AT252 -> 6061.0085 | AW252: GBP | AX252: 2.898 | AY252: =IF(AW252="EUR",AA252,IF(AW252="GBP",AB252,1)) -> 9.15 | AZ252: =V252*AX252 -> 77.443314 | BA252: =AZ252*AY252 -> 708.60633 | BB252: =AF252+AG252+AL252+AQ252+AV252+BA252 -> 137708.86 | BC252: 0.974 | BE252: 正式 Forecast 逐月降低英国空运及 Carrier C 份额，但仍高于 Budget | BF252: 沿用当前正式 Forecast | BG252: UNVERIFIED_UNLIMITED_FOR_MVP
A253: SCENARIO_BASE_2026_08 | B253: SCENARIO | C253: BASE | D253: 46266 | E253: R_GB_DE_C_AIR | F253: GB | G253: DE_FC | H253: CARRIER_C | I253: AIR | J253: 17200 | K253: 0.34 | L253: 0.96 | M253: 0.28 | N253: =J253*K253*L253*M253 -> 1571.9424 | O253: 1.19 | P253: =N253*O253 -> 1870.6115 | Q253: 0.9384 | R253: =P253*Q253 -> 1755.3818 | S253: 0.095 | T253: =N253*S253 -> 149.33453 | U253: 0.011 | V253: =P253*U253 -> 20.576726 | W253: GBP | X253: 8.22825 | Y253: PER_CHARGEABLE_KG | Z253: 0.636318 | AA253: 7.92 | AB253: 9.15 | AC253: =IF(W253="EUR",AA253,IF(W253="GBP",AB253,1)) -> 9.15 | AD253: =R253*X253 -> 14443.72 | AE253: =IF(Y253="PERCENTAGE_OF_BASE_FREIGHT",AD253*Z253,IF(Y253="PER_CHARGEABLE_KG",R253*Z253,P253*Z253)) -> 1116.981 | AF253: =AD253*AC253 -> 132160.04 | AG253: =AE253*AC253 -> 10220.376 | AH253: EUR | AI253: 1.3762011 | AJ253: =IF(AH253="EUR",AA253,IF(AH253="GBP",AB253,1)) -> 7.92 | AK253: =N253*AI253 -> 2163.3088 | AL253: =AK253*AJ253 -> 17133.406 | AM253: EUR | AN253: 0.4347 | AO253: =IF(AM253="EUR",AA253,IF(AM253="GBP",AB253,1)) -> 7.92 | AP253: =P253*AN253 -> 813.1548 | AQ253: =AP253*AO253 -> 6440.186 | AR253: GBP | AS253: 4.968 | AT253: =IF(AR253="EUR",AA253,IF(AR253="GBP",AB253,1)) -> 9.15 | AU253: =T253*AS253 -> 741.89394 | AV253: =AU253*AT253 -> 6788.3295 | AW253: GBP | AX253: 3.726 | AY253: =IF(AW253="EUR",AA253,IF(AW253="GBP",AB253,1)) -> 9.15 | AZ253: =V253*AX253 -> 76.668881 | BA253: =AZ253*AY253 -> 701.52026 | BB253: =AF253+AG253+AL253+AQ253+AV253+BA253 -> 173443.86 | BC253: 0.988 | BE253: 正式 Forecast 逐月降低英国空运及 Carrier C 份额，但仍高于 Budget | BF253: 沿用当前正式 Forecast | BG253: UNVERIFIED_UNLIMITED_FOR_MVP
A254: SCENARIO_BASE_2026_08 | B254: SCENARIO | C254: BASE | D254: 46266 | E254: R_GB_FR_B_AIR | F254: GB | G254: FR_FC | H254: CARRIER_B | I254: AIR | J254: 17200 | K254: 0.34 | L254: 0.04 | M254: 1 | N254: =J254*K254*L254*M254 -> 233.92 | O254: 1.17 | P254: =N254*O254 -> 273.6864 | Q254: 0.918 | R254: =P254*Q254 -> 251.24412 | S254: 0.095 | T254: =N254*S254 -> 22.2224 | U254: 0.014 | V254: =P254*U254 -> 3.8316096 | W254: EUR | X254: 6.9345 | Y254: PERCENTAGE_OF_BASE_FREIGHT | Z254: 0.108675 | AA254: 7.92 | AB254: 9.15 | AC254: =IF(W254="EUR",AA254,IF(W254="GBP",AB254,1)) -> 7.92 | AD254: =R254*X254 -> 1742.2523 | AE254: =IF(Y254="PERCENTAGE_OF_BASE_FREIGHT",AD254*Z254,IF(Y254="PER_CHARGEABLE_KG",R254*Z254,P254*Z254)) -> 189.33927 | AF254: =AD254*AC254 -> 13798.638 | AG254: =AE254*AC254 -> 1499.567 | AH254: EUR | AI254: 1.08675 | AJ254: =IF(AH254="EUR",AA254,IF(AH254="GBP",AB254,1)) -> 7.92 | AK254: =N254*AI254 -> 254.21256 | AL254: =AK254*AJ254 -> 2013.3635 | AM254: EUR | AN254: 0.3933 | AO254: =IF(AM254="EUR",AA254,IF(AM254="GBP",AB254,1)) -> 7.92 | AP254: =P254*AN254 -> 107.64086 | AQ254: =AP254*AO254 -> 852.51562 | AR254: EUR | AS254: 5.382 | AT254: =IF(AR254="EUR",AA254,IF(AR254="GBP",AB254,1)) -> 7.92 | AU254: =T254*AS254 -> 119.60096 | AV254: =AU254*AT254 -> 947.23958 | AW254: EUR | AX254: 2.898 | AY254: =IF(AW254="EUR",AA254,IF(AW254="GBP",AB254,1)) -> 7.92 | AZ254: =V254*AX254 -> 11.104005 | BA254: =AZ254*AY254 -> 87.943717 | BB254: =AF254+AG254+AL254+AQ254+AV254+BA254 -> 19199.268 | BC254: 0.971 | BE254: 正式 Forecast 逐月降低英国空运及 Carrier C 份额，但仍高于 Budget | BF254: 沿用当前正式 Forecast | BG254: UNVERIFIED_UNLIMITED_FOR_MVP
A255: SCENARIO_BASE_2026_08 | B255: SCENARIO | C255: BASE | D255: 46296 | E255: R_DE_DE_A_ROAD | F255: DE | G255: DE_FC | H255: CARRIER_A | I255: ROAD | J255: 19500 | K255: 0.34 | L255: 0.97 | M255: 0.6 | N255: =J255*K255*L255*M255 -> 3858.66 | O255: 1.05 | P255: =N255*O255 -> 4051.593 | Q255: 0.7878 | R255: =P255*Q255 -> 3191.845 | S255: 0.05 | T255: =N255*S255 -> 192.933 | U255: 0.016 | V255: =P255*U255 -> 64.825488 | W255: EUR | X255: 2.277 | Y255: PERCENTAGE_OF_BASE_FREIGHT | Z255: 0.098325 | AA255: 7.9 | AB255: 9.1 | AC255: =IF(W255="EUR",AA255,IF(W255="GBP",AB255,1)) -> 7.9 | AD255: =R255*X255 -> 7267.831 | AE255: =IF(Y255="PERCENTAGE_OF_BASE_FREIGHT",AD255*Z255,IF(Y255="PER_CHARGEABLE_KG",R255*Z255,P255*Z255)) -> 714.60948 | AF255: =AD255*AC255 -> 57415.865 | AG255: =AE255*AC255 -> 5645.4149 | AH255: EUR | AI255: 1.3579711 | AJ255: =IF(AH255="EUR",AA255,IF(AH255="GBP",AB255,1)) -> 7.9 | AK255: =N255*AI255 -> 5239.9489 | AL255: =AK255*AJ255 -> 41395.597 | AM255: EUR | AN255: 0.4347 | AO255: =IF(AM255="EUR",AA255,IF(AM255="GBP",AB255,1)) -> 7.9 | AP255: =P255*AN255 -> 1761.2275 | AQ255: =AP255*AO255 -> 13913.697 | AR255: EUR | AS255: 3.312 | AT255: =IF(AR255="EUR",AA255,IF(AR255="GBP",AB255,1)) -> 7.9 | AU255: =T255*AS255 -> 638.9941 | AV255: =AU255*AT255 -> 5048.0534 | AW255: EUR | AX255: 2.3805 | AY255: =IF(AW255="EUR",AA255,IF(AW255="GBP",AB255,1)) -> 7.9 | AZ255: =V255*AX255 -> 154.31707 | BA255: =AZ255*AY255 -> 1219.1049 | BB255: =AF255+AG255+AL255+AQ255+AV255+BA255 -> 124637.73 | BC255: 0.965 | BE255: 正式 Forecast 逐月降低英国空运及 Carrier C 份额，但仍高于 Budget | BF255: 沿用当前正式 Forecast | BG255: UNVERIFIED_UNLIMITED_FOR_MVP
A256: SCENARIO_BASE_2026_08 | B256: SCENARIO | C256: BASE | D256: 46296 | E256: R_DE_DE_B_ROAD | F256: DE | G256: DE_FC | H256: CARRIER_B | I256: ROAD | J256: 19500 | K256: 0.34 | L256: 0.97 | M256: 0.4 | N256: =J256*K256*L256*M256 -> 2572.44 | O256: 1.05 | P256: =N256*O256 -> 2701.062 | Q256: 0.808 | R256: =P256*Q256 -> 2182.4581 | S256: 0.05 | T256: =N256*S256 -> 128.622 | U256: 0.013 | V256: =P256*U256 -> 35.113806 | W256: EUR | X256: 2.84625 | Y256: PER_CHARGEABLE_KG | Z256: 0.21735 | AA256: 7.9 | AB256: 9.1 | AC256: =IF(W256="EUR",AA256,IF(W256="GBP",AB256,1)) -> 7.9 | AD256: =R256*X256 -> 6211.8214 | AE256: =IF(Y256="PERCENTAGE_OF_BASE_FREIGHT",AD256*Z256,IF(Y256="PER_CHARGEABLE_KG",R256*Z256,P256*Z256)) -> 474.35727 | AF256: =AD256*AC256 -> 49073.389 | AG256: =AE256*AC256 -> 3747.4224 | AH256: EUR | AI256: 1.3579711 | AJ256: =IF(AH256="EUR",AA256,IF(AH256="GBP",AB256,1)) -> 7.9 | AK256: =N256*AI256 -> 3493.2993 | AL256: =AK256*AJ256 -> 27597.064 | AM256: EUR | AN256: 0.4347 | AO256: =IF(AM256="EUR",AA256,IF(AM256="GBP",AB256,1)) -> 7.9 | AP256: =P256*AN256 -> 1174.1517 | AQ256: =AP256*AO256 -> 9275.798 | AR256: EUR | AS256: 3.312 | AT256: =IF(AR256="EUR",AA256,IF(AR256="GBP",AB256,1)) -> 7.9 | AU256: =T256*AS256 -> 425.99606 | AV256: =AU256*AT256 -> 3365.3689 | AW256: EUR | AX256: 2.3805 | AY256: =IF(AW256="EUR",AA256,IF(AW256="GBP",AB256,1)) -> 7.9 | AZ256: =V256*AX256 -> 83.588415 | BA256: =AZ256*AY256 -> 660.34848 | BB256: =AF256+AG256+AL256+AQ256+AV256+BA256 -> 93719.391 | BC256: 0.976 | BE256: 正式 Forecast 逐月降低英国空运及 Carrier C 份额，但仍高于 Budget | BF256: 沿用当前正式 Forecast | BG256: UNVERIFIED_UNLIMITED_FOR_MVP
... A364: SCENARIO_COST_SAVING_2026_08 | B364: SCENARIO | C364: COST_SAVING | D364: 46357 | E364: R_GB_FR_B_AIR | F364: GB | G364: FR_FC | H364: CARRIER_B | I364: AIR | J364: 28600 | K364: 0.4 | L364: 0.04 | M364: 1 | N364: =J364*K364*L364*M364 -> 457.6 | O364: 1.17 | P364: =N364*O364 -> 535.392 | Q364: 0.92718 | R364: =P364*Q364 -> 496.40475 | S364: 0.09 | T364: =N364*S364 -> 41.184 | U364: 0.0126 | V364: =P364*U364 -> 6.7459392 | W364: EUR | X364: 6.9345 | Y364: PERCENTAGE_OF_BASE_FREIGHT | Z364: 0.108675 | AA364: 7.86 | AB364: 9 | AC364: =IF(W364="EUR",AA364,IF(W364="GBP",AB364,1)) -> 7.86 | AD364: =R364*X364 -> 3442.3188 | AE364: =IF(Y364="PERCENTAGE_OF_BASE_FREIGHT",AD364*Z364,IF(Y364="PER_CHARGEABLE_KG",R364*Z364,P364*Z364)) -> 374.09399 | AF364: =AD364*AC364 -> 27056.626 | AG364: =AE364*AC364 -> 2940.3788 | AH364: EUR | AI364: 1.08675 | AJ364: =IF(AH364="EUR",AA364,IF(AH364="GBP",AB364,1)) -> 7.86 | AK364: =N364*AI364 -> 497.2968 | AL364: =AK364*AJ364 -> 3908.7528 | AM364: EUR | AN364: 0.3933 | AO364: =IF(AM364="EUR",AA364,IF(AM364="GBP",AB364,1)) -> 7.86 | AP364: =P364*AN364 -> 210.56967 | AQ364: =AP364*AO364 -> 1655.0776 | AR364: EUR | AS364: 5.382 | AT364: =IF(AR364="EUR",AA364,IF(AR364="GBP",AB364,1)) -> 7.86 | AU364: =T364*AS364 -> 221.65229 | AV364: =AU364*AT364 -> 1742.187 | AW364: EUR | AX364: 2.898 | AY364: =IF(AW364="EUR",AA364,IF(AW364="GBP",AB364,1)) -> 7.86 | AZ364: =V364*AX364 -> 19.549732 | BA364: =AZ364*AY364 -> 153.66089 | BB364: =AF364+AG364+AL364+AQ364+AV364+BA364 -> 37456.683 | BC364: 0.971 | BE364: 正式 Forecast 逐月降低英国空运及 Carrier C 份额，但仍高于 Budget | BF364: 仅在现有承运商与有效线路内调整英国运输结构；承运能力未验证；一次性切换成本不适用 | BG364: UNVERIFIED_UNLIMITED_FOR_MVP

Sheet Cost_Facts
A1: 履约变动成本事实
A2: 每条成本事实与 Model_Calc 的线路公式列直接勾稽；Actual 权威金额差异必须为零。
A4: Version | B4: Type | C4: Scenario | D4: Month | E4: Route | F4: Destination | G4: FC | H4: Carrier | I4: Mode | J4: Cost Component | K4: Currency | L4: Original Amount | M4: FX | N4: High Precision CNY (text) | O4: Report CNY | P4: Authority CNY | Q4: Authority Delta | R4: Posting Basis | S4: Model Recalc CNY | T4: Recalc Delta
A5: BUDGET_2026_V1 | B5: BUDGET | D5: 46023 | E5: R_DE_DE_A_ROAD | F5: DE | G5: DE_FC | H5: CARRIER_A | I5: ROAD | J5: BASE_FREIGHT | K5: EUR | L5: 6166.0479 | M5: 7.8 | N5: 48095.17352640000000 | O5: 48095.173 | R5: INVOICE_OR_PLAN | S5: =Model_Calc!AF5 -> 48095.174 | T5: =ROUND(S5-O5,4) -> 0
A6: BUDGET_2026_V1 | B6: BUDGET | D6: 46023 | E6: R_DE_DE_A_ROAD | F6: DE | G6: DE_FC | H6: CARRIER_A | I6: ROAD | J6: FUEL_SURCHARGE | K6: EUR | L6: 585.77455 | M6: 7.8 | N6: 4569.04148500800000000 | O6: 4569.0415 | R6: INVOICE_OR_PLAN | S6: =Model_Calc!AG5 -> 4569.0415 | T6: =ROUND(S6-O6,4) -> 0
A7: BUDGET_2026_V1 | B7: BUDGET | D7: 46023 | E7: R_DE_DE_A_ROAD | F7: DE | G7: DE_FC | H7: CARRIER_A | I7: ROAD | J7: FRONTLINE_VARIABLE_LABOR | K7: EUR | L7: 4038.1488 | M7: 7.8 | N7: 31497.5606400000 | O7: 31497.561 | R7: INVOICE_OR_PLAN | S7: =Model_Calc!AL5 -> 31497.561 | T7: =ROUND(S7-O7,4) -> 0
A8: BUDGET_2026_V1 | B8: BUDGET | D8: 46023 | E8: R_DE_DE_A_ROAD | F8: DE | G8: DE_FC | H8: CARRIER_A | I8: ROAD | J8: PACKAGING | K8: EUR | L8: 1509.1726 | M8: 7.8 | N8: 11771.545968000000 | O8: 11771.546 | R8: INVOICE_OR_PLAN | S8: =Model_Calc!AQ5 -> 11771.546 | T8: =ROUND(S8-O8,4) -> 0
A9: BUDGET_2026_V1 | B9: BUDGET | D9: 46023 | E9: R_DE_DE_A_ROAD | F9: DE | G9: DE_FC | H9: CARRIER_A | I9: ROAD | J9: RETURN_LOGISTICS | K9: EUR | L9: 547.5456 | M9: 7.8 | N9: 4270.8556800000000 | O9: 4270.8557 | R9: INVOICE_OR_PLAN | S9: =Model_Calc!AV5 -> 4270.8557 | T9: =ROUND(S9-O9,4) -> 0
A10: BUDGET_2026_V1 | B10: BUDGET | D10: 46023 | E10: R_DE_DE_A_ROAD | F10: DE | G10: DE_FC | H10: CARRIER_A | I10: ROAD | J10: BILLABLE_EXCEPTION | K10: EUR | L10: 132.23226 | M10: 7.8 | N10: 1031.411646720000000 | O10: 1031.4116 | R10: INVOICE_OR_PLAN | S10: =Model_Calc!BA5 -> 1031.4116 | T10: =ROUND(S10-O10,4) -> 0
A11: BUDGET_2026_V1 | B11: BUDGET | D11: 46023 | E11: R_DE_DE_B_ROAD | F11: DE | G11: DE_FC | H11: CARRIER_B | I11: ROAD | J11: BASE_FREIGHT | K11: EUR | L11: 5270.1264 | M11: 7.8 | N11: 41106.98592000000000 | O11: 41106.986 | R11: INVOICE_OR_PLAN | S11: =Model_Calc!AF6 -> 41106.986 | T11: =ROUND(S11-O11,4) -> 0
A12: BUDGET_2026_V1 | B12: BUDGET | D12: 46023 | E12: R_DE_DE_B_ROAD | F12: DE | G12: DE_FC | H12: CARRIER_B | I12: ROAD | J12: FUEL_SURCHARGE | K12: EUR | L12: 402.44602 | M12: 7.8 | N12: 3139.07892480000000 | O12: 3139.0789 | R12: INVOICE_OR_PLAN | S12: =Model_Calc!AG6 -> 3139.0789 | T12: =ROUND(S12-O12,4) -> 0
A13: BUDGET_2026_V1 | B13: BUDGET | D13: 46023 | E13: R_DE_DE_B_ROAD | F13: DE | G13: DE_FC | H13: CARRIER_B | I13: ROAD | J13: FRONTLINE_VARIABLE_LABOR | K13: EUR | L13: 2692.0992 | M13: 7.8 | N13: 20998.3737600000 | O13: 20998.374 | R13: INVOICE_OR_PLAN | S13: =Model_Calc!AL6 -> 20998.374 | T13: =ROUND(S13-O13,4) -> 0
A14: BUDGET_2026_V1 | B14: BUDGET | D14: 46023 | E14: R_DE_DE_B_ROAD | F14: DE | G14: DE_FC | H14: CARRIER_B | I14: ROAD | J14: PACKAGING | K14: EUR | L14: 1006.115 | M14: 7.8 | N14: 7847.697312000000 | O14: 7847.6973 | R14: INVOICE_OR_PLAN | S14: =Model_Calc!AQ6 -> 7847.6973 | T14: =ROUND(S14-O14,4) -> 0
A15: BUDGET_2026_V1 | B15: BUDGET | D15: 46023 | E15: R_DE_DE_B_ROAD | F15: DE | G15: DE_FC | H15: CARRIER_B | I15: ROAD | J15: RETURN_LOGISTICS | K15: EUR | L15: 365.0304 | M15: 7.8 | N15: 2847.2371200000000 | O15: 2847.2371 | R15: INVOICE_OR_PLAN | S15: =Model_Calc!AV6 -> 2847.2371 | T15: =ROUND(S15-O15,4) -> 0
A16: BUDGET_2026_V1 | B16: BUDGET | D16: 46023 | E16: R_DE_DE_B_ROAD | F16: DE | G16: DE_FC | H16: CARRIER_B | I16: ROAD | J16: BILLABLE_EXCEPTION | K16: EUR | L16: 71.625809 | M16: 7.8 | N16: 558.681308640000000 | O16: 558.6813 | R16: INVOICE_OR_PLAN | S16: =Model_Calc!BA6 -> 558.68131 | T16: =ROUND(S16-O16,4) -> 0
A17: BUDGET_2026_V1 | B17: BUDGET | D17: 46023 | E17: R_DE_FR_B_ROAD | F17: DE | G17: FR_FC | H17: CARRIER_B | I17: ROAD | J17: BASE_FREIGHT | K17: EUR | L17: 540.67306 | M17: 7.8 | N17: 4217.249836800000 | O17: 4217.2498 | R17: INVOICE_OR_PLAN | S17: =Model_Calc!AF7 -> 4217.2498 | T17: =ROUND(S17-O17,4) -> 0
A18: BUDGET_2026_V1 | B18: BUDGET | D18: 46023 | E18: R_DE_FR_B_ROAD | F18: DE | G18: FR_FC | H18: CARRIER_B | I18: ROAD | J18: FUEL_SURCHARGE | K18: EUR | L18: 39.321677 | M18: 7.8 | N18: 306.709079040000 | O18: 306.7091 | R18: INVOICE_OR_PLAN | S18: =Model_Calc!AG7 -> 306.70908 | T18: =ROUND(S18-O18,4) -> 0
A19: BUDGET_2026_V1 | B19: BUDGET | D19: 46023 | E19: R_DE_FR_B_ROAD | F19: DE | G19: FR_FC | H19: CARRIER_B | I19: ROAD | J19: FRONTLINE_VARIABLE_LABOR | K19: EUR | L19: 185.22 | M19: 7.8 | N19: 1444.71600000 | O19: 1444.716 | R19: INVOICE_OR_PLAN | S19: =Model_Calc!AL7 -> 1444.716 | T19: =ROUND(S19-O19,4) -> 0
A20: BUDGET_2026_V1 | B20: BUDGET | D20: 46023 | E20: R_DE_FR_B_ROAD | F20: DE | G20: FR_FC | H20: CARRIER_B | I20: ROAD | J20: PACKAGING | K20: EUR | L20: 72.39456 | M20: 7.8 | N20: 564.6775680000 | O20: 564.6776 | R20: INVOICE_OR_PLAN | S20: =Model_Calc!AQ7 -> 564.67757 | T20: =ROUND(S20-O20,4) -> 0
A21: BUDGET_2026_V1 | B21: BUDGET | D21: 46023 | E21: R_DE_FR_B_ROAD | F21: DE | G21: FR_FC | H21: CARRIER_B | I21: ROAD | J21: RETURN_LOGISTICS | K21: EUR | L21: 33.516 | M21: 7.8 | N21: 261.42480000000 | O21: 261.4248 | R21: INVOICE_OR_PLAN | S21: =Model_Calc!AV7 -> 261.4248 | T21: =ROUND(S21-O21,4) -> 0
A22: BUDGET_2026_V1 | B22: BUDGET | D22: 46023 | E22: R_DE_FR_B_ROAD | F22: DE | G22: FR_FC | H22: CARRIER_B | I22: ROAD | J22: BILLABLE_EXCEPTION | K22: EUR | L22: 6.1344864 | M22: 7.8 | N22: 47.8489939200000 | O22: 47.849 | R22: INVOICE_OR_PLAN | S22: =Model_Calc!BA7 -> 47.848994 | T22: =ROUND(S22-O22,4) -> 0
A23: BUDGET_2026_V1 | B23: BUDGET | D23: 46023 | E23: R_FR_FR_A_ROAD | F23: FR | G23: FR_FC | H23: CARRIER_A | I23: ROAD | J23: BASE_FREIGHT | K23: EUR | L23: 2652.6797 | M23: 7.8 | N23: 20690.901504000000 | O23: 20690.901 | R23: INVOICE_OR_PLAN | S23: =Model_Calc!AF8 -> 20690.902 | T23: =ROUND(S23-O23,4) -> 0
A24: BUDGET_2026_V1 | B24: BUDGET | D24: 46023 | E24: R_FR_FR_A_ROAD | F24: FR | G24: FR_FC | H24: CARRIER_A | I24: ROAD | J24: FUEL_SURCHARGE | K24: EUR | L24: 238.74117 | M24: 7.8 | N24: 1862.181135360000000 | O24: 1862.1811 | R24: INVOICE_OR_PLAN | S24: =Model_Calc!AG8 -> 1862.1811 | T24: =ROUND(S24-O24,4) -> 0
A25: BUDGET_2026_V1 | B25: BUDGET | D25: 46023 | E25: R_FR_FR_A_ROAD | F25: FR | G25: FR_FC | H25: CARRIER_A | I25: ROAD | J25: FRONTLINE_VARIABLE_LABOR | K25: EUR | L25: 1646.4 | M25: 7.8 | N25: 12841.92000000 | O25: 12841.92 | R25: INVOICE_OR_PLAN | S25: =Model_Calc!AL8 -> 12841.92 | T25: =ROUND(S25-O25,4) -> 0
A26: BUDGET_2026_V1 | B26: BUDGET | D26: 46023 | E26: R_FR_FR_A_ROAD | F26: FR | G26: FR_FC | H26: CARRIER_A | I26: ROAD | J26: PACKAGING | K26: EUR | L26: 631.5904 | M26: 7.8 | N26: 4926.4051200000 | O26: 4926.4051 | R26: INVOICE_OR_PLAN | S26: =Model_Calc!AQ8 -> 4926.4051 | T26: =ROUND(S26-O26,4) -> 0
A27: BUDGET_2026_V1 | B27: BUDGET | D27: 46023 | E27: R_FR_FR_A_ROAD | F27: FR | G27: FR_FC | H27: CARRIER_A | I27: ROAD | J27: RETURN_LOGISTICS | K27: EUR | L27: 282.24 | M27: 7.8 | N27: 2201.47200000000 | O27: 2201.472 | R27: INVOICE_OR_PLAN | S27: =Model_Calc!AV8 -> 2201.472 | T27: =ROUND(S27-O27,4) -> 0
A28: BUDGET_2026_V1 | B28: BUDGET | D28: 46023 | E28: R_FR_FR_A_ROAD | F28: FR | G28: FR_FC | H28: CARRIER_A | I28: ROAD | J28: BILLABLE_EXCEPTION | K28: EUR | L28: 64.987328 | M28: 7.8 | N28: 506.9011584000000 | O28: 506.9012 | R28: INVOICE_OR_PLAN | S28: =Model_Calc!BA8 -> 506.90116 | T28: =ROUND(S28-O28,4) -> 0
A29: BUDGET_2026_V1 | B29: BUDGET | D29: 46023 | E29: R_FR_FR_B_ROAD | F29: FR | G29: FR_FC | H29: CARRIER_B | I29: ROAD | J29: BASE_FREIGHT | K29: EUR | L29: 6340.1229 | M29: 7.8 | N29: 49452.958464000000 | O29: 49452.959 | R29: INVOICE_OR_PLAN | S29: =Model_Calc!AF9 -> 49452.958 | T29: =ROUND(S29-O29,4) -> 0
A30: BUDGET_2026_V1 | B30: BUDGET | D30: 46023 | E30: R_FR_FR_B_ROAD | F30: FR | G30: FR_FC | H30: CARRIER_B | I30: ROAD | J30: FUEL_SURCHARGE | K30: EUR | L30: 487.70176 | M30: 7.8 | N30: 3804.073728000000 | O30: 3804.0737 | R30: INVOICE_OR_PLAN | S30: =Model_Calc!AG9 -> 3804.0737 | T30: =ROUND(S30-O30,4) -> 0
A31: BUDGET_2026_V1 | B31: BUDGET | D31: 46023 | E31: R_FR_FR_B_ROAD | F31: FR | G31: FR_FC | H31: CARRIER_B | I31: ROAD | J31: FRONTLINE_VARIABLE_LABOR | K31: EUR | L31: 3057.6 | M31: 7.8 | N31: 23849.28000000 | O31: 23849.28 | R31: INVOICE_OR_PLAN | S31: =Model_Calc!AL9 -> 23849.28 | T31: =ROUND(S31-O31,4) -> 0
A32: BUDGET_2026_V1 | B32: BUDGET | D32: 46023 | E32: R_FR_FR_B_ROAD | F32: FR | G32: FR_FC | H32: CARRIER_B | I32: ROAD | J32: PACKAGING | K32: EUR | L32: 1172.9536 | M32: 7.8 | N32: 9149.0380800000 | O32: 9149.0381 | R32: INVOICE_OR_PLAN | S32: =Model_Calc!AQ9 -> 9149.0381 | T32: =ROUND(S32-O32,4) -> 0
A33: BUDGET_2026_V1 | B33: BUDGET | D33: 46023 | E33: R_FR_FR_B_ROAD | F33: FR | G33: FR_FC | H33: CARRIER_B | I33: ROAD | J33: RETURN_LOGISTICS | K33: EUR | L33: 524.16 | M33: 7.8 | N33: 4088.44800000000 | O33: 4088.448 | R33: INVOICE_OR_PLAN | S33: =Model_Calc!AV9 -> 4088.448 | T33: =ROUND(S33-O33,4) -> 0
A34: BUDGET_2026_V1 | B34: BUDGET | D34: 46023 | E34: R_FR_FR_B_ROAD | F34: FR | G34: FR_FC | H34: CARRIER_B | I34: ROAD | J34: BILLABLE_EXCEPTION | K34: EUR | L34: 99.392384 | M34: 7.8 | N34: 775.2605952000000 | O34: 775.2606 | R34: INVOICE_OR_PLAN | S34: =Model_Calc!BA9 -> 775.2606 | T34: =ROUND(S34-O34,4) -> 0
A35: BUDGET_2026_V1 | B35: BUDGET | D35: 46023 | E35: R_GB_DE_A_ROAD | F35: GB | G35: DE_FC | H35: CARRIER_A | I35: ROAD | J35: BASE_FREIGHT | K35: GBP | L35: 10379.207 | M35: 9 | N35: 93412.85990400000000 | O35: 93412.86 | R35: INVOICE_OR_PLAN | S35: =Model_Calc!AF10 -> 93412.86 | T35: =ROUND(S35-O35,4) -> 0
A36: BUDGET_2026_V1 | B36: BUDGET | D36: 46023 | E36: R_GB_DE_A_ROAD | F36: GB | G36: DE_FC | H36: CARRIER_A | I36: ROAD | J36: FUEL_SURCHARGE | K36: GBP | L36: 1037.9207 | M36: 9 | N36: 9341.28599040000000000 | O36: 9341.286 | R36: INVOICE_OR_PLAN | S36: =Model_Calc!AG10 -> 9341.286 | T36: =ROUND(S36-O36,4) -> 0
A37: BUDGET_2026_V1 | B37: BUDGET | D37: 46023 | E37: R_GB_DE_A_ROAD | F37: GB | G37: DE_FC | H37: CARRIER_A | I37: ROAD | J37: FRONTLINE_VARIABLE_LABOR | K37: EUR | L37: 2680.2048 | M37: 7.8 | N37: 20905.5974400000 | O37: 20905.597 | R37: INVOICE_OR_PLAN | S37: =Model_Calc!AL10 -> 20905.597 | T37: =ROUND(S37-O37,4) -> 0
A38: BUDGET_2026_V1 | B38: BUDGET | D38: 46023 | E38: R_GB_DE_A_ROAD | F38: GB | G38: DE_FC | H38: CARRIER_A | I38: ROAD | J38: PACKAGING | K38: EUR | L38: 1068.4477 | M38: 7.8 | N38: 8333.892403200000 | O38: 8333.8924 | R38: INVOICE_OR_PLAN | S38: =Model_Calc!AQ10 -> 8333.8924 | T38: =ROUND(S38-O38,4) -> 0
A39: BUDGET_2026_V1 | B39: BUDGET | D39: 46023 | E39: R_GB_DE_A_ROAD | F39: GB | G39: DE_FC | H39: CARRIER_A | I39: ROAD | J39: RETURN_LOGISTICS | K39: GBP | L39: 872.20224 | M39: 9 | N39: 7849.8201600000000 | O39: 7849.8202 | R39: INVOICE_OR_PLAN | S39: =Model_Calc!AV10 -> 7849.8202 | T39: =ROUND(S39-O39,4) -> 0
A40: BUDGET_2026_V1 | B40: BUDGET | D40: 46023 | E40: R_GB_DE_A_ROAD | F40: GB | G40: DE_FC | H40: CARRIER_A | I40: ROAD | J40: BILLABLE_EXCEPTION | K40: GBP | L40: 128.72251 | M40: 9 | N40: 1158.502625280000000 | O40: 1158.5026 | R40: INVOICE_OR_PLAN | S40: =Model_Calc!BA10 -> 1158.5026 | T40: =ROUND(S40-O40,4) -> 0
A41: BUDGET_2026_V1 | B41: BUDGET | D41: 46023 | E41: R_GB_DE_B_ROAD | F41: GB | G41: DE_FC | H41: CARRIER_B | I41: ROAD | J41: BASE_FREIGHT | K41: GBP | L41: 4598.6304 | M41: 9 | N41: 41387.67360000000000 | O41: 41387.674 | R41: INVOICE_OR_PLAN | S41: =Model_Calc!AF11 -> 41387.674 | T41: =ROUND(S41-O41,4) -> 0
A42: BUDGET_2026_V1 | B42: BUDGET | D42: 46023 | E42: R_GB_DE_B_ROAD | F42: GB | G42: DE_FC | H42: CARRIER_B | I42: ROAD | J42: FUEL_SURCHARGE | K42: GBP | L42: 322.88256 | M42: 9 | N42: 2905.94304000000000 | O42: 2905.943 | R42: INVOICE_OR_PLAN | S42: =Model_Calc!AG11 -> 2905.943 | T42: =ROUND(S42-O42,4) -> 0
A43: BUDGET_2026_V1 | B43: BUDGET | D43: 46023 | E43: R_GB_DE_B_ROAD | F43: GB | G43: DE_FC | H43: CARRIER_B | I43: ROAD | J43: FRONTLINE_VARIABLE_LABOR | K43: EUR | L43: 1030.848 | M43: 7.8 | N43: 8040.6144000000 | O43: 8040.6144 | R43: INVOICE_OR_PLAN | S43: =Model_Calc!AL11 -> 8040.6144 | T43: =ROUND(S43-O43,4) -> 0
A44: BUDGET_2026_V1 | B44: BUDGET | D44: 46023 | E44: R_GB_DE_B_ROAD | F44: GB | G44: DE_FC | H44: CARRIER_B | I44: ROAD | J44: PACKAGING | K44: EUR | L44: 410.94144 | M44: 7.8 | N44: 3205.343232000000 | O44: 3205.3432 | R44: INVOICE_OR_PLAN | S44: =Model_Calc!AQ11 -> 3205.3432 | T44: =ROUND(S44-O44,4) -> 0
A45: BUDGET_2026_V1 | B45: BUDGET | D45: 46023 | E45: R_GB_DE_B_ROAD | F45: GB | G45: DE_FC | H45: CARRIER_B | I45: ROAD | J45: RETURN_LOGISTICS | K45: GBP | L45: 335.4624 | M45: 9 | N45: 3019.1616000000000 | O45: 3019.1616 | R45: INVOICE_OR_PLAN | S45: =Model_Calc!AV11 -> 3019.1616 | T45: =ROUND(S45-O45,4) -> 0
A46: BUDGET_2026_V1 | B46: BUDGET | D46: 46023 | E46: R_GB_DE_B_ROAD | F46: GB | G46: DE_FC | H46: CARRIER_B | I46: ROAD | J46: BILLABLE_EXCEPTION | K46: GBP | L46: 38.256691 | M46: 9 | N46: 344.310220800000000 | O46: 344.3102 | R46: INVOICE_OR_PLAN | S46: =Model_Calc!BA11 -> 344.31022 | T46: =ROUND(S46-O46,4) -> 0
A47: BUDGET_2026_V1 | B47: BUDGET | D47: 46023 | E47: R_GB_DE_B_AIR | F47: GB | G47: DE_FC | H47: CARRIER_B | I47: AIR | J47: BASE_FREIGHT | K47: GBP | L47: 1596.6445 | M47: 9 | N47: 14369.80027392000000 | O47: 14369.8 | R47: INVOICE_OR_PLAN | S47: =Model_Calc!AF12 -> 14369.8 | T47: =ROUND(S47-O47,4) -> 0
A48: BUDGET_2026_V1 | B48: BUDGET | D48: 46023 | E48: R_GB_DE_B_AIR | F48: GB | G48: DE_FC | H48: CARRIER_B | I48: AIR | J48: FUEL_SURCHARGE | K48: GBP | L48: 183.61411 | M48: 9 | N48: 1652.52703150080000000 | O48: 1652.527 | R48: INVOICE_OR_PLAN | S48: =Model_Calc!AG12 -> 1652.527 | T48: =ROUND(S48-O48,4) -> 0
A49: BUDGET_2026_V1 | B49: BUDGET | D49: 46023 | E49: R_GB_DE_B_AIR | F49: GB | G49: DE_FC | H49: CARRIER_B | I49: AIR | J49: FRONTLINE_VARIABLE_LABOR | K49: EUR | L49: 288.63744 | M49: 7.8 | N49: 2251.3720320000 | O49: 2251.372 | R49: INVOICE_OR_PLAN | S49: =Model_Calc!AL12 -> 2251.372 | T49: =ROUND(S49-O49,4) -> 0
A50: BUDGET_2026_V1 | B50: BUDGET | D50: 46023 | E50: R_GB_DE_B_AIR | F50: GB | G50: DE_FC | H50: CARRIER_B | I50: AIR | J50: PACKAGING | K50: EUR | L50: 115.0636 | M50: 7.8 | N50: 897.496104960000 | O50: 897.4961 | R50: INVOICE_OR_PLAN | S50: =Model_Calc!AQ12 -> 897.4961 | T50: =ROUND(S50-O50,4) -> 0
A51: BUDGET_2026_V1 | B51: BUDGET | D51: 46023 | E51: R_GB_DE_B_AIR | F51: GB | G51: DE_FC | H51: CARRIER_B | I51: AIR | J51: RETURN_LOGISTICS | K51: GBP | L51: 93.929472 | M51: 9 | N51: 845.3652480000000 | O51: 845.3652 | R51: INVOICE_OR_PLAN | S51: =Model_Calc!AV12 -> 845.36525 | T51: =ROUND(S51-O51,4) -> 0
A52: BUDGET_2026_V1 | B52: BUDGET | D52: 46023 | E52: R_GB_DE_B_AIR | F52: GB | G52: DE_FC | H52: CARRIER_B | I52: AIR | J52: BILLABLE_EXCEPTION | K52: GBP | L52: 9.9721789 | M52: 9 | N52: 89.749610496000000 | O52: 89.7496 | R52: INVOICE_OR_PLAN | S52: =Model_Calc!BA12 -> 89.74961 | T52: =ROUND(S52-O52,4) -> 0
A53: BUDGET_2026_V1 | B53: BUDGET | D53: 46023 | E53: R_GB_DE_C_AIR | F53: GB | G53: DE_FC | H53: CARRIER_C | I53: AIR | J53: BASE_FREIGHT | K53: GBP | L53: 810.1417 | M53: 9 | N53: 7291.27526400000000 | O53: 7291.2753 | R53: INVOICE_OR_PLAN | S53: =Model_Calc!AF13 -> 7291.2753 | T53: =ROUND(S53-O53,4) -> 0
A54: BUDGET_2026_V1 | B54: BUDGET | D54: 46023 | E54: R_GB_DE_C_AIR | F54: GB | G54: DE_FC | H54: CARRIER_C | I54: AIR | J54: FUEL_SURCHARGE | K54: GBP | L54: 62.650958 | M54: 9 | N54: 563.85862041600000 | O54: 563.8586 | R54: INVOICE_OR_PLAN | S54: =Model_Calc!AG13 -> 563.85862 | T54: =ROUND(S54-O54,4) -> 0
A55: BUDGET_2026_V1 | B55: BUDGET | D55: 46023 | E55: R_GB_DE_C_AIR | F55: GB | G55: DE_FC | H55: CARRIER_C | I55: AIR | J55: FRONTLINE_VARIABLE_LABOR | K55: EUR | L55: 123.70176 | M55: 7.8 | N55: 964.8737280000 | O55: 964.8737 | R55: INVOICE_OR_PLAN | S55: =Model_Calc!AL13 -> 964.87373 | T55: =ROUND(S55-O55,4) -> 0
A56: BUDGET_2026_V1 | B56: BUDGET | D56: 46023 | E56: R_GB_DE_C_AIR | F56: GB | G56: DE_FC | H56: CARRIER_C | I56: AIR | J56: PACKAGING | K56: EUR | L56: 49.312973 | M56: 7.8 | N56: 384.641187840000 | O56: 384.6412 | R56: INVOICE_OR_PLAN | S56: =Model_Calc!AQ13 -> 384.64119 | T56: =ROUND(S56-O56,4) -> 0
A57: BUDGET_2026_V1 | B57: BUDGET | D57: 46023 | E57: R_GB_DE_C_AIR | F57: GB | G57: DE_FC | H57: CARRIER_C | I57: AIR | J57: RETURN_LOGISTICS | K57: GBP | L57: 40.255488 | M57: 9 | N57: 362.2993920000000 | O57: 362.2994 | R57: INVOICE_OR_PLAN | S57: =Model_Calc!AV13 -> 362.29939 | T57: =ROUND(S57-O57,4) -> 0
A58: BUDGET_2026_V1 | B58: BUDGET | D58: 46023 | E58: R_GB_DE_C_AIR | F58: GB | G58: DE_FC | H58: CARRIER_C | I58: AIR | J58: BILLABLE_EXCEPTION | K58: GBP | L58: 3.8041436 | M58: 9 | N58: 34.237292544000000 | O58: 34.2373 | R58: INVOICE_OR_PLAN | S58: =Model_Calc!BA13 -> 34.237293 | T58: =ROUND(S58-O58,4) -> 0
A59: BUDGET_2026_V1 | B59: BUDGET | D59: 46023 | E59: R_GB_FR_B_AIR | F59: GB | G59: FR_FC | H59: CARRIER_B | I59: AIR | J59: BASE_FREIGHT | K59: EUR | L59: 1009.6632 | M59: 7.8 | N59: 7875.372960000000 | O59: 7875.373 | R59: INVOICE_OR_PLAN | S59: =Model_Calc!AF14 -> 7875.373 | T59: =ROUND(S59-O59,4) -> 0
A60: BUDGET_2026_V1 | B60: BUDGET | D60: 46023 | E60: R_GB_FR_B_AIR | F60: GB | G60: FR_FC | H60: CARRIER_B | I60: AIR | J60: FUEL_SURCHARGE | K60: EUR | L60: 106.01464 | M60: 7.8 | N60: 826.914160800000000 | O60: 826.9142 | R60: INVOICE_OR_PLAN | S60: =Model_Calc!AG14 -> 826.91416 | T60: =ROUND(S60-O60,4) -> 0
A61: BUDGET_2026_V1 | B61: BUDGET | D61: 46023 | E61: R_GB_FR_B_AIR | F61: GB | G61: FR_FC | H61: CARRIER_B | I61: AIR | J61: FRONTLINE_VARIABLE_LABOR | K61: EUR | L61: 152.88 | M61: 7.8 | N61: 1192.46400000 | O61: 1192.464 | R61: INVOICE_OR_PLAN | S61: =Model_Calc!AL14 -> 1192.464 | T61: =ROUND(S61-O61,4) -> 0
A62: BUDGET_2026_V1 | B62: BUDGET | D62: 46023 | E62: R_GB_FR_B_AIR | F62: GB | G62: FR_FC | H62: CARRIER_B | I62: AIR | J62: PACKAGING | K62: EUR | L62: 63.6272 | M62: 7.8 | N62: 496.2921600000 | O62: 496.2922 | R62: INVOICE_OR_PLAN | S62: =Model_Calc!AQ14 -> 496.29216 | T62: =ROUND(S62-O62,4) -> 0
A63: BUDGET_2026_V1 | B63: BUDGET | D63: 46023 | E63: R_GB_FR_B_AIR | F63: GB | G63: FR_FC | H63: CARRIER_B | I63: AIR | J63: RETURN_LOGISTICS | K63: EUR | L63: 60.5696 | M63: 7.8 | N63: 472.44288000000 | O63: 472.4429 | R63: INVOICE_OR_PLAN | S63: =Model_Calc!AV14 -> 472.44288 | T63: =ROUND(S63-O63,4) -> 0
A64: BUDGET_2026_V1 | B64: BUDGET | D64: 46023 | E64: R_GB_FR_B_AIR | F64: GB | G64: FR_FC | H64: CARRIER_B | I64: AIR | J64: BILLABLE_EXCEPTION | K64: EUR | L64: 5.625984 | M64: 7.8 | N64: 43.8826752000000 | O64: 43.8827 | R64: INVOICE_OR_PLAN | S64: =Model_Calc!BA14 -> 43.882675 | T64: =ROUND(S64-O64,4) -> 0
A65: BUDGET_2026_V1 | B65: BUDGET | D65: 46054 | E65: R_DE_DE_A_ROAD | F65: DE | G65: DE_FC | H65: CARRIER_A | I65: ROAD | J65: BASE_FREIGHT | K65: EUR | L65: 5945.8319 | M65: 7.8 | N65: 46377.48875760000000 | O65: 46377.489 | R65: INVOICE_OR_PLAN | S65: =Model_Calc!AF15 -> 46377.489 | T65: =ROUND(S65-O65,4) -> 0
A66: BUDGET_2026_V1 | B66: BUDGET | D66: 46054 | E66: R_DE_DE_A_ROAD | F66: DE | G66: DE_FC | H66: CARRIER_A | I66: ROAD | J66: FUEL_SURCHARGE | K66: EUR | L66: 564.85403 | M66: 7.8 | N66: 4405.86143197200000000 | O66: 4405.8614 | R66: INVOICE_OR_PLAN | S66: =Model_Calc!AG15 -> 4405.8614 | T66: =ROUND(S66-O66,4) -> 0
A67: BUDGET_2026_V1 | B67: BUDGET | D67: 46054 | E67: R_DE_DE_A_ROAD | F67: DE | G67: DE_FC | H67: CARRIER_A | I67: ROAD | J67: FRONTLINE_VARIABLE_LABOR | K67: EUR | L67: 3893.9292 | M67: 7.8 | N67: 30372.6477600000 | O67: 30372.648 | R67: INVOICE_OR_PLAN | S67: =Model_Calc!AL15 -> 30372.648 | T67: =ROUND(S67-O67,4) -> 0
A68: BUDGET_2026_V1 | B68: BUDGET | D68: 46054 | E68: R_DE_DE_A_ROAD | F68: DE | G68: DE_FC | H68: CARRIER_A | I68: ROAD | J68: PACKAGING | K68: EUR | L68: 1455.2735 | M68: 7.8 | N68: 11351.133612000000 | O68: 11351.134 | R68: INVOICE_OR_PLAN | S68: =Model_Calc!AQ15 -> 11351.134 | T68: =ROUND(S68-O68,4) -> 0
A69: BUDGET_2026_V1 | B69: BUDGET | D69: 46054 | E69: R_DE_DE_A_ROAD | F69: DE | G69: DE_FC | H69: CARRIER_A | I69: ROAD | J69: RETURN_LOGISTICS | K69: EUR | L69: 527.9904 | M69: 7.8 | N69: 4118.3251200000000 | O69: 4118.3251 | R69: INVOICE_OR_PLAN | S69: =Model_Calc!AV15 -> 4118.3251 | T69: =ROUND(S69-O69,4) -> 0
A70: BUDGET_2026_V1 | B70: BUDGET | D70: 46054 | E70: R_DE_DE_A_ROAD | F70: DE | G70: DE_FC | H70: CARRIER_A | I70: ROAD | J70: BILLABLE_EXCEPTION | K70: EUR | L70: 127.50968 | M70: 7.8 | N70: 994.575516480000000 | O70: 994.5755 | R70: INVOICE_OR_PLAN | S70: =Model_Calc!BA15 -> 994.57552 | T70: =ROUND(S70-O70,4) -> 0
A71: BUDGET_2026_V1 | B71: BUDGET | D71: 46054 | E71: R_DE_DE_B_ROAD | F71: DE | G71: DE_FC | H71: CARRIER_B | I71: ROAD | J71: BASE_FREIGHT | K71: EUR | L71: 5081.9076 | M71: 7.8 | N71: 39638.87928000000000 | O71: 39638.879 | R71: INVOICE_OR_PLAN | S71: =Model_Calc!AF16 -> 39638.879 | T71: =ROUND(S71-O71,4) -> 0
A72: BUDGET_2026_V1 | B72: BUDGET | D72: 46054 | E72: R_DE_DE_B_ROAD | F72: DE | G72: DE_FC | H72: CARRIER_B | I72: ROAD | J72: FUEL_SURCHARGE | K72: EUR | L72: 388.07294 | M72: 7.8 | N72: 3026.96896320000000 | O72: 3026.969 | R72: INVOICE_OR_PLAN | S72: =Model_Calc!AG16 -> 3026.969 | T72: =ROUND(S72-O72,4) -> 0
A73: BUDGET_2026_V1 | B73: BUDGET | D73: 46054 | E73: R_DE_DE_B_ROAD | F73: DE | G73: DE_FC | H73: CARRIER_B | I73: ROAD | J73: FRONTLINE_VARIABLE_LABOR | K73: EUR | L73: 2595.9528 | M73: 7.8 | N73: 20248.4318400000 | O73: 20248.432 | R73: INVOICE_OR_PLAN | S73: =Model_Calc!AL16 -> 20248.432 | T73: =ROUND(S73-O73,4) -> 0
A74: BUDGET_2026_V1 | B74: BUDGET | D74: 46054 | E74: R_DE_DE_B_ROAD | F74: DE | G74: DE_FC | H74: CARRIER_B | I74: ROAD | J74: PACKAGING | K74: EUR | L74: 970.18236 | M74: 7.8 | N74: 7567.422408000000 | O74: 7567.4224 | R74: INVOICE_OR_PLAN | S74: =Model_Calc!AQ16 -> 7567.4224 | T74: =ROUND(S74-O74,4) -> 0
A75: BUDGET_2026_V1 | B75: BUDGET | D75: 46054 | E75: R_DE_DE_B_ROAD | F75: DE | G75: DE_FC | H75: CARRIER_B | I75: ROAD | J75: RETURN_LOGISTICS | K75: EUR | L75: 351.9936 | M75: 7.8 | N75: 2745.5500800000000 | O75: 2745.5501 | R75: INVOICE_OR_PLAN | S75: =Model_Calc!AV16 -> 2745.5501 | T75: =ROUND(S75-O75,4) -> 0
A76: BUDGET_2026_V1 | B76: BUDGET | D76: 46054 | E76: R_DE_DE_B_ROAD | F76: DE | G76: DE_FC | H76: CARRIER_B | I76: ROAD | J76: BILLABLE_EXCEPTION | K76: EUR | L76: 69.067744 | M76: 7.8 | N76: 538.728404760000000 | O76: 538.7284 | R76: INVOICE_OR_PLAN | S76: =Model_Calc!BA16 -> 538.7284 | T76: =ROUND(S76-O76,4) -> 0
A77: BUDGET_2026_V1 | B77: BUDGET | D77: 46054 | E77: R_DE_FR_B_ROAD | F77: DE | G77: FR_FC | H77: CARRIER_B | I77: ROAD | J77: BASE_FREIGHT | K77: EUR | L77: 521.3633 | M77: 7.8 | N77: 4066.633771200000 | O77: 4066.6338 | R77: INVOICE_OR_PLAN | S77: =Model_Calc!AF17 -> 4066.6338 | T77: =ROUND(S77-O77,4) -> 0
A78: BUDGET_2026_V1 | B78: BUDGET | D78: 46054 | E78: R_DE_FR_B_ROAD | F78: DE | G78: FR_FC | H78: CARRIER_B | I78: ROAD | J78: FUEL_SURCHARGE | K78: EUR | L78: 37.917331 | M78: 7.8 | N78: 295.755183360000 | O78: 295.7552 | R78: INVOICE_OR_PLAN | S78: =Model_Calc!AG17 -> 295.75518 | T78: =ROUND(S78-O78,4) -> 0
A79: BUDGET_2026_V1 | B79: BUDGET | D79: 46054 | E79: R_DE_FR_B_ROAD | F79: DE | G79: FR_FC | H79: CARRIER_B | I79: ROAD | J79: FRONTLINE_VARIABLE_LABOR | K79: EUR | L79: 178.605 | M79: 7.8 | N79: 1393.11900000 | O79: 1393.119 | R79: INVOICE_OR_PLAN | S79: =Model_Calc!AL17 -> 1393.119 | T79: =ROUND(S79-O79,4) -> 0
A80: BUDGET_2026_V1 | B80: BUDGET | D80: 46054 | E80: R_DE_FR_B_ROAD | F80: DE | G80: FR_FC | H80: CARRIER_B | I80: ROAD | J80: PACKAGING | K80: EUR | L80: 69.80904 | M80: 7.8 | N80: 544.5105120000 | O80: 544.5105 | R80: INVOICE_OR_PLAN | S80: =Model_Calc!AQ17 -> 544.51051 | T80: =ROUND(S80-O80,4) -> 0
A81: BUDGET_2026_V1 | B81: BUDGET | D81: 46054 | E81: R_DE_FR_B_ROAD | F81: DE | G81: FR_FC | H81: CARRIER_B | I81: ROAD | J81: RETURN_LOGISTICS | K81: EUR | L81: 32.319 | M81: 7.8 | N81: 252.08820000000 | O81: 252.0882 | R81: INVOICE_OR_PLAN | S81: =Model_Calc!AV17 -> 252.0882 | T81: =ROUND(S81-O81,4) -> 0
A82: BUDGET_2026_V1 | B82: BUDGET | D82: 46054 | E82: R_DE_FR_B_ROAD | F82: DE | G82: FR_FC | H82: CARRIER_B | I82: ROAD | J82: BILLABLE_EXCEPTION | K82: EUR | L82: 5.9153976 | M82: 7.8 | N82: 46.1401012800000 | O82: 46.1401 | R82: INVOICE_OR_PLAN | S82: =Model_Calc!BA17 -> 46.140101 | T82: =ROUND(S82-O82,4) -> 0
A83: BUDGET_2026_V1 | B83: BUDGET | D83: 46054 | E83: R_FR_FR_A_ROAD | F83: FR | G83: FR_FC | H83: CARRIER_A | I83: ROAD | J83: BASE_FREIGHT | K83: EUR | L83: 2557.9411 | M83: 7.8 | N83: 19951.940736000000 | O83: 19951.941 | R83: INVOICE_OR_PLAN | S83: =Model_Calc!AF18 -> 19951.941 | T83: =ROUND(S83-O83,4) -> 0
A84: BUDGET_2026_V1 | B84: BUDGET | D84: 46054 | E84: R_FR_FR_A_ROAD | F84: FR | G84: FR_FC | H84: CARRIER_A | I84: ROAD | J84: FUEL_SURCHARGE | K84: EUR | L84: 230.2147 | M84: 7.8 | N84: 1795.674666240000000 | O84: 1795.6747 | R84: INVOICE_OR_PLAN | S84: =Model_Calc!AG18 -> 1795.6747 | T84: =ROUND(S84-O84,4) -> 0
A85: BUDGET_2026_V1 | B85: BUDGET | D85: 46054 | E85: R_FR_FR_A_ROAD | F85: FR | G85: FR_FC | H85: CARRIER_A | I85: ROAD | J85: FRONTLINE_VARIABLE_LABOR | K85: EUR | L85: 1587.6 | M85: 7.8 | N85: 12383.28000000 | O85: 12383.28 | R85: INVOICE_OR_PLAN | S85: =Model_Calc!AL18 -> 12383.28 | T85: =ROUND(S85-O85,4) -> 0
A86: BUDGET_2026_V1 | B86: BUDGET | D86: 46054 | E86: R_FR_FR_A_ROAD | F86: FR | G86: FR_FC | H86: CARRIER_A | I86: ROAD | J86: PACKAGING | K86: EUR | L86: 609.0336 | M86: 7.8 | N86: 4750.4620800000 | O86: 4750.4621 | R86: INVOICE_OR_PLAN | S86: =Model_Calc!AQ18 -> 4750.4621 | T86: =ROUND(S86-O86,4) -> 0
A87: BUDGET_2026_V1 | B87: BUDGET | D87: 46054 | E87: R_FR_FR_A_ROAD | F87: FR | G87: FR_FC | H87: CARRIER_A | I87: ROAD | J87: RETURN_LOGISTICS | K87: EUR | L87: 272.16 | M87: 7.8 | N87: 2122.84800000000 | O87: 2122.848 | R87: INVOICE_OR_PLAN | S87: =Model_Calc!AV18 -> 2122.848 | T87: =ROUND(S87-O87,4) -> 0
A88: BUDGET_2026_V1 | B88: BUDGET | D88: 46054 | E88: R_FR_FR_A_ROAD | F88: FR | G88: FR_FC | H88: CARRIER_A | I88: ROAD | J88: BILLABLE_EXCEPTION | K88: EUR | L88: 62.666352 | M88: 7.8 | N88: 488.7975456000000 | O88: 488.7975 | R88: INVOICE_OR_PLAN | S88: =Model_Calc!BA18 -> 488.79755 | T88: =ROUND(S88-O88,4) -> 0
A89: BUDGET_2026_V1 | B89: BUDGET | D89: 46054 | E89: R_FR_FR_B_ROAD | F89: FR | G89: FR_FC | H89: CARRIER_B | I89: ROAD | J89: BASE_FREIGHT | K89: EUR | L89: 6113.6899 | M89: 7.8 | N89: 47686.781376000000 | O89: 47686.781 | R89: INVOICE_OR_PLAN | S89: =Model_Calc!AF19 -> 47686.781 | T89: =ROUND(S89-O89,4) -> 0
A90: BUDGET_2026_V1 | B90: BUDGET | D90: 46054 | E90: R_FR_FR_B_ROAD | F90: FR | G90: FR_FC | H90: CARRIER_B | I90: ROAD | J90: FUEL_SURCHARGE | K90: EUR | L90: 470.28384 | M90: 7.8 | N90: 3668.213952000000 | O90: 3668.214 | R90: INVOICE_OR_PLAN | S90: =Model_Calc!AG19 -> 3668.214 | T90: =ROUND(S90-O90,4) -> 0
A91: BUDGET_2026_V1 | B91: BUDGET | D91: 46054 | E91: R_FR_FR_B_ROAD | F91: FR | G91: FR_FC | H91: CARRIER_B | I91: ROAD | J91: FRONTLINE_VARIABLE_LABOR | K91: EUR | L91: 2948.4 | M91: 7.8 | N91: 22997.52000000 | O91: 22997.52 | R91: INVOICE_OR_PLAN | S91: =Model_Calc!AL19 -> 22997.52 | T91: =ROUND(S91-O91,4) -> 0
A92: BUDGET_2026_V1 | B92: BUDGET | D92: 46054 | E92: R_FR_FR_B_ROAD | F92: FR | G92: FR_FC | H92: CARRIER_B | I92: ROAD | J92: PACKAGING | K92: EUR | L92: 1131.0624 | M92: 7.8 | N92: 8822.2867200000 | O92: 8822.2867 | R92: INVOICE_OR_PLAN | S92: =Model_Calc!AQ19 -> 8822.2867 | T92: =ROUND(S92-O92,4) -> 0
A93: BUDGET_2026_V1 | B93: BUDGET | D93: 46054 | E93: R_FR_FR_B_ROAD | F93: FR | G93: FR_FC | H93: CARRIER_B | I93: ROAD | J93: RETURN_LOGISTICS | K93: EUR | L93: 505.44 | M93: 7.8 | N93: 3942.43200000000 | O93: 3942.432 | R93: INVOICE_OR_PLAN | S93: =Model_Calc!AV19 -> 3942.432 | T93: =ROUND(S93-O93,4) -> 0
A94: BUDGET_2026_V1 | B94: BUDGET | D94: 46054 | E94: R_FR_FR_B_ROAD | F94: FR | G94: FR_FC | H94: CARRIER_B | I94: ROAD | J94: BILLABLE_EXCEPTION | K94: EUR | L94: 95.842656 | M94: 7.8 | N94: 747.5727168000000 | O94: 747.5727 | R94: INVOICE_OR_PLAN | S94: =Model_Calc!BA19 -> 747.57272 | T94: =ROUND(S94-O94,4) -> 0
A95: BUDGET_2026_V1 | B95: BUDGET | D95: 46054 | E95: R_GB_DE_A_ROAD | F95: GB | G95: DE_FC | H95: CARRIER_A | I95: ROAD | J95: BASE_FREIGHT | K95: GBP | L95: 10008.521 | M95: 9 | N95: 90076.68633600000000 | O95: 90076.686 | R95: INVOICE_OR_PLAN | S95: =Model_Calc!AF20 -> 90076.686 | T95: =ROUND(S95-O95,4) -> 0
A96: BUDGET_2026_V1 | B96: BUDGET | D96: 46054 | E96: R_GB_DE_A_ROAD | F96: GB | G96: DE_FC | H96: CARRIER_A | I96: ROAD | J96: FUEL_SURCHARGE | K96: GBP | L96: 1000.8521 | M96: 9 | N96: 9007.66863360000000000 | O96: 9007.6686 | R96: INVOICE_OR_PLAN | S96: =Model_Calc!AG20 -> 9007.6686 | T96: =ROUND(S96-O96,4) -> 0
A97: BUDGET_2026_V1 | B97: BUDGET | D97: 46054 | E97: R_GB_DE_A_ROAD | F97: GB | G97: DE_FC | H97: CARRIER_A | I97: ROAD | J97: FRONTLINE_VARIABLE_LABOR | K97: EUR | L97: 2584.4832 | M97: 7.8 | N97: 20158.9689600000 | O97: 20158.969 | R97: INVOICE_OR_PLAN | S97: =Model_Calc!AL20 -> 20158.969 | T97: =ROUND(S97-O97,4) -> 0
A98: BUDGET_2026_V1 | B98: BUDGET | D98: 46054 | E98: R_GB_DE_A_ROAD | F98: GB | G98: DE_FC | H98: CARRIER_A | I98: ROAD | J98: PACKAGING | K98: EUR | L98: 1030.2889 | M98: 7.8 | N98: 8036.253388800000 | O98: 8036.2534 | R98: INVOICE_OR_PLAN | S98: =Model_Calc!AQ20 -> 8036.2534 | T98: =ROUND(S98-O98,4) -> 0
A99: BUDGET_2026_V1 | B99: BUDGET | D99: 46054 | E99: R_GB_DE_A_ROAD | F99: GB | G99: DE_FC | H99: CARRIER_A | I99: ROAD | J99: RETURN_LOGISTICS | K99: GBP | L99: 841.05216 | M99: 9 | N99: 7569.4694400000000 | O99: 7569.4694 | R99: INVOICE_OR_PLAN | S99: =Model_Calc!AV20 -> 7569.4694 | T99: =ROUND(S99-O99,4) -> 0
A100: BUDGET_2026_V1 | B100: BUDGET | D100: 46054 | E100: R_GB_DE_A_ROAD | F100: GB | G100: DE_FC | H100: CARRIER_A | I100: ROAD | J100: BILLABLE_EXCEPTION | K100: GBP | L100: 124.12528 | M100: 9 | N100: 1117.127531520000000 | O100: 1117.1275 | R100: INVOICE_OR_PLAN | S100: =Model_Calc!BA20 -> 1117.1275 | T100: =ROUND(S100-O100,4) -> 0
A101: BUDGET_2026_V1 | B101: BUDGET | D101: 46054 | E101: R_GB_DE_B_ROAD | F101: GB | G101: DE_FC | H101: CARRIER_B | I101: ROAD | J101: BASE_FREIGHT | K101: GBP | L101: 4434.3936 | M101: 9 | N101: 39909.54240000000000 | O101: 39909.542 | R101: INVOICE_OR_PLAN | S101: =Model_Calc!AF21 -> 39909.542 | T101: =ROUND(S101-O101,4) -> 0
...

Sheet Fixed_Costs
A1: 固定成本事实
A2: 仓租、一线作业基础人工、仓库管理人工和系统费用按发货仓或共享范围单独展示，不分摊到目的国或线路。
A4: Version | B4: Type | C4: Scenario | D4: Month | E4: Scope | F4: Category | G4: Currency | H4: Original Amount | I4: FX | J4: High Precision CNY (text) | K4: Report CNY | L4: Recalc CNY | M4: Delta
A5: BUDGET_2026_V1 | B5: BUDGET | D5: 46023 | E5: DE_FC | F5: WAREHOUSE_RENT | G5: EUR | H5: 25000 | I5: 7.8 | J5: 195000.00 | K5: 195000 | L5: =H5*I5 -> 195000 | M5: =L5-K5 -> 0
A6: BUDGET_2026_V1 | B6: BUDGET | D6: 46023 | E6: DE_FC | F6: FRONTLINE_BASE_LABOR | G6: EUR | H6: 14000 | I6: 7.8 | J6: 109200.00 | K6: 109200 | L6: =H6*I6 -> 109200 | M6: =L6-K6 -> 0
A7: BUDGET_2026_V1 | B7: BUDGET | D7: 46023 | E7: DE_FC | F7: WAREHOUSE_MANAGEMENT_LABOR | G7: EUR | H7: 4000 | I7: 7.8 | J7: 31200.00 | K7: 31200 | L7: =H7*I7 -> 31200 | M7: =L7-K7 -> 0
A8: BUDGET_2026_V1 | B8: BUDGET | D8: 46023 | E8: FR_FC | F8: WAREHOUSE_RENT | G8: EUR | H8: 18000 | I8: 7.8 | J8: 140400.00 | K8: 140400 | L8: =H8*I8 -> 140400 | M8: =L8-K8 -> 0
A9: BUDGET_2026_V1 | B9: BUDGET | D9: 46023 | E9: FR_FC | F9: FRONTLINE_BASE_LABOR | G9: EUR | H9: 11000 | I9: 7.8 | J9: 85800.00 | K9: 85800 | L9: =H9*I9 -> 85800 | M9: =L9-K9 -> 0
A10: BUDGET_2026_V1 | B10: BUDGET | D10: 46023 | E10: FR_FC | F10: WAREHOUSE_MANAGEMENT_LABOR | G10: EUR | H10: 3000 | I10: 7.8 | J10: 23400.00 | K10: 23400 | L10: =H10*I10 -> 23400 | M10: =L10-K10 -> 0
A11: BUDGET_2026_V1 | B11: BUDGET | D11: 46023 | E11: SHARED | F11: SYSTEM_COST | G11: CNY | H11: 50000 | I11: 1 | J11: 50000 | K11: 50000 | L11: =H11*I11 -> 50000 | M11: =L11-K11 -> 0
A12: BUDGET_2026_V1 | B12: BUDGET | D12: 46054 | E12: DE_FC | F12: WAREHOUSE_RENT | G12: EUR | H12: 25000 | I12: 7.8 | J12: 195000.00 | K12: 195000 | L12: =H12*I12 -> 195000 | M12: =L12-K12 -> 0
A13: BUDGET_2026_V1 | B13: BUDGET | D13: 46054 | E13: DE_FC | F13: FRONTLINE_BASE_LABOR | G13: EUR | H13: 14000 | I13: 7.8 | J13: 109200.00 | K13: 109200 | L13: =H13*I13 -> 109200 | M13: =L13-K13 -> 0
A14: BUDGET_2026_V1 | B14: BUDGET | D14: 46054 | E14: DE_FC | F14: WAREHOUSE_MANAGEMENT_LABOR | G14: EUR | H14: 4000 | I14: 7.8 | J14: 31200.00 | K14: 31200 | L14: =H14*I14 -> 31200 | M14: =L14-K14 -> 0
A15: BUDGET_2026_V1 | B15: BUDGET | D15: 46054 | E15: FR_FC | F15: WAREHOUSE_RENT | G15: EUR | H15: 18000 | I15: 7.8 | J15: 140400.00 | K15: 140400 | L15: =H15*I15 -> 140400 | M15: =L15-K15 -> 0
A16: BUDGET_2026_V1 | B16: BUDGET | D16: 46054 | E16: FR_FC | F16: FRONTLINE_BASE_LABOR | G16: EUR | H16: 11000 | I16: 7.8 | J16: 85800.00 | K16: 85800 | L16: =H16*I16 -> 85800 | M16: =L16-K16 -> 0
... A172: FORECAST_2026_08_V1 | B172: FORECAST | D172: 46357 | E172: SHARED | F172: SYSTEM_COST | G172: CNY | H172: 50900 | I172: 1 | J172: 50900.000 | K172: 50900 | L172: =H172*I172 -> 50900 | M172: =L172-K172 -> 0
A173: SCENARIO_BASE_2026_08 | B173: SCENARIO | C173: BASE | D173: 46266 | E173: DE_FC | F173: WAREHOUSE_RENT | G173: EUR | H173: 25450 | I173: 7.92 | J173: 201564.00000 | K173: 201564 | L173: =H173*I173 -> 201564 | M173: =L173-K173 -> 0
A174: SCENARIO_BASE_2026_08 | B174: SCENARIO | C174: BASE | D174: 46266 | E174: DE_FC | F174: FRONTLINE_BASE_LABOR | G174: EUR | H174: 14252 | I174: 7.92 | J174: 112875.84000 | K174: 112875.84 | L174: =H174*I174 -> 112875.84 | M174: =L174-K174 -> 0
A175: SCENARIO_BASE_2026_08 | B175: SCENARIO | C175: BASE | D175: 46266 | E175: DE_FC | F175: WAREHOUSE_MANAGEMENT_LABOR | G175: EUR | H175: 4072 | I175: 7.92 | J175: 32250.24000 | K175: 32250.24 | L175: =H175*I175 -> 32250.24 | M175: =L175-K175 -> -3.6379788e-12
A176: SCENARIO_BASE_2026_08 | B176: SCENARIO | C176: BASE | D176: 46266 | E176: FR_FC | F176: WAREHOUSE_RENT | G176: EUR | H176: 18324 | I176: 7.92 | J176: 145126.08000 | K176: 145126.08 | L176: =H176*I176 -> 145126.08 | M176: =L176-K176 -> 0
A177: SCENARIO_BASE_2026_08 | B177: SCENARIO | C177: BASE | D177: 46266 | E177: FR_FC | F177: FRONTLINE_BASE_LABOR | G177: EUR | H177: 11198 | I177: 7.92 | J177: 88688.16000 | K177: 88688.16 | L177: =H177*I177 -> 88688.16 | M177: =L177-K177 -> 0
A178: SCENARIO_BASE_2026_08 | B178: SCENARIO | C178: BASE | D178: 46266 | E178: FR_FC | F178: WAREHOUSE_MANAGEMENT_LABOR | G178: EUR | H178: 3054 | I178: 7.92 | J178: 24187.68000 | K178: 24187.68 | L178: =H178*I178 -> 24187.68 | M178: =L178-K178 -> 0
A179: SCENARIO_BASE_2026_08 | B179: SCENARIO | C179: BASE | D179: 46266 | E179: SHARED | F179: SYSTEM_COST | G179: CNY | H179: 50900 | I179: 1 | J179: 50900.000 | K179: 50900 | L179: =H179*I179 -> 50900 | M179: =L179-K179 -> 0
A180: SCENARIO_BASE_2026_08 | B180: SCENARIO | C180: BASE | D180: 46296 | E180: DE_FC | F180: WAREHOUSE_RENT | G180: EUR | H180: 25450 | I180: 7.9 | J180: 201055.00000 | K180: 201055 | L180: =H180*I180 -> 201055 | M180: =L180-K180 -> 0
A181: SCENARIO_BASE_2026_08 | B181: SCENARIO | C181: BASE | D181: 46296 | E181: DE_FC | F181: FRONTLINE_BASE_LABOR | G181: EUR | H181: 14252 | I181: 7.9 | J181: 112590.80000 | K181: 112590.8 | L181: =H181*I181 -> 112590.8 | M181: =L181-K181 -> 0
A182: SCENARIO_BASE_2026_08 | B182: SCENARIO | C182: BASE | D182: 46296 | E182: DE_FC | F182: WAREHOUSE_MANAGEMENT_LABOR | G182: EUR | H182: 4072 | I182: 7.9 | J182: 32168.80000 | K182: 32168.8 | L182: =H182*I182 -> 32168.8 | M182: =L182-K182 -> 3.6379788e-12
A183: SCENARIO_BASE_2026_08 | B183: SCENARIO | C183: BASE | D183: 46296 | E183: FR_FC | F183: WAREHOUSE_RENT | G183: EUR | H183: 18324 | I183: 7.9 | J183: 144759.60000 | K183: 144759.6 | L183: =H183*I183 -> 144759.6 | M183: =L183-K183 -> 0
A184: SCENARIO_BASE_2026_08 | B184: SCENARIO | C184: BASE | D184: 46296 | E184: FR_FC | F184: FRONTLINE_BASE_LABOR | G184: EUR | H184: 11198 | I184: 7.9 | J184: 88464.20000 | K184: 88464.2 | L184: =H184*I184 -> 88464.2 | M184: =L184-K184 -> 0
... A256: SCENARIO_COST_SAVING_2026_08 | B256: SCENARIO | C256: COST_SAVING | D256: 46357 | E256: SHARED | F256: SYSTEM_COST | G256: CNY | H256: 50900 | I256: 1 | J256: 50900.000 | K256: 50900 | L256: =H256*I256 -> 50900 | M256: =L256-K256 -> 0

Sheet GMV_Facts
A1: 履约 GMV 事实
A2: GMV 粒度为月份 × 目的国 × 版本，不复制或分摊到线路。
A4: Version | B4: Type | C4: Scenario | D4: Month | E4: Destination | F4: Currency | G4: Original Amount | H4: FX | I4: High Precision CNY (text) | J4: Report CNY | K4: Recalc CNY | L4: Delta | M4: Source Class | N4: Note
A5: BUDGET_2026_V1 | B5: BUDGET | D5: 46023 | E5: DE | F5: EUR | G5: 482160 | H5: 7.8 | I5: 3760848.0000 | J5: 3760848 | K5: =G5*H5 -> 3760848 | L5: =K5-J5 -> 0 | M5: SYNTHETIC_DEMO_DATA | N5: 履约 GMV，不含取消订单
A6: BUDGET_2026_V1 | B6: BUDGET | D6: 46023 | E6: FR | F6: EUR | G6: 385280 | H6: 7.8 | I6: 3005184.0000 | J6: 3005184 | K6: =G6*H6 -> 3005184 | L6: =K6-J6 -> 0 | M6: SYNTHETIC_DEMO_DATA | N6: 履约 GMV，不含取消订单
A7: BUDGET_2026_V1 | B7: BUDGET | D7: 46023 | E7: GB | F7: GBP | G7: 283920 | H7: 9 | I7: 2555280.0000 | J7: 2555280 | K7: =G7*H7 -> 2555280 | L7: =K7-J7 -> 0 | M7: SYNTHETIC_DEMO_DATA | N7: 履约 GMV，不含取消订单
A8: BUDGET_2026_V1 | B8: BUDGET | D8: 46054 | E8: DE | F8: EUR | G8: 464940 | H8: 7.8 | I8: 3626532.0000 | J8: 3626532 | K8: =G8*H8 -> 3626532 | L8: =K8-J8 -> 0 | M8: SYNTHETIC_DEMO_DATA | N8: 履约 GMV，不含取消订单
A9: BUDGET_2026_V1 | B9: BUDGET | D9: 46054 | E9: FR | F9: EUR | G9: 371520 | H9: 7.8 | I9: 2897856.0000 | J9: 2897856 | K9: =G9*H9 -> 2897856 | L9: =K9-J9 -> 0 | M9: SYNTHETIC_DEMO_DATA | N9: 履约 GMV，不含取消订单
A10: BUDGET_2026_V1 | B10: BUDGET | D10: 46054 | E10: GB | F10: GBP | G10: 273780 | H10: 9 | I10: 2464020.0000 | J10: 2464020 | K10: =G10*H10 -> 2464020 | L10: =K10-J10 -> 0 | M10: SYNTHETIC_DEMO_DATA | N10: 履约 GMV，不含取消订单
A11: BUDGET_2026_V1 | B11: BUDGET | D11: 46082 | E11: DE | F11: EUR | G11: 492000 | H11: 7.8 | I11: 3837600.0000 | J11: 3837600 | K11: =G11*H11 -> 3837600 | L11: =K11-J11 -> 0 | M11: SYNTHETIC_DEMO_DATA | N11: 履约 GMV，不含取消订单
A12: BUDGET_2026_V1 | B12: BUDGET | D12: 46082 | E12: FR | F12: EUR | G12: 412800 | H12: 7.8 | I12: 3219840.0000 | J12: 3219840 | K12: =G12*H12 -> 3219840 | L12: =K12-J12 -> 0 | M12: SYNTHETIC_DEMO_DATA | N12: 履约 GMV，不含取消订单
A13: BUDGET_2026_V1 | B13: BUDGET | D13: 46082 | E13: GB | F13: GBP | G13: 327600 | H13: 9 | I13: 2948400.0000 | J13: 2948400 | K13: =G13*H13 -> 2948400 | L13: =K13-J13 -> 0 | M13: SYNTHETIC_DEMO_DATA | N13: 履约 GMV，不含取消订单
A14: BUDGET_2026_V1 | B14: BUDGET | D14: 46113 | E14: DE | F14: EUR | G14: 508400 | H14: 7.8 | I14: 3965520.0000 | J14: 3965520 | K14: =G14*H14 -> 3965520 | L14: =K14-J14 -> 0 | M14: SYNTHETIC_DEMO_DATA | N14: 履约 GMV，不含取消订单
A15: BUDGET_2026_V1 | B15: BUDGET | D15: 46113 | E15: FR | F15: EUR | G15: 426560 | H15: 7.8 | I15: 3327168.0000 | J15: 3327168 | K15: =G15*H15 -> 3327168 | L15: =K15-J15 -> 0 | M15: SYNTHETIC_DEMO_DATA | N15: 履约 GMV，不含取消订单
A16: BUDGET_2026_V1 | B16: BUDGET | D16: 46113 | E16: GB | F16: GBP | G16: 338520 | H16: 9 | I16: 3046680.0000 | J16: 3046680 | K16: =G16*H16 -> 3046680 | L16: =K16-J16 -> 0 | M16: SYNTHETIC_DEMO_DATA | N16: 履约 GMV，不含取消订单
... A76: FORECAST_2026_08_V1 | B76: FORECAST | D76: 46357 | E76: GB | F76: GBP | G76: 869440 | H76: 9 | I76: 7824960.0000 | J76: 7824960 | K76: =G76*H76 -> 7824960 | L76: =K76-J76 -> 0 | M76: SYNTHETIC_DEMO_DATA | N76: 履约 GMV，不含取消订单
A77: SCENARIO_BASE_2026_08 | B77: SCENARIO | C77: BASE | D77: 46266 | E77: DE | F77: EUR | G77: 513936 | H77: 7.92 | I77: 4070373.1200 | J77: 4070373.1 | K77: =G77*H77 -> 4070373.1 | L77: =K77-J77 -> 0 | M77: SYNTHETIC_DEMO_DATA | N77: 履约 GMV，不含取消订单
A78: SCENARIO_BASE_2026_08 | B78: SCENARIO | C78: BASE | D78: 46266 | E78: FR | F78: EUR | G78: 448920 | H78: 7.92 | I78: 3555446.4000 | J78: 3555446.4 | K78: =G78*H78 -> 3555446.4 | L78: =K78-J78 -> 0 | M78: SYNTHETIC_DEMO_DATA | N78: 履约 GMV，不含取消订单
A79: SCENARIO_BASE_2026_08 | B79: SCENARIO | C79: BASE | D79: 46266 | E79: GB | F79: GBP | G79: 444448 | H79: 9.15 | I79: 4066699.2000 | J79: 4066699.2 | K79: =G79*H79 -> 4066699.2 | L79: =K79-J79 -> 0 | M79: SYNTHETIC_DEMO_DATA | N79: 履约 GMV，不含取消订单
A80: SCENARIO_BASE_2026_08 | B80: SCENARIO | C80: BASE | D80: 46296 | E80: DE | F80: EUR | G80: 550290 | H80: 7.9 | I80: 4347291.0000 | J80: 4347291 | K80: =G80*H80 -> 4347291 | L80: =K80-J80 -> 0 | M80: SYNTHETIC_DEMO_DATA | N80: 履约 GMV，不含取消订单
A81: SCENARIO_BASE_2026_08 | B81: SCENARIO | C81: BASE | D81: 46296 | E81: FR | F81: EUR | G81: 508950 | H81: 7.9 | I81: 4020705.0000 | J81: 4020705 | K81: =G81*H81 -> 4020705 | L81: =K81-J81 -> 0 | M81: SYNTHETIC_DEMO_DATA | N81: 履约 GMV，不含取消订单
A82: SCENARIO_BASE_2026_08 | B82: SCENARIO | C82: BASE | D82: 46296 | E82: GB | F82: GBP | G82: 533520 | H82: 9.1 | I82: 4855032.0000 | J82: 4855032 | K82: =G82*H82 -> 4855032 | L82: =K82-J82 -> 0 | M82: SYNTHETIC_DEMO_DATA | N82: 履约 GMV，不含取消订单
A83: SCENARIO_BASE_2026_08 | B83: SCENARIO | C83: BASE | D83: 46327 | E83: DE | F83: EUR | G83: 658688 | H83: 7.88 | I83: 5190461.4400 | J83: 5190461.4 | K83: =G83*H83 -> 5190461.4 | L83: =K83-J83 -> -9.3132257e-10 | M83: SYNTHETIC_DEMO_DATA | N83: 履约 GMV，不含取消订单
A84: SCENARIO_BASE_2026_08 | B84: SCENARIO | C84: BASE | D84: 46327 | E84: FR | F84: EUR | G84: 625704 | H84: 7.88 | I84: 4930547.5200 | J84: 4930547.5 | K84: =G84*H84 -> 4930547.5 | L84: =K84-J84 -> 0 | M84: SYNTHETIC_DEMO_DATA | N84: 履约 GMV，不含取消订单
A85: SCENARIO_BASE_2026_08 | B85: SCENARIO | C85: BASE | D85: 46327 | E85: GB | F85: GBP | G85: 735072 | H85: 9.05 | I85: 6652401.6000 | J85: 6652401.6 | K85: =G85*H85 -> 6652401.6 | L85: =K85-J85 -> 9.3132257e-10 | M85: SYNTHETIC_DEMO_DATA | N85: 履约 GMV，不含取消订单
A86: SCENARIO_BASE_2026_08 | B86: SCENARIO | C86: BASE | D86: 46357 | E86: DE | F86: EUR | G86: 759616 | H86: 7.86 | I86: 5970581.7600 | J86: 5970581.8 | K86: =G86*H86 -> 5970581.8 | L86: =K86-J86 -> 9.3132257e-10 | M86: SYNTHETIC_DEMO_DATA | N86: 履约 GMV，不含取消订单
A87: SCENARIO_BASE_2026_08 | B87: SCENARIO | C87: BASE | D87: 46357 | E87: FR | F87: EUR | G87: 696696 | H87: 7.86 | I87: 5476030.5600 | J87: 5476030.6 | K87: =G87*H87 -> 5476030.6 | L87: =K87-J87 -> 9.3132257e-10 | M87: SYNTHETIC_DEMO_DATA | N87: 履约 GMV，不含取消订单
A88: SCENARIO_BASE_2026_08 | B88: SCENARIO | C88: BASE | D88: 46357 | E88: GB | F88: GBP | G88: 869440 | H88: 9 | I88: 7824960.0000 | J88: 7824960 | K88: =G88*H88 -> 7824960 | L88: =K88-J88 -> 0 | M88: SYNTHETIC_DEMO_DATA | N88: 履约 GMV，不含取消订单
... A112: SCENARIO_COST_SAVING_2026_08 | B112: SCENARIO | C112: COST_SAVING | D112: 46357 | E112: GB | F112: GBP | G112: 869440 | H112: 9 | I112: 7824960.0000 | J112: 7824960 | K112: =G112*H112 -> 7824960 | L112: =K112-J112 -> 0 | M112: SYNTHETIC_DEMO_DATA | N112: 履约 GMV，不含取消订单

Sheet Service_Facts
A1: 服务事实与成熟度
A2: Actual 准时率 = 按时妥投包裹 ÷ 已到承诺截止日期包裹；Forecast/情景使用版本化线路预计准时率。
A4: Version | B4: Type | C4: Scenario | D4: Month | E4: Route | F4: Destination | G4: FC | H4: Carrier | I4: Mode | J4: Cohort Packages | K4: Due Packages | L4: On-time Packages | M4: On-time Rate | N4: Maturity Rate | O4: Recalc Rate | P4: Delta
A5: BUDGET_2026_V1 | B5: BUDGET | D5: 46023 | E5: R_DE_DE_A_ROAD | F5: DE | G5: DE_FC | H5: CARRIER_A | I5: ROAD | J5: 3593.268 | K5: 3593.268 | L5: 3467.5036 | M5: 0.965 | N5: 1 | O5: =IF(K5="",M5,L5/K5) -> 0.965 | P5: =O5-M5 -> 0
A6: BUDGET_2026_V1 | B6: BUDGET | D6: 46023 | E6: R_DE_DE_B_ROAD | F6: DE | G6: DE_FC | H6: CARRIER_B | I6: ROAD | J6: 2395.512 | K6: 2395.512 | L6: 2338.0197 | M6: 0.976 | N6: 1 | O6: =IF(K6="",M6,L6/K6) -> 0.976 | P6: =O6-M6 -> -1.110223e-16
A7: BUDGET_2026_V1 | B7: BUDGET | D7: 46023 | E7: R_DE_FR_B_ROAD | F7: DE | G7: FR_FC | H7: CARRIER_B | I7: ROAD | J7: 190.512 | K7: 190.512 | L7: 184.41562 | M7: 0.968 | N7: 1 | O7: =IF(K7="",M7,L7/K7) -> 0.968 | P7: =O7-M7 -> 0
A8: BUDGET_2026_V1 | B8: BUDGET | D8: 46023 | E8: R_FR_FR_A_ROAD | F8: FR | G8: FR_FC | H8: CARRIER_A | I8: ROAD | J8: 1662.08 | K8: 1662.08 | L8: 1597.2589 | M8: 0.961 | N8: 1 | O8: =IF(K8="",M8,L8/K8) -> 0.961 | P8: =O8-M8 -> 1.110223e-16
A9: BUDGET_2026_V1 | B9: BUDGET | D9: 46023 | E9: R_FR_FR_B_ROAD | F9: FR | G9: FR_FC | H9: CARRIER_B | I9: ROAD | J9: 3086.72 | K9: 3086.72 | L9: 3003.3786 | M9: 0.973 | N9: 1 | O9: =IF(K9="",M9,L9/K9) -> 0.973 | P9: =O9-M9 -> 1.110223e-16
A10: BUDGET_2026_V1 | B10: BUDGET | D10: 46023 | E10: R_GB_DE_A_ROAD | F10: GB | G10: DE_FC | H10: CARRIER_A | I10: ROAD | J10: 2543.9232 | K10: 2543.9232 | L10: 2365.8486 | M10: 0.93 | N10: 1 | O10: =IF(K10="",M10,L10/K10) -> 0.93 | P10: =O10-M10 -> -2.220446e-16
A11: BUDGET_2026_V1 | B11: BUDGET | D11: 46023 | E11: R_GB_DE_B_ROAD | F11: GB | G11: DE_FC | H11: CARRIER_B | I11: ROAD | J11: 978.432 | K11: 978.432 | L11: 929.5104 | M11: 0.95 | N11: 1 | O11: =IF(K11="",M11,L11/K11) -> 0.95 | P11: =O11-M11 -> 0
A12: BUDGET_2026_V1 | B12: BUDGET | D12: 46023 | E12: R_GB_DE_B_AIR | F12: GB | G12: DE_FC | H12: CARRIER_B | I12: AIR | J12: 273.96096 | K12: 273.96096 | L12: 266.83798 | M12: 0.974 | N12: 1 | O12: =IF(K12="",M12,L12/K12) -> 0.974 | P12: =O12-M12 -> 0
A13: BUDGET_2026_V1 | B13: BUDGET | D13: 46023 | E13: R_GB_DE_C_AIR | F13: GB | G13: DE_FC | H13: CARRIER_C | I13: AIR | J13: 117.41184 | K13: 117.41184 | L13: 116.0029 | M13: 0.988 | N13: 1 | O13: =IF(K13="",M13,L13/K13) -> 0.988 | P13: =O13-M13 -> 0
A14: BUDGET_2026_V1 | B14: BUDGET | D14: 46023 | E14: R_GB_FR_B_AIR | F14: GB | G14: FR_FC | H14: CARRIER_B | I14: AIR | J14: 167.44 | K14: 167.44 | L14: 162.58424 | M14: 0.971 | N14: 1 | O14: =IF(K14="",M14,L14/K14) -> 0.971 | P14: =O14-M14 -> 0
A15: BUDGET_2026_V1 | B15: BUDGET | D15: 46054 | E15: R_DE_DE_A_ROAD | F15: DE | G15: DE_FC | H15: CARRIER_A | I15: ROAD | J15: 3464.937 | K15: 3464.937 | L15: 3343.6642 | M15: 0.965 | N15: 1 | O15: =IF(K15="",M15,L15/K15) -> 0.965 | P15: =O15-M15 -> 1.110223e-16
A16: BUDGET_2026_V1 | B16: BUDGET | D16: 46054 | E16: R_DE_DE_B_ROAD | F16: DE | G16: DE_FC | H16: CARRIER_B | I16: ROAD | J16: 2309.958 | K16: 2309.958 | L16: 2254.519 | M16: 0.976 | N16: 1 | O16: =IF(K16="",M16,L16/K16) -> 0.976 | P16: =O16-M16 -> 1.110223e-16
... A204: ACTUAL_2026_08_CLOSE_V1 | B204: ACTUAL | D204: 46235 | E204: R_GB_FR_B_AIR | F204: GB | G204: FR_FC | H204: CARRIER_B | I204: AIR | J204: 316.1928 | K204: 290.89738 | L204: 281.58866 | M204: 0.968 | N204: 0.92 | O204: =IF(K204="",M204,L204/K204) -> 0.968 | P204: =O204-M204 -> 0
A205: FORECAST_2026_08_V1 | B205: FORECAST | D205: 46266 | E205: R_DE_DE_A_ROAD | F205: DE | G205: DE_FC | H205: CARRIER_A | I205: ROAD | J205: 3783.9312 | M205: 0.965 | O205: =IF(K205="",M205,L205/K205) -> 0.965 | P205: =O205-M205 -> 0
A206: FORECAST_2026_08_V1 | B206: FORECAST | D206: 46266 | E206: R_DE_DE_B_ROAD | F206: DE | G206: DE_FC | H206: CARRIER_B | I206: ROAD | J206: 2522.6208 | M206: 0.976 | O206: =IF(K206="",M206,L206/K206) -> 0.976 | P206: =O206-M206 -> 0
A207: FORECAST_2026_08_V1 | B207: FORECAST | D207: 46266 | E207: R_DE_FR_B_ROAD | F207: DE | G207: FR_FC | H207: CARRIER_B | I207: ROAD | J207: 200.6208 | M207: 0.968 | O207: =IF(K207="",M207,L207/K207) -> 0.968 | P207: =O207-M207 -> 0
A208: FORECAST_2026_08_V1 | B208: FORECAST | D208: 46266 | E208: R_FR_FR_A_ROAD | F208: FR | G208: FR_FC | H208: CARRIER_A | I208: ROAD | J208: 1914.36 | M208: 0.961 | O208: =IF(K208="",M208,L208/K208) -> 0.961 | P208: =O208-M208 -> 0
A209: FORECAST_2026_08_V1 | B209: FORECAST | D209: 46266 | E209: R_FR_FR_B_ROAD | F209: FR | G209: FR_FC | H209: CARRIER_B | I209: ROAD | J209: 3555.24 | M209: 0.973 | O209: =IF(K209="",M209,L209/K209) -> 0.973 | P209: =O209-M209 -> 0
A210: FORECAST_2026_08_V1 | B210: FORECAST | D210: 46266 | E210: R_GB_DE_A_ROAD | F210: GB | G210: DE_FC | H210: CARRIER_A | I210: ROAD | J210: 2004.2266 | M210: 0.93 | O210: =IF(K210="",M210,L210/K210) -> 0.93 | P210: =O210-M210 -> 0
A211: FORECAST_2026_08_V1 | B211: FORECAST | D211: 46266 | E211: R_GB_DE_B_ROAD | F211: GB | G211: DE_FC | H211: CARRIER_B | I211: ROAD | J211: 1135.7284 | M211: 0.95 | O211: =IF(K211="",M211,L211/K211) -> 0.95 | P211: =O211-M211 -> 0
A212: FORECAST_2026_08_V1 | B212: FORECAST | D212: 46266 | E212: R_GB_DE_B_AIR | F212: GB | G212: DE_FC | H212: CARRIER_B | I212: AIR | J212: 1670.1888 | M212: 0.974 | O212: =IF(K212="",M212,L212/K212) -> 0.974 | P212: =O212-M212 -> 0
A213: FORECAST_2026_08_V1 | B213: FORECAST | D213: 46266 | E213: R_GB_DE_C_AIR | F213: GB | G213: DE_FC | H213: CARRIER_C | I213: AIR | J213: 1870.6115 | M213: 0.988 | O213: =IF(K213="",M213,L213/K213) -> 0.988 | P213: =O213-M213 -> 0
A214: FORECAST_2026_08_V1 | B214: FORECAST | D214: 46266 | E214: R_GB_FR_B_AIR | F214: GB | G214: FR_FC | H214: CARRIER_B | I214: AIR | J214: 273.6864 | M214: 0.971 | O214: =IF(K214="",M214,L214/K214) -> 0.971 | P214: =O214-M214 -> 0
A215: FORECAST_2026_08_V1 | B215: FORECAST | D215: 46296 | E215: R_DE_DE_A_ROAD | F215: DE | G215: DE_FC | H215: CARRIER_A | I215: ROAD | J215: 4051.593 | M215: 0.965 | O215: =IF(K215="",M215,L215/K215) -> 0.965 | P215: =O215-M215 -> 0
A216: FORECAST_2026_08_V1 | B216: FORECAST | D216: 46296 | E216: R_DE_DE_B_ROAD | F216: DE | G216: DE_FC | H216: CARRIER_B | I216: ROAD | J216: 2701.062 | M216: 0.976 | O216: =IF(K216="",M216,L216/K216) -> 0.976 | P216: =O216-M216 -> 0
... A244: FORECAST_2026_08_V1 | B244: FORECAST | D244: 46357 | E244: R_GB_FR_B_AIR | F244: GB | G244: FR_FC | H244: CARRIER_B | I244: AIR | J244: 535.392 | M244: 0.971 | O244: =IF(K244="",M244,L244/K244) -> 0.971 | P244: =O244-M244 -> 0
A245: SCENARIO_BASE_2026_08 | B245: SCENARIO | C245: BASE | D245: 46266 | E245: R_DE_DE_A_ROAD | F245: DE | G245: DE_FC | H245: CARRIER_A | I245: ROAD | J245: 3783.9312 | M245: 0.965 | O245: =IF(K245="",M245,L245/K245) -> 0.965 | P245: =O245-M245 -> 0
A246: SCENARIO_BASE_2026_08 | B246: SCENARIO | C246: BASE | D246: 46266 | E246: R_DE_DE_B_ROAD | F246: DE | G246: DE_FC | H246: CARRIER_B | I246: ROAD | J246: 2522.6208 | M246: 0.976 | O246: =IF(K246="",M246,L246/K246) -> 0.976 | P246: =O246-M246 -> 0
A247: SCENARIO_BASE_2026_08 | B247: SCENARIO | C247: BASE | D247: 46266 | E247: R_DE_FR_B_ROAD | F247: DE | G247: FR_FC | H247: CARRIER_B | I247: ROAD | J247: 200.6208 | M247: 0.968 | O247: =IF(K247="",M247,L247/K247) -> 0.968 | P247: =O247-M247 -> 0
A248: SCENARIO_BASE_2026_08 | B248: SCENARIO | C248: BASE | D248: 46266 | E248: R_FR_FR_A_ROAD | F248: FR | G248: FR_FC | H248: CARRIER_A | I248: ROAD | J248: 1914.36 | M248: 0.961 | O248: =IF(K248="",M248,L248/K248) -> 0.961 | P248: =O248-M248 -> 0
A249: SCENARIO_BASE_2026_08 | B249: SCENARIO | C249: BASE | D249: 46266 | E249: R_FR_FR_B_ROAD | F249: FR | G249: FR_FC | H249: CARRIER_B | I249: ROAD | J249: 3555.24 | M249: 0.973 | O249: =IF(K249="",M249,L249/K249) -> 0.973 | P249: =O249-M249 -> 0
A250: SCENARIO_BASE_2026_08 | B250: SCENARIO | C250: BASE | D250: 46266 | E250: R_GB_DE_A_ROAD | F250: GB | G250: DE_FC | H250: CARRIER_A | I250: ROAD | J250: 2004.2266 | M250: 0.93 | O250: =IF(K250="",M250,L250/K250) -> 0.93 | P250: =O250-M250 -> 0
A251: SCENARIO_BASE_2026_08 | B251: SCENARIO | C251: BASE | D251: 46266 | E251: R_GB_DE_B_ROAD | F251: GB | G251: DE_FC | H251: CARRIER_B | I251: ROAD | J251: 1135.7284 | M251: 0.95 | O251: =IF(K251="",M251,L251/K251) -> 0.95 | P251: =O251-M251 -> 0
A252: SCENARIO_BASE_2026_08 | B252: SCENARIO | C252: BASE | D252: 46266 | E252: R_GB_DE_B_AIR | F252: GB | G252: DE_FC | H252: CARRIER_B | I252: AIR | J252: 1670.1888 | M252: 0.974 | O252: =IF(K252="",M252,L252/K252) -> 0.974 | P252: =O252-M252 -> 0
A253: SCENARIO_BASE_2026_08 | B253: SCENARIO | C253: BASE | D253: 46266 | E253: R_GB_DE_C_AIR | F253: GB | G253: DE_FC | H253: CARRIER_C | I253: AIR | J253: 1870.6115 | M253: 0.988 | O253: =IF(K253="",M253,L253/K253) -> 0.988 | P253: =O253-M253 -> 0
A254: SCENARIO_BASE_2026_08 | B254: SCENARIO | C254: BASE | D254: 46266 | E254: R_GB_FR_B_AIR | F254: GB | G254: FR_FC | H254: CARRIER_B | I254: AIR | J254: 273.6864 | M254: 0.971 | O254: =IF(K254="",M254,L254/K254) -> 0.971 | P254: =O254-M254 -> 0
A255: SCENARIO_BASE_2026_08 | B255: SCENARIO | C255: BASE | D255: 46296 | E255: R_DE_DE_A_ROAD | F255: DE | G255: DE_FC | H255: CARRIER_A | I255: ROAD | J255: 4051.593 | M255: 0.965 | O255: =IF(K255="",M255,L255/K255) -> 0.965 | P255: =O255-M255 -> 0
A256: SCENARIO_BASE_2026_08 | B256: SCENARIO | C256: BASE | D256: 46296 | E256: R_DE_DE_B_ROAD | F256: DE | G256: DE_FC | H256: CARRIER_B | I256: ROAD | J256: 2701.062 | M256: 0.976 | O256: =IF(K256="",M256,L256/K256) -> 0.976 | P256: =O256-M256 -> 0
... A364: SCENARIO_COST_SAVING_2026_08 | B364: SCENARIO | C364: COST_SAVING | D364: 46357 | E364: R_GB_FR_B_AIR | F364: GB | G364: FR_FC | H364: CARRIER_B | I364: AIR | J364: 535.392 | M364: 0.971 | O364: =IF(K364="",M364,L364/K364) -> 0.971 | P364: =O364-M364 -> 0

Sheet Monthly_Summary
A1: 月度管理汇总
A2: 统一时间轴；Actual、Budget、Forecast、Latest Outlook 与三类情景使用同一指标口径。
A4: Series | B4: Month | C4: Orders | D4: Packages | E4: Chargeable Weight kg | F4: Variable Cost CNY | G4: Fixed Cost CNY | H4: Source Total Cost CNY | I4: Recalc Total Cost CNY | J4: Delta | K4: GMV CNY | L4: Company Total Cost Rate | M4: Unit Variable/Order | N4: Transport Cost/kg | O4: On-time Rate | P4: Maturity Rate
A5: BUDGET | B5: 46023 | C5: 14000 | D5: 15009.26 | E5: 12674.16 | F5: 559244.98 | G5: 635000 | H5: 1194245 | I5: =F5+G5 -> 1194245 | J5: =ROUND(I5-H5,4) -> 0 | K5: 9321312 | L5: =I5/K5 -> 0.12811984 | M5: =F5/C5 -> 39.94607 | N5: 28.157436 | O5: 0.96149713 | P5: 1
A6: BUDGET | B6: 46054 | C6: 13500 | D6: 14473.215 | E6: 12221.512 | F6: 539271.94 | G6: 635000 | H6: 1174271.9 | I6: =F6+G6 -> 1174271.9 | J6: =ROUND(I6-H6,4) -> 0 | K6: 8988408 | L6: =I6/K6 -> 0.13064293 | M6: =F6/C6 -> 39.94607 | N6: 28.157436 | O6: 0.96149713 | P6: 1
A7: BUDGET | B7: 46082 | C7: 15000 | D7: 16102.44 | E7: 13667.369 | F7: 609596.96 | G7: 635000 | H7: 1244597 | I7: =F7+G7 -> 1244597 | J7: =ROUND(I7-H7,4) -> 0 | K7: 10005840 | L7: =I7/K7 -> 0.12438705 | M7: =F7/C7 -> 40.639797 | N7: 28.680864 | O7: 0.96091716 | P7: 1
A8: BUDGET | B8: 46113 | C8: 15500 | D8: 16639.188 | E8: 14122.948 | F8: 629916.86 | G8: 635000 | H8: 1264916.9 | I8: =F8+G8 -> 1264916.9 | J8: =ROUND(I8-H8,4) -> 0 | K8: 10339368 | L8: =I8/K8 -> 0.12233986 | M8: =F8/C8 -> 40.639797 | N8: 28.680864 | O8: 0.96091716 | P8: 1
A9: BUDGET | B9: 46143 | C9: 16000 | D9: 17187.184 | E9: 14625.414 | F9: 655786.57 | G9: 635000 | H9: 1290786.6 | I9: =F9+G9 -> 1290786.6 | J9: =ROUND(I9-H9,4) -> 0 | K9: 10682880 | L9: =I9/K9 -> 0.12082758 | M9: =F9/C9 -> 40.986661 | N9: 28.940061 | O9: 0.96062775 | P9: 1
A10: BUDGET | B10: 46174 | C10: 16500 | D10: 17724.284 | E10: 15082.458 | F10: 676279.9 | G10: 635000 | H10: 1311279.9 | I10: =F10+G10 -> 1311279.9 | J10: =ROUND(I10-H10,4) -> 0 | K10: 11016720 | L10: =I10/K10 -> 0.11902634 | M10: =F10/C10 -> 40.986661 | N10: 28.940061 | O10: 0.96062775 | P10: 1
A11: BUDGET | B11: 46204 | C11: 17000 | D11: 18273.334 | E11: 15589.319 | F11: 702669.92 | G11: 635000 | H11: 1337669.9 | I11: =F11+G11 -> 1337669.9 | J11: =ROUND(I11-H11,4) -> 0 | K11: 11361168 | L11: =I11/K11 -> 0.11774053 | M11: =F11/C11 -> 41.333525 | N11: 29.197601 | O11: 0.96033871 | P11: 1
A12: BUDGET | B12: 46235 | C12: 16000 | D12: 17198.432 | E12: 14672.3 | F12: 661336.39 | G12: 635000 | H12: 1296336.4 | I12: =F12+G12 -> 1296336.4 | J12: =ROUND(I12-H12,4) -> 0 | K12: 10692864 | L12: =I12/K12 -> 0.12123379 | M12: =F12/C12 -> 41.333525 | N12: 29.197601 | O12: 0.96033871 | P12: 1
A13: BUDGET | B13: 46266 | C13: 16000 | D13: 17208.224 | E13: 14719.854 | F13: 667117.66 | G13: 635000 | H13: 1302117.7 | I13: =F13+G13 -> 1302117.7 | J13: =ROUND(I13-H13,4) -> 0 | K13: 10697856 | L13: =I13/K13 -> 0.12171763 | M13: =F13/C13 -> 41.694854 | N13: 29.455739 | O13: 0.96005475 | P13: 1
A14: BUDGET | B14: 46296 | C14: 18000 | D14: 19384.56 | E14: 16831.983 | F14: 767987.84 | G14: 635000 | H14: 1402987.8 | I14: =F14+G14 -> 1402987.8 | J14: =ROUND(I14-H14,4) -> 0 | K14: 12057552 | L14: =I14/K14 -> 0.1163576 | M14: =F14/C14 -> 42.665991 | N14: 29.962641 | O14: 0.9594785 | P14: 1
A15: BUDGET | B15: 46327 | C15: 22000 | D15: 23736.636 | E15: 20768.69 | F15: 962075.62 | G15: 635000 | H15: 1597075.6 | I15: =F15+G15 -> 1597075.6 | J15: =ROUND(I15-H15,4) -> 0 | K15: 15214468 | L15: =I15/K15 -> 0.10497085 | M15: =F15/C15 -> 43.73071 | N15: 30.713222 | O15: 0.95862152 | P15: 1
A16: BUDGET | B16: 46357 | C16: 26000 | D16: 28068.3 | E16: 24622.864 | F16: 1146477.3 | G16: 635000 | H16: 1781477.3 | I16: =F16+G16 -> 1781477.3 | J16: =ROUND(I16-H16,4) -> 0 | K16: 17989090 | L16: =I16/K16 -> 0.099030986 | M16: =F16/C16 -> 44.095282 | N16: 30.961692 | O16: 0.95833959 | P16: 1
... A24: ACTUAL | B24: 46235 | C24: 20300 | D24: 22879.135 | E24: 20135.839 | F24: 1262887 | G24: 654005 | H24: 1916892 | I24: =F24+G24 -> 1916892 | J24: =ROUND(I24-H24,4) -> 0 | K24: 13571806 | L24: =I24/K24 -> 0.14124075 | M24: =F24/C24 -> 62.211182 | N24: 45.249202 | O24: 0.96397243 | P24: 0.92
A25: FORECAST | B25: 46266 | C25: 17200 | D25: 18931.214 | E25: 16257.293 | F25: 899609.03 | G25: 655592 | H25: 1555201 | I25: =F25+G25 -> 1555201 | J25: =ROUND(I25-H25,4) -> 0 | K25: 11692519 | L25: =I25/K25 -> 0.13300821 | M25: =F25/C25 -> 52.30285 | N25: 37.779526 | O25: 0.96614357
A26: FORECAST | B26: 46296 | C26: 19500 | D26: 21381.867 | E26: 18682.051 | F26: 1011496.4 | G26: 654065 | H26: 1665561.4 | I26: =F26+G26 -> 1665561.4 | J26: =ROUND(I26-H26,4) -> 0 | K26: 13223028 | L26: =I26/K26 -> 0.12595915 | M26: =F26/C26 -> 51.871612 | N26: 37.002753 | O26: 0.96435408
A27: FORECAST | B27: 46327 | C27: 24800 | D27: 27279.702 | E27: 24099.496 | F27: 1280144.4 | G27: 652538 | H27: 1932682.4 | I27: =F27+G27 -> 1932682.4 | J27: =ROUND(I27-H27,4) -> 0 | K27: 16773411 | L27: =I27/K27 -> 0.11522298 | M27: =F27/C27 -> 51.618725 | N27: 36.633309 | O27: 0.9622448
A28: FORECAST | B28: 46357 | C28: 28600 | D28: 31491.117 | E28: 27984.463 | F28: 1455636.8 | G28: 651011 | H28: 2106647.8 | I28: =F28+G28 -> 2106647.8 | J28: =ROUND(I28-H28,4) -> 0 | K28: 19271572 | L28: =I28/K28 -> 0.10931375 | M28: =F28/C28 -> 50.896393 | N28: 35.67267 | O28: 0.96052039
A29: SCENARIO_BASE | B29: 46266 | C29: 17200 | D29: 18931.214 | E29: 16257.293 | F29: 899609.03 | G29: 655592 | H29: 1555201 | I29: =F29+G29 -> 1555201 | J29: =ROUND(I29-H29,4) -> 0 | K29: 11692519 | L29: =I29/K29 -> 0.13300821 | M29: =F29/C29 -> 52.30285 | N29: 37.779526 | O29: 0.96614357
A30: SCENARIO_BASE | B30: 46296 | C30: 19500 | D30: 21381.867 | E30: 18682.051 | F30: 1011496.4 | G30: 654065 | H30: 1665561.4 | I30: =F30+G30 -> 1665561.4 | J30: =ROUND(I30-H30,4) -> 0 | K30: 13223028 | L30: =I30/K30 -> 0.12595915 | M30: =F30/C30 -> 51.871612 | N30: 37.002753 | O30: 0.96435408
A31: SCENARIO_BASE | B31: 46327 | C31: 24800 | D31: 27279.702 | E31: 24099.496 | F31: 1280144.4 | G31: 652538 | H31: 1932682.4 | I31: =F31+G31 -> 1932682.4 | J31: =ROUND(I31-H31,4) -> 0 | K31: 16773411 | L31: =I31/K31 -> 0.11522298 | M31: =F31/C31 -> 51.618725 | N31: 36.633309 | O31: 0.9622448
A32: SCENARIO_BASE | B32: 46357 | C32: 28600 | D32: 31491.117 | E32: 27984.463 | F32: 1455636.8 | G32: 651011 | H32: 2106647.8 | I32: =F32+G32 -> 2106647.8 | J32: =ROUND(I32-H32,4) -> 0 | K32: 19271572 | L32: =I32/K32 -> 0.10931375 | M32: =F32/C32 -> 50.896393 | N32: 35.67267 | O32: 0.96052039
A33: SCENARIO_GROWTH | B33: 46266 | C33: 17784.8 | D33: 19626.659 | E33: 16942.458 | F33: 952142.8 | G33: 655592 | H33: 1607734.8 | I33: =F33+G33 -> 1607734.8 | J33: =ROUND(I33-H33,4) -> 0 | K33: 12099189 | L33: =I33/K33 -> 0.13287955 | M33: =F33/C33 -> 53.536885 | N33: 38.671166 | O33: 0.96596301
A34: SCENARIO_GROWTH | B34: 46296 | C34: 20202 | D34: 22203.207 | E34: 19505.965 | F34: 1071520.7 | G34: 654065 | H34: 1725585.7 | I34: =F34+G34 -> 1725585.7 | J34: =ROUND(I34-H34,4) -> 0 | K34: 13708531 | L34: =I34/K34 -> 0.12587678 | M34: =F34/C34 -> 53.040328 | N34: 37.824215 | O34: 0.96407292
A35: SCENARIO_GROWTH | B35: 46327 | C35: 25767.2 | D35: 28411.326 | E35: 25243.62 | F35: 1359002.9 | G35: 652538 | H35: 2011540.9 | I35: =F35+G35 -> 2011540.9 | J35: =ROUND(I35-H35,4) -> 0 | K35: 17438651 | L35: =I35/K35 -> 0.11534957 | M35: =F35/C35 -> 52.741583 | N35: 37.387047 | O35: 0.96186014
A36: SCENARIO_GROWTH | B36: 46357 | C36: 29744 | D36: 32829.597 | E36: 29346.995 | F36: 1545602.9 | G36: 651011 | H36: 2196613.9 | I36: =F36+G36 -> 2196613.9 | J36: =ROUND(I36-H36,4) -> 0 | K36: 20054068 | L36: =I36/K36 -> 0.10953458 | M36: =F36/C36 -> 51.963517 | N36: 36.36368 | O36: 0.96004743
... A40: SCENARIO_COST_SAVING | B40: 46357 | C40: 28600 | D40: 31051.821 | E40: 27671.131 | F40: 1392017.5 | G40: 651011 | H40: 2043028.5 | I40: =F40+G40 -> 2043028.5 | J40: =ROUND(I40-H40,4) -> 0 | K40: 19271572 | L40: =I40/K40 -> 0.10601255 | M40: =F40/C40 -> 48.67194 | N40: 33.854893 | O40: 0.95842746
A41: LATEST_OUTLOOK | B41: 46023 | C41: 13850 | D41: 14848.32 | E41: 12590.999 | F41: 558784.21 | G41: 634450.25 | H41: 1193234.5 | I41: =F41+G41 -> 1193234.5 | J41: =ROUND(I41-H41,4) -> 0 | K41: 9247852.3 | L41: =I41/K41 -> 0.12902828 | M41: =F41/C41 -> 40.345431 | N41: 28.472184 | O41: 0.96287832 | P41: 1
A42: LATEST_OUTLOOK | B42: 46054 | C42: 13680 | D42: 14684.119 | E42: 12460.642 | F42: 553302.69 | G42: 633896 | H42: 1187198.7 | I42: =F42+G42 -> 1187198.7 | J42: =ROUND(I42-H42,4) -> 0 | K42: 9112571.7 | L42: =I42/K42 -> 0.13028141 | M42: =F42/C42 -> 40.446103 | N42: 28.529652 | O42: 0.9627936 | P42: 1
A43: LATEST_OUTLOOK | B43: 46082 | C43: 15300 | D43: 16461.509 | E43: 14044.333 | F43: 636858.68 | G43: 639364.25 | H43: 1276222.9 | I43: =F43+G43 -> 1276222.9 | J43: =ROUND(I43-H43,4) -> 0 | K43: 10281897 | L43: =I43/K43 -> 0.12412329 | M43: =F43/C43 -> 41.62475 | N43: 29.372571 | O43: 0.96221702 | P43: 1
A44: LATEST_OUTLOOK | B44: 46113 | C44: 15800 | D44: 17013.379 | E44: 14503.772 | F44: 659595.83 | G44: 641828 | H44: 1301423.8 | I44: =F44+G44 -> 1301423.8 | J44: =ROUND(I44-H44,4) -> 0 | K44: 10645866 | L44: =I44/K44 -> 0.12224687 | M44: =F44/C44 -> 41.746572 | N44: 29.437746 | O44: 0.96229861 | P44: 1
A45: LATEST_OUTLOOK | B45: 46143 | C45: 16600 | D45: 17908.737 | E45: 15321.533 | F45: 705747.68 | G45: 645051.88 | H45: 1350799.6 | I45: =F45+G45 -> 1350799.6 | J45: =ROUND(I45-H45,4) -> 0 | K45: 11233018 | L45: =I45/K45 -> 0.12025259 | M45: =F45/C45 -> 42.514921 | N45: 29.972137 | O45: 0.96191462 | P45: 1
A46: LATEST_OUTLOOK | B46: 46174 | C46: 17200 | D46: 18583.615 | E46: 15931.764 | F46: 740538.91 | G46: 647525.75 | H46: 1388064.7 | I46: =F46+G46 -> 1388064.7 | J46: =ROUND(I46-H46,4) -> 0 | K46: 11676307 | L46: =I46/K46 -> 0.11887874 | M46: =F46/C46 -> 43.054588 | N46: 30.3429 | O46: 0.96169686 | P46: 1
A47: LATEST_OUTLOOK | B47: 46204 | C47: 18000 | D47: 19500.043 | E47: 16808.202 | F47: 803530 | G47: 650004.12 | H47: 1453534.1 | I47: =F47+G47 -> 1453534.1 | J47: =ROUND(I47-H47,4) -> 0 | K47: 12268491 | L47: =I47/K47 -> 0.11847701 | M47: =F47/C47 -> 44.640555 | N47: 31.633632 | O47: 0.95769993 | P47: 0.995
A48: LATEST_OUTLOOK | B48: 46235 | C48: 20300 | D48: 22879.135 | E48: 20135.839 | F48: 1262887 | G48: 654005 | H48: 1916892 | I48: =F48+G48 -> 1916892 | J48: =ROUND(I48-H48,4) -> 0 | K48: 13571806 | L48: =I48/K48 -> 0.14124075 | M48: =F48/C48 -> 62.211182 | N48: 45.249202 | O48: 0.96397243 | P48: 0.92
A49: LATEST_OUTLOOK | B49: 46266 | C49: 17200 | D49: 18931.214 | E49: 16257.293 | F49: 899609.03 | G49: 655592 | H49: 1555201 | I49: =F49+G49 -> 1555201 | J49: =ROUND(I49-H49,4) -> 0 | K49: 11692519 | L49: =I49/K49 -> 0.13300821 | M49: =F49/C49 -> 52.30285 | N49: 37.779526 | O49: 0.96614357
A50: LATEST_OUTLOOK | B50: 46296 | C50: 19500 | D50: 21381.867 | E50: 18682.051 | F50: 1011496.4 | G50: 654065 | H50: 1665561.4 | I50: =F50+G50 -> 1665561.4 | J50: =ROUND(I50-H50,4) -> 0 | K50: 13223028 | L50: =I50/K50 -> 0.12595915 | M50: =F50/C50 -> 51.871612 | N50: 37.002753 | O50: 0.96435408
A51: LATEST_OUTLOOK | B51: 46327 | C51: 24800 | D51: 27279.702 | E51: 24099.496 | F51: 1280144.4 | G51: 652538 | H51: 1932682.4 | I51: =F51+G51 -> 1932682.4 | J51: =ROUND(I51-H51,4) -> 0 | K51: 16773411 | L51: =I51/K51 -> 0.11522298 | M51: =F51/C51 -> 51.618725 | N51: 36.633309 | O51: 0.9622448
A52: LATEST_OUTLOOK | B52: 46357 | C52: 28600 | D52: 31491.117 | E52: 27984.463 | F52: 1455636.8 | G52: 651011 | H52: 2106647.8 | I52: =F52+G52 -> 2106647.8 | J52: =ROUND(I52-H52,4) -> 0 | K52: 19271572 | L52: =I52/K52 -> 0.10931375 | M52: =F52/C52 -> 50.896393 | N52: 35.67267 | O52: 0.96052039

Sheet Country_Summary
A1: 目的国管理汇总
A2: 目的国层只展示履约变动成本率；固定成本不分摊到目的国。
A4: Series | B4: Month | C4: Destination | D4: Orders | E4: Packages | F4: Variable Cost CNY | G4: GMV CNY | H4: Variable Cost Rate | I4: Air Package Share | J4: Carrier C Share | K4: On-time Rate | L4: Maturity Rate | M4: Variable Cost/Order | N4: Note
A5: BUDGET | B5: 46023 | C5: DE | D5: 5880 | E5: 6179.292 | F5: 184576.27 | G5: 3760848 | H5: 0.049078365 | I5: 0 | J5: 0 | K5: 0.96935684 | L5: 1 | M5: =F5/D5 -> 31.390522
A6: BUDGET | B6: 46023 | C6: FR | D6: 4480 | E6: 4748.8 | F6: 134148.84 | G6: 3005184 | H6: 0.044639143 | I6: 0 | J6: 0 | K6: 0.9688 | L6: 1 | M6: =F6/D6 -> 29.943937
A7: BUDGET | B7: 46023 | C7: GB | D7: 3640 | E7: 4081.168 | F7: 240519.87 | G7: 2555280 | H7: 0.09412662 | I7: 0.13692472 | J7: 0.028769176 | K7: 0.94109924 | L7: 1 | M7: =F7/D7 -> 66.076887
A8: BUDGET | B8: 46054 | C8: DE | D8: 5670 | E8: 5958.603 | F8: 177984.26 | G8: 3626532 | H8: 0.049078365 | I8: 0 | J8: 0 | K8: 0.96935684 | L8: 1 | M8: =F8/D8 -> 31.390522
A9: BUDGET | B9: 46054 | C9: FR | D9: 4320 | E9: 4579.2 | F9: 129357.81 | G9: 2897856 | H9: 0.044639143 | I9: 0 | J9: 0 | K9: 0.9688 | L9: 1 | M9: =F9/D9 -> 29.943937
A10: BUDGET | B10: 46054 | C10: GB | D10: 3510 | E10: 3935.412 | F10: 231929.87 | G10: 2464020 | H10: 0.09412662 | I10: 0.13692472 | J10: 0.028769176 | K10: 0.94109924 | L10: 1 | M10: =F10/D10 -> 66.076887
A11: BUDGET | B11: 46082 | C11: DE | D11: 6000 | E11: 6305.4 | F11: 188343.13 | G11: 3837600 | H11: 0.049078365 | I11: 0 | J11: 0 | K11: 0.96935684 | L11: 1 | M11: =F11/D11 -> 31.390522
A12: BUDGET | B12: 46082 | C12: FR | D12: 4800 | E12: 5088 | F12: 143730.9 | G12: 3219840 | H12: 0.044639143 | I12: 0 | J12: 0 | K12: 0.9688 | L12: 1 | M12: =F12/D12 -> 29.943937
A13: BUDGET | B13: 46082 | C13: GB | D13: 4200 | E13: 4709.04 | F13: 277522.93 | G13: 2948400 | H13: 0.09412662 | I13: 0.13692472 | J13: 0.028769176 | K13: 0.94109924 | L13: 1 | M13: =F13/D13 -> 66.076887
A14: BUDGET | B14: 46113 | C14: DE | D14: 6200 | E14: 6515.58 | F14: 194621.24 | G14: 3965520 | H14: 0.049078365 | I14: 0 | J14: 0 | K14: 0.96935684 | L14: 1 | M14: =F14/D14 -> 31.390522
A15: BUDGET | B15: 46113 | C15: FR | D15: 4960 | E15: 5257.6 | F15: 148521.93 | G15: 3327168 | H15: 0.044639143 | I15: 0 | J15: 0 | K15: 0.9688 | L15: 1 | M15: =F15/D15 -> 29.943937
A16: BUDGET | B16: 46113 | C16: GB | D16: 4340 | E16: 4866.008 | F16: 286773.69 | G16: 3046680 | H16: 0.09412662 | I16: 0.13692472 | J16: 0.028769176 | K16: 0.94109924 | L16: 1 | M16: =F16/D16 -> 66.076887
... A27: BUDGET | B27: 46235 | C27: FR | D27: 5120 | E27: 5427.2 | F27: 153312.96 | G27: 3434496 | H27: 0.044639143 | I27: 0 | J27: 0 | K27: 0.9688 | L27: 1 | M27: =F27/D27 -> 29.943937
A28: BUDGET | B28: 46235 | C28: GB | D28: 4800 | E28: 5381.76 | F28: 317169.06 | G28: 3369600 | H28: 0.09412662 | I28: 0.13692472 | J28: 0.028769176 | K28: 0.94109924 | L28: 1 | M28: =F28/D28 -> 66.076887 | N28: 核心异常范围
A29: BUDGET | B29: 46266 | C29: DE | D29: 6080 | E29: 6389.472 | F29: 190854.37 | G29: 3888768 | H29: 0.049078365 | I29: 0 | J29: 0 | K29: 0.96935684 | L29: 1 | M29: =F29/D29 -> 31.390522
A30: BUDGET | B30: 46266 | C30: FR | D30: 4960 | E30: 5257.6 | F30: 148521.93 | G30: 3327168 | H30: 0.044639143 | I30: 0 | J30: 0 | K30: 0.9688 | L30: 1 | M30: =F30/D30 -> 29.943937
A31: BUDGET | B31: 46266 | C31: GB | D31: 4960 | E31: 5561.152 | F31: 327741.36 | G31: 3481920 | H31: 0.09412662 | I31: 0.13692472 | J31: 0.028769176 | K31: 0.94109924 | L31: 1 | M31: =F31/D31 -> 66.076887
A32: BUDGET | B32: 46296 | C32: DE | D32: 6480 | E32: 6809.832 | F32: 204528.43 | G32: 4144608 | H32: 0.049348076 | I32: 0 | J32: 0 | K32: 0.96935684 | L32: 1 | M32: =F32/D32 -> 31.563029
A33: BUDGET | B33: 46296 | C33: FR | D33: 5580 | E33: 5914.8 | F33: 168031.41 | G33: 3743064 | H33: 0.044891408 | I33: 0 | J33: 0 | K33: 0.9688 | L33: 1 | M33: =F33/D33 -> 30.113156
A34: BUDGET | B34: 46296 | C34: GB | D34: 5940 | E34: 6659.928 | F34: 395427.99 | G34: 4169880 | H34: 0.094829586 | I34: 0.13692472 | J34: 0.028769176 | K34: 0.94109924 | L34: 1 | M34: =F34/D34 -> 66.570369
A35: BUDGET | B35: 46327 | C35: DE | D35: 7480 | E35: 7860.732 | F35: 236091.46 | G35: 4927734.2 | H35: 0.047910753 | I35: 0 | J35: 0 | K35: 0.96935684 | L35: 1 | M35: =F35/D35 -> 31.563029
A36: BUDGET | B36: 46327 | C36: FR | D36: 6600 | E36: 6996 | F36: 198746.83 | G36: 4560098.4 | H36: 0.043583891 | I36: 0 | J36: 0 | K36: 0.9688 | L36: 1 | M36: =F36/D36 -> 30.113156
A37: BUDGET | B37: 46327 | C37: GB | D37: 7920 | E37: 8879.904 | F37: 527237.33 | G37: 5726635.2 | H37: 0.092067559 | I37: 0.13692472 | J37: 0.028769176 | K37: 0.94109924 | L37: 1 | M37: =F37/D37 -> 66.570369
A38: BUDGET | B38: 46357 | C38: DE | D38: 8840 | E38: 9289.956 | F38: 279017.18 | G38: 5823685.9 | H38: 0.047910753 | I38: 0 | J38: 0 | K38: 0.96935684 | L38: 1 | M38: =F38/D38 -> 31.563029
A39: BUDGET | B39: 46357 | C39: FR | D39: 7540 | E39: 7992.4 | F39: 227053.2 | G39: 5209567 | H39: 0.043583891 | I39: 0 | J39: 0 | K39: 0.9688 | L39: 1 | M39: =F39/D39 -> 30.113156
A40: BUDGET | B40: 46357 | C40: GB | D40: 9620 | E40: 10785.944 | F40: 640406.95 | G40: 6955837.2 | H40: 0.092067559 | I40: 0.13692472 | J40: 0.028769176 | K40: 0.94109924 | L40: 1 | M40: =F40/D40 -> 66.570369
... A63: ACTUAL | B63: 46235 | C63: FR | D63: 5075 | E63: 5379.5 | F63: 157401.05 | G63: 3489950.6 | H63: 0.045101226 | I63: 0 | J63: 0 | K63: 0.9658 | L63: 0.92 | M63: =F63/D63 -> 31.014986
A64: ACTUAL | B64: 46235 | C64: GB | D64: 8932 | E64: 10886.322 | F64: 891643.28 | G64: 5929418.9 | H64: 0.15037617 | I64: 0.66016574 | J64: 0.38838202 | K64: 0.96162083 | L64: 0.92 | M64: =F64/D64 -> 99.825714 | N64: 核心异常范围
A65: FORECAST | B65: 46266 | C65: DE | D65: 6192 | E65: 6507.1728 | F65: 211813.57 | G65: 4070373.1 | H65: 0.052037875 | I65: 0 | J65: 0 | K65: 0.96935684 | M65: =F65/D65 -> 34.207618
A66: FORECAST | B66: 46266 | C66: FR | D66: 5160 | E66: 5469.6 | F66: 162457.77 | G66: 3555446.4 | H66: 0.045692651 | I66: 0 | J66: 0 | K66: 0.9688 | M66: =F66/D66 -> 31.484064
A67: FORECAST | B67: 46266 | C67: GB | D67: 5848 | E67: 6954.4416 | F67: 525337.69 | G67: 4066699.2 | H67: 0.12918037 | I67: 0.54849647 | J67: 0.26898083 | K67: 0.96104771 | M67: =F67/D67 -> 89.832026
A68: FORECAST | B68: 46296 | C68: DE | D68: 6630 | E68: 6967.467 | F68: 226498.42 | G68: 4347291 | H68: 0.052101049 | I68: 0 | J68: 0 | K68: 0.96935684 | M68: =F68/D68 -> 34.162658
A69: FORECAST | B69: 46296 | C69: FR | D69: 5850 | E69: 6201 | F69: 184755.28 | G69: 4020705 | H69: 0.045950965 | I69: 0 | J69: 0 | K69: 0.9688 | M69: =F69/D69 -> 31.582098
A70: FORECAST | B70: 46296 | C70: GB | D70: 7020 | E70: 8213.4 | F70: 600242.73 | G70: 4855032 | H70: 0.12363311 | I70: 0.4624 | J70: 0.192 | K70: 0.9567536 | M70: =F70/D70 -> 85.504662
A71: FORECAST | B71: 46327 | C71: DE | D71: 7936 | E71: 8339.9424 | F71: 264995.49 | G71: 5190461.4 | H71: 0.051054322 | I71: 0 | J71: 0 | K71: 0.96935684 | M71: =F71/D71 -> 33.391569
A72: FORECAST | B72: 46327 | C72: FR | D72: 7192 | E72: 7623.52 | F72: 226563.42 | G72: 4930547.5 | H72: 0.045950965 | I72: 0 | J72: 0 | K72: 0.9688 | M72: =F72/D72 -> 31.502144
A73: FORECAST | B73: 46327 | C73: GB | D73: 9672 | E73: 11316.24 | F73: 788585.47 | G73: 6652401.6 | H73: 0.11854147 | I73: 0.376 | J73: 0.1248 | K73: 0.9525872 | M73: =F73/D73 -> 81.532824
A74: FORECAST | B74: 46357 | C74: DE | D74: 9152 | E74: 9617.8368 | F74: 304347.88 | G74: 5970581.8 | H74: 0.050974577 | I74: 0 | J74: 0 | K74: 0.96935684 | M74: =F74/D74 -> 33.254795
A75: FORECAST | B75: 46357 | C75: FR | D75: 8008 | E75: 8488.48 | F75: 251628.89 | G75: 5476030.6 | H75: 0.045950965 | I75: 0 | J75: 0 | K75: 0.9688 | M75: =F75/D75 -> 31.422189
A76: FORECAST | B76: 46357 | C76: GB | D76: 11440 | E76: 13384.8 | F76: 899660.08 | G76: 7824960 | H76: 0.11497312 | I76: 0.2992 | J76: 0.0768 | K76: 0.94892 | M76: =F76/D76 -> 78.641615
... A112: SCENARIO_COST_SAVING | B112: 46357 | C112: GB | D112: 11440 | E112: 12945.504 | F112: 836040.71 | G112: 7824960 | H112: 0.10684281 | I112: 0.17556734 | J112: 0.038345705 | K112: 0.94350613 | M112: =F112/D112 -> 73.080482
A113: LATEST_OUTLOOK | B113: 46023 | C113: DE | D113: 5830.85 | E113: 6127.6403 | F113: 183473.45 | G113: 3765213.1 | H113: 0.048728571 | I113: 0 | J113: 0 | K113: 0.97035684 | L113: 1 | M113: =F113/D113 -> 31.465987
A114: LATEST_OUTLOOK | B114: 46023 | C114: FR | D114: 4418.15 | E114: 4683.239 | F114: 132624.07 | G114: 2973282.4 | H114: 0.044605271 | I114: 0 | J114: 0 | K114: 0.9698 | L114: 1 | M114: =F114/D114 -> 30.018009
A115: LATEST_OUTLOOK | B115: 46023 | C115: GB | D115: 3601 | E115: 4037.4412 | F115: 242686.69 | G115: 2509356.9 | H115: 0.096712707 | I115: 0.1656939 | J115: 0.038358901 | K115: 0.94349934 | L115: 1 | M115: =F115/D115 -> 67.39425
A116: LATEST_OUTLOOK | B116: 46054 | C116: DE | D116: 5663.52 | E116: 5957.745 | F116: 178232.87 | G116: 3647760 | H116: 0.048860911 | I116: 0 | J116: 0 | K116: 0.97035684 | L116: 1 | M116: =F116/D116 -> 31.470335
A117: LATEST_OUTLOOK | B117: 46054 | C117: FR | D117: 4418.64 | E117: 4688.4422 | F117: 132655.78 | G117: 2965967.9 | H117: 0.044725966 | I117: 0 | J117: 0 | K117: 0.9698 | L117: 1 | M117: =F117/D117 -> 30.021857
A118: LATEST_OUTLOOK | B118: 46054 | C118: GB | D118: 3597.84 | E118: 4037.9321 | F118: 242414.04 | G118: 2498843.8 | H118: 0.097010482 | I118: 0.1656939 | J118: 0.038358901 | K118: 0.94349934 | L118: 1 | M118: =F118/D118 -> 67.37766
A119: LATEST_OUTLOOK | B119: 46082 | C119: DE | D119: 6074.1 | E119: 6396.0382 | F119: 193154.27 | G119: 3942455.3 | H119: 0.048993395 | I119: 0 | J119: 0 | K119: 0.97035684 | L119: 1 | M119: =F119/D119 -> 31.799653
A120: LATEST_OUTLOOK | B120: 46082 | C120: FR | D120: 4880.7 | E120: 5183.8891 | F120: 148059.52 | G120: 3301451.9 | H120: 0.04484679 | I120: 0 | J120: 0 | K120: 0.9698 | L120: 1 | M120: =F120/D120 -> 30.335714
A121: LATEST_OUTLOOK | B121: 46082 | C121: GB | D121: 4345.2 | E121: 4881.5819 | F121: 295644.88 | G121: 3037990 | H121: 0.097315949 | I121: 0.1656939 | J121: 0.038358901 | K121: 0.94349934 | L121: 1 | M121: =F121/D121 -> 68.039419
A122: LATEST_OUTLOOK | B122: 46113 | C122: DE | D122: 6288.4 | E122: 6628.305 | F122: 201023.09 | G122: 4091987.6 | H122: 0.049126025 | I122: 0 | J122: 0 | K122: 0.97035684 | L122: 1 | M122: =F122/D122 -> 31.967287
A123: LATEST_OUTLOOK | B123: 46113 | C123: FR | D123: 5071.8 | E123: 5392.2363 | F123: 154666.18 | G123: 3439491.9 | H123: 0.044967742 | I123: 0 | J123: 0 | K123: 0.9698 | L123: 1 | M123: =F123/D123 -> 30.495324
A124: LATEST_OUTLOOK | B124: 46113 | C124: GB | D124: 4439.8 | E124: 4992.8375 | F124: 303906.56 | G124: 3114386.5 | H124: 0.097581518 | I124: 0.1656939 | J124: 0.038358901 | K124: 0.94349934 | L124: 1 | M124: =F124/D124 -> 68.450508
... A135: LATEST_OUTLOOK | B135: 46235 | C135: FR | D135: 5075 | E135: 5379.5 | F135: 157401.05 | G135: 3489950.6 | H135: 0.045101226 | I135: 0 | J135: 0 | K135: 0.9658 | L135: 0.92 | M135: =F135/D135 -> 31.014986
A136: LATEST_OUTLOOK | B136: 46235 | C136: GB | D136: 8932 | E136: 10886.322 | F136: 891643.28 | G136: 5929418.9 | H136: 0.15037617 | I136: 0.66016574 | J136: 0.38838202 | K136: 0.96162083 | L136: 0.92 | M136: =F136/D136 -> 99.825714 | N136: 核心异常范围
A137: LATEST_OUTLOOK | B137: 46266 | C137: DE | D137: 6192 | E137: 6507.1728 | F137: 211813.57 | G137: 4070373.1 | H137: 0.052037875 | I137: 0 | J137: 0 | K137: 0.96935684 | M137: =F137/D137 -> 34.207618
A138: LATEST_OUTLOOK | B138: 46266 | C138: FR | D138: 5160 | E138: 5469.6 | F138: 162457.77 | G138: 3555446.4 | H138: 0.045692651 | I138: 0 | J138: 0 | K138: 0.9688 | M138: =F138/D138 -> 31.484064
A139: LATEST_OUTLOOK | B139: 46266 | C139: GB | D139: 5848 | E139: 6954.4416 | F139: 525337.69 | G139: 4066699.2 | H139: 0.12918037 | I139: 0.54849647 | J139: 0.26898083 | K139: 0.96104771 | M139: =F139/D139 -> 89.832026
A140: LATEST_OUTLOOK | B140: 46296 | C140: DE | D140: 6630 | E140: 6967.467 | F140: 226498.42 | G140: 4347291 | H140: 0.052101049 | I140: 0 | J140: 0 | K140: 0.96935684 | M140: =F140/D140 -> 34.162658
A141: LATEST_OUTLOOK | B141: 46296 | C141: FR | D141: 5850 | E141: 6201 | F141: 184755.28 | G141: 4020705 | H141: 0.045950965 | I141: 0 | J141: 0 | K141: 0.9688 | M141: =F141/D141 -> 31.582098
A142: LATEST_OUTLOOK | B142: 46296 | C142: GB | D142: 7020 | E142: 8213.4 | F142: 600242.73 | G142: 4855032 | H142: 0.12363311 | I142: 0.4624 | J142: 0.192 | K142: 0.9567536 | M142: =F142/D142 -> 85.504662
A143: LATEST_OUTLOOK | B143: 46327 | C143: DE | D143: 7936 | E143: 8339.9424 | F143: 264995.49 | G143: 5190461.4 | H143: 0.051054322 | I143: 0 | J143: 0 | K143: 0.96935684 | M143: =F143/D143 -> 33.391569
A144: LATEST_OUTLOOK | B144: 46327 | C144: FR | D144: 7192 | E144: 7623.52 | F144: 226563.42 | G144: 4930547.5 | H144: 0.045950965 | I144: 0 | J144: 0 | K144: 0.9688 | M144: =F144/D144 -> 31.502144
A145: LATEST_OUTLOOK | B145: 46327 | C145: GB | D145: 9672 | E145: 11316.24 | F145: 788585.47 | G145: 6652401.6 | H145: 0.11854147 | I145: 0.376 | J145: 0.1248 | K145: 0.9525872 | M145: =F145/D145 -> 81.532824
A146: LATEST_OUTLOOK | B146: 46357 | C146: DE | D146: 9152 | E146: 9617.8368 | F146: 304347.88 | G146: 5970581.8 | H146: 0.050974577 | I146: 0 | J146: 0 | K146: 0.96935684 | M146: =F146/D146 -> 33.254795
A147: LATEST_OUTLOOK | B147: 46357 | C147: FR | D147: 8008 | E147: 8488.48 | F147: 251628.89 | G147: 5476030.6 | H147: 0.045950965 | I147: 0 | J147: 0 | K147: 0.9688 | M147: =F147/D147 -> 31.422189
A148: LATEST_OUTLOOK | B148: 46357 | C148: GB | D148: 11440 | E148: 13384.8 | F148: 899660.08 | G148: 7824960 | H148: 0.11497312 | I148: 0.2992 | J148: 0.0768 | K148: 0.94892 | M148: =F148/D148 -> 78.641615

Sheet Attribution
A1: 五因素归因与 Shapley 参考
A2: 正式口径为量→结构→效率→价→汇率连环替代；ALL 为公司层，国家行由同一原子归因向上汇总。
A4: Comparison | B4: Month | C4: Method | D4: Factor | E4: Destination | F4: High Precision CNY (text) | G4: Report CNY | H4: Shapley Difference | I4: Normalized Sensitivity | J4: Order Sensitive | K4: Comparison | L4: Month | M4: Expected Difference | N4: Chain Total | O4: Chain Delta | P4: Shapley Total | Q4: Shapley Delta | R4: Chain Status | S4: Shapley Status
A5: ACTUAL_VS_BUDGET | B5: 46023 | C5: CHAIN | D5: EFFICIENCY | E5: ALL | F5: 90.505101510096000000000000 | G5: 90.5051 | H5: 0.75935416 | I5: 6.5558364e-05 | J5: =FALSE() -> FALSE | K5: ACTUAL_VS_BUDGET | L5: 46023 | M5: -460.76406 | N5: -460.76406 | O5: 0 | P5: -460.76406 | Q5: 0 | R5: =IF(ABS(O5)<0.0001,"PASS","FAIL") -> PASS | S5: =IF(ABS(Q5)<0.0001,"PASS","FAIL") -> PASS
A6: ACTUAL_VS_BUDGET | B6: 46023 | C6: CHAIN | D6: EFFICIENCY | E6: DE | F6: 32.485012976052000000000000 | G6: 32.485 | K6: ACTUAL_VS_BUDGET | L6: 46054 | M6: 14030.75 | N6: 14030.75 | O6: 0 | P6: 14030.75 | Q6: 0 | R6: =IF(ABS(O6)<0.0001,"PASS","FAIL") -> PASS | S6: =IF(ABS(Q6)<0.0001,"PASS","FAIL") -> PASS
A7: ACTUAL_VS_BUDGET | B7: 46023 | C7: CHAIN | D7: EFFICIENCY | E7: FR | F7: 25.2892096056600000000000 | G7: 25.2892 | K7: ACTUAL_VS_BUDGET | L7: 46082 | M7: 27261.717 | N7: 27261.717 | O7: 0 | P7: 27261.717 | Q7: 0 | R7: =IF(ABS(O7)<0.0001,"PASS","FAIL") -> PASS | S7: =IF(ABS(Q7)<0.0001,"PASS","FAIL") -> PASS
A8: ACTUAL_VS_BUDGET | B8: 46023 | C8: CHAIN | D8: EFFICIENCY | E8: GB | F8: 32.730878928384000000000000 | G8: 32.7309 | K8: ACTUAL_VS_BUDGET | L8: 46113 | M8: 29678.976 | N8: 29678.976 | O8: 0 | P8: 29678.976 | Q8: 0 | R8: =IF(ABS(O8)<0.0001,"PASS","FAIL") -> PASS | S8: =IF(ABS(Q8)<0.0001,"PASS","FAIL") -> PASS
A9: ACTUAL_VS_BUDGET | B9: 46023 | C9: CHAIN | D9: FX | E9: ALL | F9: 80.484203438191218817080000000000 | G9: 80.4842 | H9: 7.6382113 | I9: 0.00065944018 | J9: =FALSE() -> FALSE | K9: ACTUAL_VS_BUDGET | L9: 46143 | M9: 49961.108 | N9: 49961.108 | O9: 0 | P9: 49961.108 | Q9: 0 | R9: =IF(ABS(O9)<0.0001,"PASS","FAIL") -> PASS | S9: =IF(ABS(Q9)<0.0001,"PASS","FAIL") -> PASS
A10: ACTUAL_VS_BUDGET | B10: 46023 | C10: CHAIN | D10: FX | E10: DE | F10: -471.654115793950477197480000000000 | G10: -471.6541 | K10: ACTUAL_VS_BUDGET | L10: 46174 | M10: 64259.011 | N10: 64259.011 | O10: 0 | P10: 64259.011 | Q10: 0 | R10: =IF(ABS(O10)<0.0001,"PASS","FAIL") -> PASS | S10: =IF(ABS(Q10)<0.0001,"PASS","FAIL") -> PASS
A11: ACTUAL_VS_BUDGET | B11: 46023 | C11: CHAIN | D11: FX | E11: FR | F11: -340.9359088698008442744000000000 | G11: -340.9359 | K11: ACTUAL_VS_BUDGET | L11: 46204 | M11: 100860.08 | N11: 100860.08 | O11: 0 | P11: 100860.08 | Q11: 0 | R11: =IF(ABS(O11)<0.0001,"PASS","FAIL") -> PASS | S11: =IF(ABS(Q11)<0.0001,"PASS","FAIL") -> PASS
A12: ACTUAL_VS_BUDGET | B12: 46023 | C12: CHAIN | D12: FX | E12: GB | F12: 893.074228101942540288960000000000 | G12: 893.0742 | K12: ACTUAL_VS_BUDGET | L12: 46235 | M12: 601550.61 | N12: 601550.61 | O12: 0 | P12: 601550.61 | Q12: 0 | R12: =IF(ABS(O12)<0.0001,"PASS","FAIL") -> PASS | S12: =IF(ABS(Q12)<0.0001,"PASS","FAIL") -> PASS
A13: ACTUAL_VS_BUDGET | B13: 46023 | C13: CHAIN | D13: MIX | E13: ALL | F13: 4208.595052119451500000000 | G13: 4208.5951 | H13: 34.900253 | I13: 0.0030130914 | J13: =FALSE() -> FALSE | K13: FORECAST_VS_BUDGET | L13: 46266 | M13: 232491.36 | N13: 232491.36 | O13: 0 | P13: 232491.36 | Q13: 0 | R13: =IF(ABS(O13)<0.0001,"PASS","FAIL") -> PASS | S13: =IF(ABS(Q13)<0.0001,"PASS","FAIL") -> PASS
A14: ACTUAL_VS_BUDGET | B14: 46023 | C14: CHAIN | D14: MIX | E14: DE | F14: 937.690559397138300000000 | G14: 937.6906 | K14: FORECAST_VS_BUDGET | L14: 46296 | M14: 243508.59 | N14: 243508.59 | O14: 0 | P14: 243508.59 | Q14: 0 | R14: =IF(ABS(O14)<0.0001,"PASS","FAIL") -> PASS | S14: =IF(ABS(Q14)<0.0001,"PASS","FAIL") -> PASS
A15: ACTUAL_VS_BUDGET | B15: 46023 | C15: CHAIN | D15: MIX | E15: FR | F15: -40.9060573238460000000 | G15: -40.9061 | K15: FORECAST_VS_BUDGET | L15: 46327 | M15: 318068.76 | N15: 318068.76 | O15: 0 | P15: 318068.76 | Q15: 0 | R15: =IF(ABS(O15)<0.0001,"PASS","FAIL") -> PASS | S15: =IF(ABS(Q15)<0.0001,"PASS","FAIL") -> PASS
A16: ACTUAL_VS_BUDGET | B16: 46023 | C16: CHAIN | D16: MIX | E16: GB | F16: 3311.810550046159200000000 | G16: 3311.8106 | K16: FORECAST_VS_BUDGET | L16: 46357 | M16: 309159.52 | N16: 309159.52 | O16: 0 | P16: 309159.52 | Q16: 0 | R16: =IF(ABS(O16)<0.0001,"PASS","FAIL") -> PASS | S16: =IF(ABS(Q16)<0.0001,"PASS","FAIL") -> PASS
A17: ACTUAL_VS_BUDGET | B17: 46023 | C17: CHAIN | D17: PRICE | E17: ALL | F17: 1151.562072604733763246000000000000 | G17: 1151.5621 | H17: 1.8862903 | I17: 0.00016285169 | J17: =FALSE() -> FALSE | K17: SCENARIO_COST_SAVING_VS_FORECAST | L17: 46266 | M17: 0 | N17: 0 | O17: 0 | P17: 0 | Q17: 0 | R17: =IF(ABS(O17)<0.0001,"PASS","FAIL") -> PASS | S17: =IF(ABS(Q17)<0.0001,"PASS","FAIL") -> PASS
A18: ACTUAL_VS_BUDGET | B18: 46023 | C18: CHAIN | D18: PRICE | E18: DE | F18: 376.262906182295807017200000000000 | G18: 376.2629 | K18: SCENARIO_COST_SAVING_VS_FORECAST | L18: 46296 | M18: -33897.34 | N18: -33897.34 | O18: 0 | P18: -33897.34 | Q18: 0 | R18: =IF(ABS(O18)<0.0001,"PASS","FAIL") -> PASS | S18: =IF(ABS(Q18)<0.0001,"PASS","FAIL") -> PASS
A19: ACTUAL_VS_BUDGET | B19: 46023 | C19: CHAIN | D19: PRICE | E19: FR | F19: 269.0905196765152670160000000000 | G19: 269.0905 | K19: SCENARIO_COST_SAVING_VS_FORECAST | L19: 46327 | M19: -70837.716 | N19: -70837.716 | O19: 0 | P19: -70837.716 | Q19: 0 | R19: =IF(ABS(O19)<0.0001,"PASS","FAIL") -> PASS | S19: =IF(ABS(Q19)<0.0001,"PASS","FAIL") -> PASS
